Workbook

Sheet Forecast
B1: Forecasting Assumptions | D1: 2020 | E1: 2025 | F1: 2030 | G1: 2035 | H1: 2040 | I1: 2045 | J1: 2050 | L1: Assumptions to be considered
A3: Assumptions
A5: Statement of Financial Position
A6: Opening cash and cash equivalents | D6: 4116
A7: Assets not elsewhere classified | D7: =D12-SUM(D50,D8:D9) -> 16685
A8: Property, plant and equipment | D8: 10558
A9: Goodwill and intangible assets | D9: =18942+15999 -> 34941
A10: Non-current liabilities (debt) | B10: Fixed debt to EBITDA ratio | D10: 29412 | E10: =$D10/$D18 -> 2.690204 | F10: =$D10/$D18 -> 2.690204 | G10: =$D10/$D18 -> 2.690204 | H10: =$D10/$D18 -> 2.690204 | I10: =$D10/$D18 -> 2.690204 | J10: =$D10/$D18 -> 2.690204
A11: Shareholders' equity (incl. non-controlling interests) | D11: 17655
A12: Total Balance Sheet | D12: 67659
A14: Income Statement
A15: Revenue | B15: YOY %-change from IAM | D15: 50724 | E15: =(IAM!F15/IAM!E15)^(1/5)-1 -> 0.019831963 | F15: =(IAM!G15/IAM!F15)^(1/5)-1 -> 0.019629726 | G15: =(IAM!H15/IAM!G15)^(1/5)-1 -> 0.016281198 | H15: =(IAM!I15/IAM!H15)^(1/5)-1 -> 0.017078976 | I15: =(IAM!J15/IAM!I15)^(1/5)-1 -> 0.017092973 | J15: =(IAM!K15/IAM!J15)^(1/5)-1 -> 0.015841518
A16: Cost of sales | B16: YOY %-change from IAM | D16: =28684/D15 -> 0.56549168 | E16: =(IAM!F17/IAM!E17)^(1/5)-1 -> 0.019265097 | F16: =(IAM!G17/IAM!F17)^(1/5)-1 -> 0.019227088 | G16: =(IAM!H17/IAM!G17)^(1/5)-1 -> 0.014194481 | H16: =(IAM!I17/IAM!H17)^(1/5)-1 -> 0.015506627 | I16: =(IAM!J17/IAM!I17)^(1/5)-1 -> 0.015677706 | J16: =(IAM!K17/IAM!J17)^(1/5)-1 -> 0.015021935
A17: Operating expenses (Costs of labour) | B17: YOY %-change from IAM | D17: =(1-$D16)-D18/D15 -> 0.21896932 | E17: =(IAM!F20/IAM!E20)^(1/5)-1 -> 0.019238341 | F17: =(IAM!G20/IAM!F20)^(1/5)-1 -> 0.018026024 | G17: =(IAM!H20/IAM!G20)^(1/5)-1 -> 0.013284343 | H17: =(IAM!I20/IAM!H20)^(1/5)-1 -> 0.013156824 | I17: =(IAM!J20/IAM!I20)^(1/5)-1 -> 0.01239681 | J17: =(IAM!K20/IAM!J20)^(1/5)-1 -> 0.010256282
A18: EBITDA (Cash flow from operating activities) | B18: YOY %-change from IAM | D18: 10933 | E18: =(IAM!F21/IAM!E21)^(1/5)-1 -> 0.022560111 | F18: =(IAM!G21/IAM!F21)^(1/5)-1 -> 0.022634755 | G18: =(IAM!H21/IAM!G21)^(1/5)-1 -> 0.026537376 | H18: =(IAM!I21/IAM!H21)^(1/5)-1 -> 0.025765215 | I18: =(IAM!J21/IAM!I21)^(1/5)-1 -> 0.025417199 | J18: =(IAM!K21/IAM!J21)^(1/5)-1 -> 0.022539453
A19: Depreciation rate (incl. amortisation) | B19: Constant rate | D19: =2018/D8 -> 0.19113468 | E19: =$D19 -> 0.19113468 | F19: =$D19 -> 0.19113468 | G19: =$D19 -> 0.19113468 | H19: =$D19 -> 0.19113468 | I19: =$D19 -> 0.19113468 | J19: =$D19 -> 0.19113468
A20: Underlying effective debt interest rate | B20: Constant rate | D20: =624/D10 -> 0.02121583 | E20: =$D20 -> 0.02121583 | F20: =$D20 -> 0.02121583 | G20: =$D20 -> 0.02121583 | H20: =$D20 -> 0.02121583 | I20: =$D20 -> 0.02121583 | J20: =$D20 -> 0.02121583
A21: Underlying effective tax rate on EBT | B21: Constant rate | D21: =1923/SUM(D37,D39:D41) -> 0.24049525 | E21: =$D21 -> 0.24049525 | F21: =$D21 -> 0.24049525 | G21: =$D21 -> 0.24049525 | H21: =$D21 -> 0.24049525 | I21: =$D21 -> 0.24049525 | J21: =$D21 -> 0.24049525
A22: Capital expenditure (on non-financial assets) | B22: Fixed Capex to revenue ratio | D22: =-Actual!$K51/$D15 -> 0.018373945 | E22: =-Actual!$K51/$D15 -> 0.018373945 | F22: =-Actual!$K51/$D15 -> 0.018373945 | G22: =-Actual!$K51/$D15 -> 0.018373945 | H22: =-Actual!$K51/$D15 -> 0.018373945 | I22: =-Actual!$K51/$D15 -> 0.018373945 | J22: =-Actual!$K51/$D15 -> 0.018373945 | L22: To be linked to Inv %-change from IAM
A23: Net change in debt | D23: =SUM(Actual!O45:O46) -> 0
A24: Net change in other liabilities | D24: =SUM(Actual!O44,Actual!O47) -> 1425
A25: Underlying effective dividend rate | D25: =4279/D11 -> 0.2423676 | E25: =D25 -> 0.2423676 | F25: =E25 -> 0.2423676 | G25: =F25 -> 0.2423676 | H25: =G25 -> 0.2423676 | I25: =H25 -> 0.2423676 | J25: =I25 -> 0.2423676
A26: Net change in equity | D26: =SUM(Actual!O51:O52) -> 0
A27: Net change in other equity equivalents | D27: =SUM(Actual!O50,Actual!O54:O55) -> 0
A30: Income Statement | O30: Balanced (2025) | P30: Unbalanced (2025)
A32: Revenue | B32: =B36 -> Share-adjusted YOY %-change from IAM | C32: =C36 -> 2 | D32: =D15 -> 50724 | E32: =E$37*D32*(1+E15)^5/(D32*(1+E15)^5+D33*(1+E16)^5+D36*(1+E17)^5) -> 56135.108 | F32: =F$37*E32*(1+F15)^5/(E32*(1+F15)^5+E33*(1+F16)^5+E36*(1+F17)^5) -> 61978.452 | G32: =G$37*F32*(1+G15)^5/(F32*(1+G15)^5+F33*(1+G16)^5+F36*(1+G17)^5) -> 67901.48 | H32: =H$37*G32*(1+H15)^5/(G32*(1+H15)^5+G33*(1+H16)^5+G36*(1+H17)^5) -> 74396.093 | I32: =I$37*H32*(1+I15)^5/(H32*(1+I15)^5+H33*(1+I16)^5+H36*(1+I17)^5) -> 81392.933 | J32: =J$37*I32*(1+J15)^5/(I32*(1+J15)^5+I33*(1+J16)^5+I36*(1+J17)^5) -> 88207.081 | N32: Share-(un)adjusted YOY %-change from IAM | O32: =O$37*D32*(1+E15)^5/(D32*(1+E15)^5+D33*(1+E16)^5+D36*(1+E17)^5) -> 56135.108 | P32: =D32*(1+E15)^5 -> 55957.279
A33: Cost of sales | B33: =B36 -> Share-adjusted YOY %-change from IAM | C33: =C36 -> 2 | D33: =-$D16*D$32 -> -28684 | E33: =E$37*D33*(1+E16)^5/(D32*(1+E15)^5+D33*(1+E16)^5+D36*(1+E17)^5) -> -31655.812 | F33: =F$37*E33*(1+F16)^5/(E32*(1+F15)^5+E33*(1+F16)^5+E36*(1+F17)^5) -> -34882.047 | G33: =G$37*F33*(1+G16)^5/(F32*(1+G15)^5+F33*(1+G16)^5+F36*(1+G17)^5) -> -37824.852 | H33: =H$37*G33*(1+H16)^5/(G32*(1+H15)^5+G33*(1+H16)^5+G36*(1+H17)^5) -> -41123.356 | I33: =I$37*H33*(1+I16)^5/(H32*(1+I15)^5+H33*(1+I16)^5+H36*(1+I17)^5) -> -44678.794 | J33: =J$37*I33*(1+J16)^5/(I32*(1+J15)^5+I33*(1+J16)^5+I36*(1+J17)^5) -> -48224.257 | N33: Share-(un)adjusted YOY %-change from IAM | O33: =O$37*D33*(1+E16)^5/(D32*(1+E15)^5+D33*(1+E16)^5+D36*(1+E17)^5) -> -31655.812 | P33: =D33*(1+E16)^5 -> -31555.53
A34: Total gross profit | D34: =SUM(D32:D33) -> 22040 | E34: =SUM(E32:E33) -> 24479.297 | F34: =SUM(F32:F33) -> 27096.406 | G34: =SUM(G32:G33) -> 30076.628 | H34: =SUM(H32:H33) -> 33272.737 | I34: =SUM(I32:I33) -> 36714.138 | J34: =SUM(J32:J33) -> 39982.824 | O34: =SUM(O32:O33) -> 24479.297 | P34: =SUM(P32:P33) -> 24401.749
A36: Operating expenses (Costs of labour) | B36: Share-adjusted YOY %-change from IAM | C36: 2 | D36: =-$D17*D$32 -> -11107 | E36: =E37*D36*(1+E17)^5/(D32*(1+E15)^5+D33*(1+E16)^5+D36*(1+E17)^5) -> -12256.134 | F36: =F37*E36*(1+F17)^5/(E32*(1+F15)^5+E33*(1+F16)^5+E36*(1+F17)^5) -> -13425.845 | G36: =G37*F36*(1+G17)^5/(F32*(1+G15)^5+F33*(1+G16)^5+F36*(1+G17)^5) -> -14493.302 | H36: =H37*G36*(1+H17)^5/(G32*(1+H15)^5+G33*(1+H16)^5+G36*(1+H17)^5) -> -15575.723 | I36: =I37*H36*(1+I17)^5/(H32*(1+I15)^5+H33*(1+I16)^5+H36*(1+I17)^5) -> -16650.81 | J36: =J37*I36*(1+J17)^5/(I32*(1+J15)^5+I33*(1+J16)^5+I36*(1+J17)^5) -> -17554.163 | N36: Share-adjusted YOY %-change from IAM | O36: =O37*D36*(1+E17)^5/(D32*(1+E15)^5+D33*(1+E16)^5+D36*(1+E17)^5) -> -12256.134 | P36: =D36*(1+E17)^5 -> -12217.308
A37: EBITDA (Cash flow from operating activities) | B37: YOY %-change from IAM | C37: 1 | D37: =SUM(D34,D36) -> 10933 | E37: =D37*(1+E18)^5 -> 12223.162 | F37: =E37*(1+F18)^5 -> 13670.561 | G37: =F37*(1+G18)^5 -> 15583.326 | H37: =G37*(1+H18)^5 -> 17697.014 | I37: =H37*(1+I18)^5 -> 20063.329 | J37: =I37*(1+J18)^5 -> 22428.661 | N37: YOY %-change from IAM (Total) | O37: =D37*(1+E18)^5 -> 12223.162 | P37: =SUM(P34,P36) -> 12184.441
A39: Depreciation, amortisation and impairment | B39: Geometric rate on net physical assets | C39: 3c | D39: =-D19*D52 -> -2018 | E39: =-E19*E52 -> -1859.6896 | F39: =-F19*F52 -> -1744.0107 | G39: =-G19*G52 -> -1664.3574 | H39: =-H19*H52 -> -1616.634 | I39: =-I19*I52 -> -1597.1978 | J39: =-J19*J52 -> -1600.971 | N39: EBITDA YOY %-change from IAM | O39: =D39*(1+E$18)^5 -> -2256.1366 | P39: =D39*(1+E$18)^5 -> -2256.1366
A40: Interest payments (linked to debt) | B40: =B20 -> Constant rate | C40: 4b | D40: =-D20*D56 -> -624 | E40: =-E20*E56 -> -697.63591 | F40: =-F20*F56 -> -780.24603 | G40: =-G20*G56 -> -889.41695 | H40: =-H20*H56 -> -1010.0555 | I40: =-I20*I56 -> -1145.1127 | J40: =-J20*J56 -> -1280.1138 | N40: EBITDA YOY %-change from IAM | O40: =D40*(1+E$18)^5 -> -697.63591 | P40: =D40*(1+E$18)^5 -> -697.63591
A41: Other income and balance sheet movements | B41: For base year reconciliation only | D41: =-(SUM(Actual!K31:K32,Actual!K36:K43)+D40) -> -295 | N41: EBITDA YOY %-change from IAM | O41: =D41*(1+E$18)^5 -> -329.81185 | P41: =D41*(1+E$18)^5 -> -329.81185
A42: Corporate tax (Capital income tax) | B42: =B21 -> Constant rate | C42: 5 | D42: =-D21*SUM(D37,D39:D41) -> -1923 | E42: =-E21*SUM(E37,E39:E41) -> -2324.5879 | F42: =-F21*SUM(F37,F39:F41) -> -2680.6331 | G42: =-G21*SUM(G37,G39:G41) -> -3133.5453 | H42: =-H21*SUM(H37,H39:H41) -> -3624.3414 | I42: =-I21*SUM(I37,I39:I41) -> -4165.6225 | J42: =-J21*SUM(J37,J39:J41) -> -4701.0992 | N42: EBITDA YOY %-change from IAM | O42: =D42*(1+E$18)^5 -> -2149.926 | P42: =D42*(1+E$18)^5 -> -2149.926
A43: Net income | B43: Closure - Income statement residual | D43: =SUM(D37,D39:D42) -> 6073 | E43: =SUM(E37,E39:E42) -> 7341.2491 | F43: =SUM(F37,F39:F42) -> 8465.6708 | G43: =SUM(G37,G39:G42) -> 9896.0065 | H43: =SUM(H37,H39:H42) -> 11445.983 | I43: =SUM(I37,I39:I42) -> 13155.396 | J43: =SUM(J37,J39:J42) -> 14846.477 | N43: EBITDA YOY %-change from IAM | O43: =D43*(1+E$18)^5 -> 6789.652 | P43: =D43*(1+E$18)^5 -> 6789.652
A45: Income statement check | D45: =SUM(D37,D39:D42)-D43 -> 0 | E45: =SUM(E37,E39:E42)-E43 -> 0 | F45: =SUM(F37,F39:F42)-F43 -> 0 | G45: =SUM(G37,G39:G42)-G43 -> 0 | H45: =SUM(H37,H39:H42)-H43 -> 0 | I45: =SUM(I37,I39:I42)-I43 -> 0 | J45: =SUM(J37,J39:J42)-J43 -> 0 | N45: Total | O45: =SUM(O37,O39:O42)-O43 -> 0 | P45: =SUM(P37,P39:P42)-P43 -> -38.721437
A48: Statement of Financial Position
A50: Cash and equivalents | B50: From cash flow calculation | D50: =D97 -> 5475 | E50: =E97 -> 12836.315 | F50: =F97 -> 21522.005 | G50: =G97 -> 32701.48 | H50: =H97 -> 45804.399 | I50: =I97 -> 61148.352 | J50: =J97 -> 78059.315
A51: Assets not elsewhere classified | B51: No change | D51: =D7 -> 16685 | E51: =D51 -> 16685 | F51: =E51 -> 16685 | G51: =F51 -> 16685 | H51: =G51 -> 16685 | I51: =H51 -> 16685 | J51: =I51 -> 16685
A52: Property, plant and equipment | B52: K(t) = [ I(t) + K(t-1) ] / [1 + δ] | C52: 3b | D52: =D8 -> 10558 | E52: =(D52-E77)/(1+E19) -> 9729.7338 | F52: =(E52-F77)/(1+F19) -> 9124.5118 | G52: =(F52-G77)/(1+G19) -> 8707.7725 | H52: =(G52-H77)/(1+H19) -> 8458.0882 | I52: =(H52-I77)/(1+I19) -> 8356.3997 | J52: =(I52-J77)/(1+J19) -> 8376.1408
A53: Goodwill and intangible assets | B53: No change | D53: =D9 -> 34941 | E53: =D53 -> 34941 | F53: =E53 -> 34941 | G53: =F53 -> 34941 | H53: =G53 -> 34941 | I53: =H53 -> 34941 | J53: =I53 -> 34941
A55: Current liabilities | B55: No change | D55: =D12-SUM(D10:D11) -> 20592 | E55: =D55 -> 20592 | F55: =E55 -> 20592 | G55: =F55 -> 20592 | H55: =G55 -> 20592 | I55: =H55 -> 20592 | J55: =I55 -> 20592
A56: Non-current liabilities (debt) | C56: 4a | D56: =D10 -> 29412 | E56: =E10*E37 -> 32882.8 | F56: =F10*F37 -> 36776.597 | G56: =G10*G37 -> 41922.326 | H56: =H10*H37 -> 47608.578 | I56: =I10*I37 -> 53974.446 | J56: =J10*J37 -> 60337.674
A57: Shareholders' equity | B57: No change | D57: =D11 -> 17655 | E57: =D57 -> 17655 | F57: =E57 -> 17655 | G57: =F57 -> 17655 | H57: =G57 -> 17655 | I57: =H57 -> 17655 | J57: =I57 -> 17655
A58: Retained earnings | B58: RE(t) = RE(t-1) + NI(t) - Div(t) | D58: 0 | E58: =D58+E43-E88 -> 3062.2491 | F58: =E58+F43-F88 -> 7248.9199 | G58: =F58+G43-G88 -> 12865.926 | H58: =G58+H43-H88 -> 20032.91 | I58: =H58+I43-I88 -> 28909.305 | J58: =I58+J43-J88 -> 39476.782
A60: Balance sheet check | D60: =SUM(D50:D53)-SUM(D55:D58) -> 0 | E60: =SUM(E50:E53)-SUM(E55:E58) -> 0 | F60: =SUM(F50:F53)-SUM(F55:F58) -> 0 | G60: =SUM(G50:G53)-SUM(G55:G58) -> 0 | H60: =SUM(H50:H53)-SUM(H55:H58) -> 0 | I60: =SUM(I50:I53)-SUM(I55:I58) -> 0 | J60: =SUM(J50:J53)-SUM(J55:J58) -> 0
A63: Indirect Cash Flow
A65: EBITDA (Cash flow from operating activities) | B65: From income statement | D65: =D37 -> 10933 | E65: =E37 -> 12223.162 | F65: =F37 -> 13670.561 | G65: =G37 -> 15583.326 | H65: =H37 -> 17697.014 | I65: =I37 -> 20063.329 | J65: =J37 -> 22428.661
A66: Depreciation (incl. amortisation) | B66: From income statement | D66: =D39 -> -2018 | E66: =E39 -> -1859.6896 | F66: =F39 -> -1744.0107 | G66: =G39 -> -1664.3574 | H66: =H39 -> -1616.634 | I66: =I39 -> -1597.1978 | J66: =J39 -> -1600.971
A67: Other balance sheet movements | B67: For base year reconciliation only | D67: =-SUM(Actual!K36:K43) -> -612
A68: EBITA (Operating income/profit) | D68: =SUM(D65:D67) -> 8303 | E68: =SUM(E65:E67) -> 10363.473 | F68: =SUM(F65:F67) -> 11926.55 | G68: =SUM(G65:G67) -> 13918.969 | H68: =SUM(H65:H67) -> 16080.38 | I68: =SUM(I65:I67) -> 18466.131 | J68: =SUM(J65:J67) -> 20827.69
A70: Corporate tax on EBT | B70: From income statement | D70: =D42 -> -1923 | E70: =E42 -> -2324.5879 | F70: =F42 -> -2680.6331 | G70: =G42 -> -3133.5453 | H70: =H42 -> -3624.3414 | I70: =I42 -> -4165.6225 | J70: =J42 -> -4701.0992
A71: NOPAT | D71: =SUM(D68,D70) -> 6380 | E71: =SUM(E68,E70) -> 8038.885 | F71: =SUM(F68,F70) -> 9245.9169 | G71: =SUM(G68,G70) -> 10785.423 | H71: =SUM(H68,H70) -> 12456.039 | I71: =SUM(I68,I70) -> 14300.508 | J71: =SUM(J68,J70) -> 16126.591
A73: Depreciation, amortisation and impairment | B73: From income statement | D73: =-D66 -> 2018 | E73: =-E66 -> 1859.6896 | F73: =-F66 -> 1744.0107 | G73: =-G66 -> 1664.3574 | H73: =-H66 -> 1616.634 | I73: =-I66 -> 1597.1978 | J73: =-J66 -> 1600.971
A74: Gross cash flow | D74: =SUM(D71,D73) -> 8398 | E74: =SUM(E71,E73) -> 9898.5746 | F74: =SUM(F71,F73) -> 10989.928 | G74: =SUM(G71,G73) -> 12449.781 | H74: =SUM(H71,H73) -> 14072.673 | I74: =SUM(I71,I73) -> 15897.706 | J74: =SUM(J71,J73) -> 17727.562
A76: Decrease (increase) in working capital | B76: For base year reconciliation only | D76: =SUM(Actual!O21:O22) -> 660
A77: Capital expenditures | C77: 3a | D77: =-D22*D32 -> -932 | E77: =-E22*E32 -> -1031.4234 | F77: =-F22*F32 -> -1138.7887 | G77: =-G22*G32 -> -1247.6181 | H77: =-H22*H32 -> -1366.9497 | I77: =-I22*I32 -> -1495.5093 | J77: =-J22*J32 -> -1620.7121
A78: Other cash movements in invested capital | B78: For base year reconciliation only | D78: =SUM(Actual!O26:O28) -> -455
A79: Free cash flow | D79: =SUM(D74,D76:D78) -> 7671 | E79: =SUM(E74,E76:E78) -> 8867.1512 | F79: =SUM(F74,F76:F78) -> 9851.1389 | G79: =SUM(G74,G76:G78) -> 11202.163 | H79: =SUM(H74,H76:H78) -> 12705.723 | I79: =SUM(I74,I76:I78) -> 14402.197 | J79: =SUM(J74,J76:J78) -> 16106.85
A81: Decrease (increase) in excess cash | B81: Closure - Cash flow residual | D81: =SUM(D85:D90)-D79-D82 -> -1773 | E81: =SUM(E85:E90)-E79-E82 -> -7361.3155 | F81: =SUM(F85:F90)-F79-F82 -> -8685.6893 | G81: =SUM(G85:G90)-G79-G82 -> -11179.475 | H81: =SUM(H85:H90)-H79-H82 -> -13102.919 | I81: =SUM(I85:I90)-I79-I82 -> -15343.953 | J81: =SUM(J85:J90)-J79-J82 -> -16910.964
A82: Other nonoperating cash flows | B82: For base year reconciliation only | D82: =SUM(Actual!O31:O34,Actual!O36:O38) -> 430
A83: Cash flow to investors | D83: =SUM(D79,D81:D82) -> 6328 | E83: =SUM(E79,E81:E82) -> 1505.8357 | F83: =SUM(F79,F81:F82) -> 1165.4496 | G83: =SUM(G79,G81:G82) -> 22.687785 | H83: =SUM(H79,H81:H82) -> -397.19631 | I83: =SUM(I79,I81:I82) -> -941.75586 | J83: =SUM(J79,J81:J82) -> -804.11377
A85: Interest paid | B85: From income statement | D85: =-D40 -> 624 | E85: =-E40 -> 697.63591 | F85: =-F40 -> 780.24603 | G85: =-G40 -> 889.41695 | H85: =-H40 -> 1010.0555 | I85: =-I40 -> 1145.1127 | J85: =-J40 -> 1280.1138
A86: Decrease (increase) in debt | B86: ∆Debt = Debt(t) - Debt(t-1) | D86: =D23 -> 0 | E86: =-(E56-D56) -> -3470.8002 | F86: =-(F56-E56) -> -3893.7965 | G86: =-(G56-F56) -> -5145.7292 | H86: =-(H56-G56) -> -5686.2518 | I86: =-(I56-H56) -> -6365.8685 | J86: =-(J56-I56) -> -6363.2276
A87: Decrease (increase) in other liabilities | B87: Included in debt | D87: =D24 -> 1425
A88: Dividends paid | C88: 6 | D88: =D25*D57 -> 4279 | E88: =E25*E57 -> 4279 | F88: =F25*F57 -> 4279 | G88: =G25*G57 -> 4279 | H88: =H25*H57 -> 4279 | I88: =I25*I57 -> 4279 | J88: =J25*J57 -> 4279
A89: Decrease (increase) in equity | D89: =D26 -> 0
A90: Decrease (increase) in other equity equivalents | D90: =D27 -> 0
A92: Cash flow check | D92: =D83-SUM(D85:D90) -> 0 | E92: =E83-SUM(E85:E90) -> 0 | F92: =F83-SUM(F85:F90) -> 0 | G92: =G83-SUM(G85:G90) -> 0 | H92: =H83-SUM(H85:H90) -> 0 | I92: =I83-SUM(I85:I90) -> 9.094947e-13 | J92: =J83-SUM(J85:J90) -> 9.094947e-13
A94: Opening cash and cash equivalents | B94: OpeningCash(t) = ClosingCash(t-1) | D94: =D6 -> 4116 | E94: =D97 -> 5475 | F94: =E97 -> 12836.315 | G94: =F97 -> 21522.005 | H94: =G97 -> 32701.48 | I94: =H97 -> 45804.399 | J94: =I97 -> 61148.352
A95: Increase (decrease) in cash and cash equivalents | B95: From cash flow residual | D95: =-D81 -> 1773 | E95: =-E81 -> 7361.3155 | F95: =-F81 -> 8685.6893 | G95: =-G81 -> 11179.475 | H95: =-H81 -> 13102.919 | I95: =-I81 -> 15343.953 | J95: =-J81 -> 16910.964
A96: Effect of foreign exchange rate changes | B96: For base year reconciliation only | D96: =Actual!K72 -> -414
A97: Closing cash and cash equivalents | B97: Closure - Total cash | D97: =SUM(D94:D96) -> 5475 | E97: =SUM(E94:E96) -> 12836.315 | F97: =SUM(F94:F96) -> 21522.005 | G97: =SUM(G94:G96) -> 32701.48 | H97: =SUM(H94:H96) -> 45804.399 | I97: =SUM(I94:I96) -> 61148.352 | J97: =SUM(J94:J96) -> 78059.315

Sheet Actual
A1: Income Statement | B1: Costco | C1: Unilever | E1: NOPAT and Its Reconciliation to Net Income | F1: Costco | G1: Unilever | I1: Consolidated Statements of Cash Flows | J1: Costco | K1: Unilever | M1: Free Cash Flow and Cash Flow to Investors | N1: Costco | O1: Unilever
A3: Merchandise sales | B3: 149351 | C3: 50724
A4: Membership fees | B4: 3352
A5: Revenues | B5: =SUM(B3:B4) -> 152703 | C5: =SUM(C3:C4) -> 50724
A7: Merchandise costs | B7: -132886 | C7: -28684
A8: Selling, general, and administrative | B8: -13502 | C8: =-12673-C9 -> -10655
A9: Depreciation | B9: -1492 | C9: -2018
A10: Remaining items | B10: -86 | C10: -1064
A11: Operating income/profit | B11: =SUM(B5:B10) -> 4737 | C11: =SUM(C5:C10) -> 8303 | E11: EBITA, unadjusted | F11: =B11 -> 4737 | G11: =C11 -> 8303
A13: Interest expense | B13: -150 | C13: =-9-728 -> -737 | E13: Operating lease interest | F13: 91
A14: Interest income | B14: 126 | C14: 232 | E14: EBITA, adjusted | F14: =SUM(F11:F13) -> 4828 | G14: =SUM(G11:G13) -> 8303
A15: Other income | B15: 52 | C15: =20+175+3 -> 198
A16: Earnings before taxes | B16: =SUM(B11:B15) -> 4765 | C16: =SUM(C11:C15) -> 7996 | E16: Operating cash taxes | F16: -1009 | G16: -1923
E17: NOPAT | F17: =SUM(F14:F16) -> 3819 | G17: =SUM(G14:G16) -> 6380 | M17: NOPAT | N17: =F17 -> 3819 | O17: =G17 -> 6380
M18: Depreciation | N18: =-B9 -> 1492 | O18: =-C9 -> 2018
E19: Taxes related to nonoperating accounts | F19: 15 | M19: Gross cash flow | N19: =SUM(N17:N18) -> 5311 | O19: =SUM(O17:O18) -> 8398
E20: Other nonoperating taxes | F20: 92
M21: Decrease (increase) in working capital | N21: 449 | O21: 680
E22: Interest expense | F22: =B13 -> -150 | G22: =C13 -> -737 | M22: Other cash movements from operations | O22: =SUM(K30,K37:K38,K43,K46) -> -20
E23: Operating lease interest | F23: =-F13 -> -91 | G23: =-G13 -> 0 | M23: Net cash provided by operating activities | N23: =SUM(N19:N22) -> 5760 | O23: =SUM(O19:O22) -> 9058
E24: Interest income | F24: =B14 -> 126 | G24: =C14 -> 232
E25: Other income | F25: =B15 -> 52 | G25: =C15 -> 198 | M25: Less: Capital expenditures | N25: =J51 -> -2998 | O25: =K51 -> -932
E26: Adjusted net income | F26: =SUM(F17:F25) -> 3863 | G26: =SUM(G17:G25) -> 6073 | M26: Decrease (increase) in capitalized operating leases | N26: 86
M27: Decrease (increase) in other assets, net of liabilities | N27: -173
A28: Provision for income taxes | B28: =SUM(F16,F19:F20,F28) -> -1061 | C28: =SUM(G16,G19:G20,G28) -> -1923 | E28: Operating taxes deferred | F28: -159 | M28: Other cash movements in invested capital | O28: =K54+K67 -> -455
A29: Net income, consolidated | B29: =SUM(B16:B28) -> 3704 | C29: =SUM(C16:C28) -> 6073 | E29: Net income, consolidated | F29: =SUM(F26:F28) -> 3704 | G29: =SUM(G26:G28) -> 6073 | I29: Net income/profit | J29: =F29 -> 3704 | K29: =G29 -> 6073 | M29: Free cash flow | N29: =SUM(N23:N28) -> 2675 | O29: =SUM(O23:O28) -> 7671
I30: Taxation | K30: 1923
A31: Net income, noncontrolling interests | B31: -45 | I31: Other income | K31: =-C15 -> -198 | M31: Interest income | N31: =F24 -> 126 | O31: =G24 -> 232
A32: Net income | B32: =SUM(B29:B31) -> 3659 | C32: =SUM(C29:C31) -> 6073 | I32: Net finance costs | K32: =-SUM(C13:C14) -> 505 | M32: Other income | N32: =F25 -> 52 | O32: =G25 -> 198
I33: Operating income/profit | J33: =SUM(J29:J32) -> 3704 | K33: =SUM(K29:K32) -> 8303 | M33: Taxes related to nonoperating accounts | N33: =F19 -> 15 | O33: =G19 -> 0
M34: Other nonoperating taxes | N34: =F20 -> 92 | O34: =G20 -> 0
I35: Depreciation and amortization | J35: =-B9 -> 1492 | K35: =-C9 -> 2018 | M35: Decrease (increase) in excess cash | N35: -1962 | O35: -1773
I36: Non-cash lease expense | M36: Decrease (increase) in tax credit carryforward | N36: -65
I37: Stock-based compensation | J37: 595 | K37: 108 | M37: Unexplained foreign-currency translation | N37: 60
I38: Other non-cash operating activities, net | J38: 9 | K38: -1 | M38: Other nonoperating cash flows
I39: Deferred income taxes | J39: 147 | M39: Cash flow to investors | N39: =SUM(N29:N37) -> 993 | O39: =SUM(O29:O37) -> 6328
I40: Changes in operating assets and liabilities
I41: Merchandise inventories | J41: -536 | K41: -587 | M41: Reconciliation of cash flow to investors
I42: Accounts payable | J42: 322 | K42: =1125+142 -> 1267
I43: Other operating assets and liabilities, net | J43: 623 | K43: =-182-53+60 -> -175 | M43: Interest expense | N43: =-F22 -> 150 | O43: =-K67 -> 624
I44: Cash flow from operating activities | J44: =SUM(J33:J43) -> 6356 | K44: =SUM(K33:K43) -> 10933 | M44: Operating lease interest | N44: =F13 -> 91 | O44: =G13 -> 0
M45: Decrease (increase) in long-term debt and capital leases | N45: -270
I46: Income tax paid | K46: -1875 | M46: Decrease (increase) in capitalized operating leases | N46: =N26 -> 86 | O46: =O26 -> 0
I47: Net cash provided by operating activities | J47: =SUM(J44:J46) -> 6356 | K47: =SUM(K44:K46) -> 9058 | M47: Net change in other liabilities | O47: =O39-SUM(O43:O46)-O56 -> 1425
M48: Cash flow to debt and debt equivalents | N48: =SUM(N43:N47) -> 57 | O48: =SUM(O43:O47) -> 2049
I49: Purchases of short-term investments | J49: -1094 | K49: -128
I50: Maturities and sales of short-term investments | J50: 1231 | K50: =51+558 -> 609 | M50: Nonoperating deferred income taxes | N50: -50
I51: Additions to property and equipment | J51: -2998 | K51: =-158-863+89 -> -932 | M51: Shares issued for stock-based compensation, net | N51: -326
I52: Acquisitions | K52: =-1426+39 -> -1387 | M52: Repurchases of common stock | N52: =-J64 -> 247 | O52: =-K64 -> 0
I53: Other investing activities, net | J53: -4 | M53: Dividends | N53: 1057 | O53: 4279
I54: Interest received | K54: 169 | M54: Payments to (investments in) noncontrolling interests | N54: 8
I55: Dividends from non-current investments | K55: 188 | M55: Net change in other equity equivalents
I56: Net cash used in investing activities | J56: =SUM(J49:J54) -> -2865 | K56: =SUM(K49:K55) -> -1481 | M56: Cash flow to equity and equity equivalents | N56: =SUM(N50:N54) -> 936 | O56: =SUM(O50:O54) -> 4279
I58: Change in bank payments outstanding | J58: 210 | M58: Cash flow to investors | N58: =SUM(N48,N56) -> 993 | O58: =SUM(O48,O56) -> 6328
I59: Proceeds from short-term borrowings | K59: 722
I60: Proceeds from issuance of long-term debt | J60: 298 | K60: 3117
I61: Repayments of long-term debt | J61: -89 | K61: -3577
I62: Tax withholdings on stock-based awards | J62: -272
I63: Capital element of lease rental payments | K63: -443
I64: Repurchases of common stock | J64: -247
I65: Cash dividend payments | J65: -1038 | K65: -4279
I66: Other financing activities, net | J66: -9 | K66: -720
I67: Interest paid | K67: -624
I68: Net cash used in financing activities | J68: =SUM(J58:J67) -> -1147 | K68: =SUM(K58:K67) -> -5804
I70: Net change in cash and cash equivalents | J70: =SUM(J47,J56,J68) -> 2344 | K70: =SUM(K47,K56,K68) -> 1773
I71: Cash and cash equivalents at the beginning of the year | J71: 6055 | K71: 4116
I72: Effect of foreign exchange rate changes | J72: -15 | K72: -414
I73: Cash and cash equivalents at the end of the year | J73: =SUM(J70:J72) -> 8384 | K73: =SUM(K70:K72) -> 5475

Sheet IAM
A1: (€ million, 2020) | C1: World | D1: The Americas | E1: Europe | F1: Asia/AMET/RUB
A3: Total revenue | C3: =SUM(C4:C6) -> 50724 | D3: 16080 | E3: 11204 | F3: 23440
A4: Beauty & Personal Care (33) | C4: 21124 | D4: =$C4/$C$3*D$3 -> 6696.5129 | E4: =$C4/$C$3*E$3 -> 4665.9036 | F4: =$C4/$C$3*F$3 -> 9761.5835
A5: Home Care (31) | C5: 10460 | D5: =$C5/$C$3*D$3 -> 3315.9215 | E5: =$C5/$C$3*E$3 -> 2310.4219 | F5: =$C5/$C$3*F$3 -> 4833.6567
A6: Foods & Refreshment (22, 25) | C6: 19140 | D6: =$C6/$C$3*D$3 -> 6067.5656 | E6: =$C6/$C$3*E$3 -> 4227.6745 | F6: =$C6/$C$3*F$3 -> 8844.7599
A9: Current Aggregation (Version 3.7) | E9: Based on Updated Coefficients | M9: Based on Qty/Price YOY%
A11: Sector | B11: Chemicals | C11: Firm | E11: Chemicals | F11: Chemicals | G11: Chemicals | H11: Chemicals | I11: Chemicals | J11: Chemicals | K11: Chemicals | M11: Chemicals | N11: Chemicals
B12: (USA, 33) | C12: =C15/B15 -> 0.083092247 | E12: (USA, 33) | F12: (USA, 33) | G12: (USA, 33) | H12: (USA, 33) | I12: (USA, 33) | J12: (USA, 33) | K12: (USA, 33) | M12: (USA, 33) | N12: (USA, 33)
A13: Share | B13: 2014 | C13: 2020 | E13: 2020 | F13: 2025 | G13: 2030 | H13: 2035 | I13: 2040 | J13: 2045 | K13: 2050 | M13: 2020 | N13: 2025
A15: Revenue | B15: ='US SAM'!DF186 -> 610454.06 | C15: =C3 -> 50724 | E15: 621549.69 | F15: 685676 | G15: 755668.62 | H15: 819220.56 | I15: 891608.56 | J15: 970459.69 | K15: 1049801.8 | M15: {=B15*PRODUCT(1+'3.7-1_O20'!I2:N3/100)-1} -> 621263.86 | N15: {=M15*PRODUCT(1+'3.7-1_O20'!O2:S3/100)-1} -> 685137.41
A16: Non-product indirect tax | B16: ='US SAM'!GD403 -> 3975.5 | C16: =C$12*B16 -> 330.33323 | E16: 4047.8125 | F16: 4465.25 | G16: 4920.8125 | H16: 5334.5 | I16: 5805.9375 | J16: 6319.125 | K16: 6836 | M16: =B16+SUM('3.7-1_O20'!I8:N8) -> 4425.3839 | N16: =M16+SUM('3.7-1_O20'!O8:S8) -> 5062.7905
A17: Intermediate demand | B17: =SUM('US SAM'!GD2:GD153,'US SAM'!GD237:GD388) -> 418986.24 | C17: =C$12*B17 -> 34814.508 | E17: 409408.68 | F17: 450394.22 | G17: 495390.41 | H17: 531561.86 | I17: 574073.66 | J17: 620507.76 | K17: 668535.32 | M17: {=B17*PRODUCT(1+'3.7-1_O20'!I4:N5/100)-1} -> 428195.57 | N17: {=M17*PRODUCT(1+'3.7-1_O20'!O4:S5/100)-1} -> 473566.26
A18: Total gross profit | B18: =B15-SUM(B16:B17) -> 187492.32 | C18: =C15-SUM(C16:C17) -> 15579.159 | E18: =E15-SUM(E16:E17) -> 208093.2 | F18: =F15-SUM(F16:F17) -> 230816.53 | G18: =G15-SUM(G16:G17) -> 255357.4 | H18: =H15-SUM(H16:H17) -> 282324.21 | I18: =I15-SUM(I16:I17) -> 311728.97 | J18: =J15-SUM(J16:J17) -> 343632.8 | K18: =K15-SUM(K16:K17) -> 374430.43 | M18: =M15-SUM(M16:M17) -> 188642.91 | N18: =N15-SUM(N16:N17) -> 206508.36
A20: Costs of labour (wages, salaries) | B20: =SUM('US SAM'!GD231:GD232,'US SAM'!GD390:GD391) -> 100827.48 | C20: =C$12*B20 -> 8377.9823 | E20: 101597.08 | F20: 111753.2 | G20: 122195.27 | H20: 130530.21 | I20: 139345.97 | J20: 148200.02 | K20: 155957.42 | M20: {=B20*PRODUCT(1+'3.7-1_O20'!I6:N7/100)-1} -> 101582.51 | N20: {=M20*PRODUCT(1+'3.7-1_O20'!O6:S7/100)-1} -> 111744.69
A21: EBITDA | B21: =B18-B20 -> 86664.84 | C21: =C18-C20 -> 7201.1764 | E21: =E18-E20 -> 106496.12 | F21: =F18-F20 -> 119063.33 | G21: =G18-G20 -> 133162.14 | H21: =H18-H20 -> 151793.99 | I21: =I18-I20 -> 172383 | J21: =J18-J20 -> 195432.78 | K21: =K18-K20 -> 218473.01 | M21: =M18-M20 -> 87060.397 | N21: =N18-N20 -> 94763.664
A23: Return to capital (dep, int & div) | B23: ='US SAM'!GD233 -> 83912.016 | C23: =C$12*B23 -> 6972.438 | E23: 103113.39 | F23: 115281.3 | G23: 128932.03 | H23: 146972.03 | I23: 166907.16 | J23: 189224.73 | K23: 211533.09 | M23: {=B23*PRODUCT(1+'3.7-1_O20'!I9:N10/100)-1} -> 103078.2 | N23: {=M23*PRODUCT(1+'3.7-1_O20'!O9:S10/100)-1} -> 115171.59
A24: Capital income tax | B24: ='US SAM'!GD392 -> 2752.7734 | C24: =C$12*B24 -> 228.73413 | E24: =106496.0703125-E23 -> 3382.6797 | F24: =119063.15625-F23 -> 3781.8516 | G24: =133161.734375-G23 -> 4229.7031 | H24: =151793.515625-H23 -> 4821.4844 | I24: =172382.59375-I23 -> 5475.4375 | J24: =195432.3125-J23 -> 6207.5781 | K24: =218472.55-K23 -> 6939.4562 | M24: =B24+SUM('3.7-1_O20'!I11:N11) -> 3683.5558 | N24: =M24+SUM('3.7-1_O20'!O11:S11) -> 4267.7315
A25: Pure profits | B25: =B21-SUM(B23:B24) -> 0.051221 | C25: =C21-SUM(C23:C24) -> 0.004256068 | E25: =E21-SUM(E23:E24) -> 0.0479955 | F25: =F21-SUM(F23:F24) -> 0.17085 | G25: =G21-SUM(G23:G24) -> 0.402999 | H25: =H21-SUM(H23:H24) -> 0.4788755 | I25: =I21-SUM(I23:I24) -> 0.403398 | J25: =J21-SUM(J23:J24) -> 0.470095 | K25: =K21-SUM(K23:K24) -> 0.455661 | M25: =M21-SUM(M23:M24) -> -19701.358 | N25: =N21-SUM(N23:N24) -> -24675.66
B28: Potential Aggregation
A30: Sector | B30: Dairy | C30: Other Food | D30: Pulp, Paper | E30: Chemicals | F30: Sectors | G30: Firm
B31: (mil, 22) | C31: (ofd, 25) | D31: (ppp, 31) | E31: (chm, 33) | F31: (22, 25, 31, 33)
A32: Share | B32: =C6/SUM($B$34:$C$34) -> 0.0051390898 | C32: =C6/SUM($B$34:$C$34) -> 0.0051390898 | D32: =C5/D34 -> 0.0058431028 | E32: =C4/E34 -> 0.004818213 | G32: =G34/F34 -> 0.0051242897
A34: Revenue | B34: ='World SAM'!CU175 -> 796859.97 | C34: ='World SAM'!CX178 -> 2927534.9 | D34: ='World SAM'!DD184 -> 1790144.8 | E34: ='World SAM'!DF186 -> 4384198.1 | F34: =SUM(B34:E34) -> 9898737.7 | G34: =SUMPRODUCT($B$32:$E$32,B34:E34) -> 50724
A35: Non-product indirect tax | B35: ='World SAM'!FS403 -> 4155.6584 | C35: ='World SAM'!FV403 -> 10476.311 | D35: ='World SAM'!GB403 -> 14434.41 | E35: ='World SAM'!GD403 -> 14506.023 | F35: =SUM(B35:E35) -> 43572.403 | G35: =SUMPRODUCT($B$32:$E$32,B35:E35) -> 229.42986
A36: Intermediate demand | B36: =SUM('World SAM'!FS2:'World SAM'!FS153,'World SAM'!FS237:'World SAM'!FS388) -> 620335.02 | C36: =SUM('World SAM'!FV2:'World SAM'!FV153,'World SAM'!FV237:'World SAM'!FV388) -> 2092735.3 | D36: =SUM('World SAM'!GB2:'World SAM'!GB153,'World SAM'!GB237:'World SAM'!GB388) -> 1170257.3 | E36: =SUM('World SAM'!GD2:'World SAM'!GD153,'World SAM'!GD237:'World SAM'!GD388) -> 3427180.4 | F36: =SUM(B36:E36) -> 7310507.9 | G36: =SUMPRODUCT($B$32:$E$32,B36:E36) -> 37293.53
A37: Total gross profit | B37: =B34-SUM(B35:B36) -> 172369.28 | C37: =C34-SUM(C35:C36) -> 824323.36 | D37: =D34-SUM(D35:D36) -> 605453.12 | E37: =E34-SUM(E35:E36) -> 942511.68 | F37: =F34-SUM(F35:F36) -> 2544657.4 | G37: =G34-SUM(G35:G36) -> 13201.04
A39: Costs of labour (wages, salaries) | B39: =SUM('World SAM'!FS231:FS232,'World SAM'!FS390:FS391) -> 83951.581 | C39: =SUM('World SAM'!FV231:FV232,'World SAM'!FV390:FV391) -> 416251.18 | D39: =SUM('World SAM'!GB231:GB232,'World SAM'!GB390:GB391) -> 351127.62 | E39: =SUM('World SAM'!GD231:GD232,'World SAM'!GD390:GD391) -> 355590.01 | F39: =SUM(B39:E39) -> 1206920.4 | G39: =SUMPRODUCT($B$32:$E$32,B39:E39) -> 6335.5701
A40: EBITDA | B40: =B37-B39 -> 88417.703 | C40: =C37-C39 -> 408072.17 | D40: =D37-D39 -> 254325.5 | E40: =E37-E39 -> 586921.66 | F40: =F37-F39 -> 1337737 | G40: =G37-G39 -> 6865.4697
A42: Return to capital (dep, int & div) | B42: ='World SAM'!FS233 -> 86428.504 | C42: ='World SAM'!FV233 -> 398049.03 | D42: ='World SAM'!GB233 -> 247647.14 | E42: ='World SAM'!GD233 -> 572448.35 | F42: =SUM(B42:E42) -> 1304573 | G42: =SUMPRODUCT($B$32:$E$32,B42:E42) -> 6694.9794
A43: Capital income tax | B43: ='World SAM'!FS392 -> 1989.175 | C43: ='World SAM'!FV392 -> 10023.217 | D43: ='World SAM'!GB392 -> 6678.3712 | E43: ='World SAM'!GD392 -> 14473.161 | F43: =SUM(B43:E43) -> 33163.924 | G43: =SUMPRODUCT($B$32:$E$32,B43:E43) -> 170.48994
A44: Pure profits | B44: =B40-SUM(B42:B43) -> 0.024548 | C44: =C40-SUM(C42:C43) -> -0.078083001 | D44: =D40-SUM(D42:D43) -> -0.015318 | E44: =E40-SUM(E42:E43) -> 0.152802 | F44: =F40-SUM(F42:F43) -> 0.083949003 | G44: =G40-SUM(G42:G43) -> 0.00037160676

Sheet 3.7-1_O20
A1: Variable | B1: Measure | C1: Unit | D1: Style | E1: Region | F1: Sector | G1: Commodity | H1: 2014 | I1: 2015 | J1: 2016 | K1: 2017 | L1: 2018 | M1: 2019 | N1: 2020 | O1: 2021 | P1: 2022 | Q1: 2023 | R1: 2024 | S1: 2025 | T1: 2026 | U1: 2027 | V1: 2028 | W1: 2029 | X1: 2030 | Y1: 2031 | Z1: 2032 | AA1: 2033 | AB1: 2034 | AC1: 2035 | AD1: 2036 | AE1: 2037 | AF1: 2038 | AG1: 2039 | AH1: 2040 | AI1: 2041 | AJ1: 2042 | AK1: 2043 | AL1: 2044 | AM1: 2045 | AN1: 2046 | AO1: 2047 | AP1: 2048 | AQ1: 2049 | AR1: 2050
A2: Output | B2: Quantity | C2: Mill$ | D2: YOY% | E2: US | F2: Chemicals | G2: _Macro | I2: -0.16822109 | J2: 2.3741691 | K2: 2.5660856 | L2: 2.6936049 | M2: 2.76545 | N2: 2.7889814 | O2: 3.2386124 | P2: 3.1698079 | Q2: 3.0827944 | R2: 2.985213 | S2: 2.8826036 | T2: 2.7805359 | U2: 2.688 | V2: 2.6058736 | W2: 2.5329678 | X2: 2.4682093 | Y2: 2.0274742 | Z2: 1.9976623 | AA2: 1.9813111 | AB2: 1.9777035 | AC2: 1.9857428 | AD2: 2.0021255 | AE2: 2.0190053 | AF2: 2.0339119 | AG2: 2.0463281 | AH2: 2.0557845 | AI2: 2.0275865 | AJ2: 2.0293005 | AK2: 2.0270565 | AL2: 2.0220995 | AM2: 2.0153718 | AN2: 2.0069458 | AO2: 1.9942038 | AP2: 1.9767956 | AQ2: 1.9550815 | AR2: 1.9293698
A3: Output | B3: Price | C3: Unit$ | D3: YOY% | E3: US | F3: Chemicals | G3: _Macro | I3: -2.1297328 | J3: -1.6948423 | K3: -1.7972566 | L3: -1.8303581 | M3: -1.8054156 | N3: -1.7328657 | O3: -1.2925636 | P3: -1.1644435 | Q3: -1.0488744 | R3: -0.94688505 | S3: -0.8591857 | T3: -0.78370583 | U3: -0.71104223 | V3: -0.6386528 | W3: -0.56632078 | X3: -0.4938601 | Y3: -0.42966148 | Z3: -0.37875584 | AA3: -0.34498531 | AB3: -0.32628953 | AC3: -0.32086363 | AD3: -0.32446191 | AE3: -0.32597524 | AF3: -0.32283494 | AG3: -0.31523392 | AH3: -0.30334631 | AI3: -0.3117083 | AJ3: -0.30383125 | AK3: -0.30281314 | AL3: -0.30900103 | AM3: -0.32257187 | AN3: -0.34231937 | AO3: -0.36293763 | AP3: -0.38299552 | AQ3: -0.40239328 | AR3: -0.4210313
A4: IntermDem | B4: Quantity | C4: Mill$ | D4: YOY% | E4: US | F4: Chemicals | G4: _Macro | I4: -0.16822109 | J4: 2.3741691 | K4: 2.5660856 | L4: 2.6936049 | M4: 2.76545 | N4: 2.7889814 | O4: 3.2385066 | P4: 3.1694698 | Q4: 3.0821185 | R4: 2.9841123 | S4: 2.8810039 | T4: 2.7783699 | U4: 2.6851947 | V4: 2.60236 | W4: 2.5286853 | X4: 2.4631066 | Y4: 2.0203962 | Z4: 1.9893497 | AA4: 1.9716814 | AB4: 1.9666719 | AC4: 1.9732237 | AD4: 1.9880383 | AE4: 2.0032966 | AF4: 2.0165467 | AG4: 2.0272846 | AH4: 2.0350547 | AI4: 2.0050402 | AJ4: 2.0049684 | AK4: 2.0008314 | AL4: 1.9938594 | AM4: 1.9849814 | AN4: 1.9743032 | AO4: 1.9594046 | AP4: 1.9400014 | AQ4: 1.916471 | AR4: 1.8891373
A5: IntermDem | B5: Price | C5: Unit$ | D5: YOY% | E5: US | F5: Chemicals | G5: _Macro | I5: -1.8555071 | J5: -1.6993947 | K5: -1.7872914 | L5: -1.8043072 | M5: -1.762056 | N5: -1.6709512 | O5: -1.2609761 | P5: -1.1186527 | Q5: -0.99041557 | R5: -0.87706178 | S5: -0.77908641 | T5: -0.69412762 | U5: -0.61224449 | V5: -0.53087991 | W5: -0.44994467 | X5: -0.3693752 | Y5: -0.27305788 | Z5: -0.21007466 | AA5: -0.16449912 | AB5: -0.13418414 | AC5: -0.11727148 | AD5: -0.1095717 | AE5: -0.10031538 | AF5: -0.087081932 | AG5: -0.070130669 | AH5: -0.049691271 | AI5: -0.048778933 | AJ5: -0.032757599 | AK5: -0.023141367 | AL5: -0.020205628 | AM5: -0.024062308 | AN5: -0.033901457 | AO5: -0.046239767 | AP5: -0.060051862 | AQ5: -0.075174846 | AR5: -0.091439433
A6: EndowSupp | B6: Quantity | C6: Mill$ | D6: YOY% | E6: US | F6: Chemicals | G6: Labour | I6: -4.5269518 | J6: -0.086146176 | K6: 0.080191471 | L6: 0.21651857 | M6: 0.32936695 | N6: 0.42296779 | O6: 1.4073347 | P6: 1.4213061 | Q6: 1.37924 | R6: 1.2919635 | S6: 1.1673591 | T6: 1.0243573 | U6: 0.9188447 | V6: 0.86303794 | W6: 0.85574079 | X6: 0.89584494 | Y6: 0.37893942 | Z6: 0.44235235 | AA6: 0.48673329 | AB6: 0.5117057 | AC6: 0.51668036 | AD6: 0.50589973 | AE6: 0.50031167 | AF6: 0.50464833 | AG6: 0.51843971 | AH6: 0.54125893 | AI6: 0.52255058 | AJ6: 0.52630788 | AK6: 0.50395876 | AL6: 0.45698392 | AM6: 0.38646242 | AN6: 0.29896888 | AO6: 0.21749851 | AP6: 0.14802518 | AQ6: 0.090864949 | AR6: 0.046315607
A7: EndowSupp | B7: Price | C7: Unit$ | D7: YOY% | E7: US | F7: Chemicals | G7: Labour | I7: 1.5398968 | J7: 0.74863023 | K7: 0.63491195 | L7: 0.55426216 | M7: 0.49892449 | N7: 0.46222338 | O7: 0.48970559 | P7: 0.51245004 | Q7: 0.56211793 | R7: 0.63363546 | S7: 0.72327763 | T7: 0.81991404 | U7: 0.88831186 | V7: 0.92041063 | W7: 0.91670179 | X7: 0.87773991 | Y7: 0.94320571 | Z7: 0.88586205 | AA7: 0.84255654 | AB7: 0.81473494 | AC7: 0.80349714 | AD7: 0.80606079 | AE7: 0.80736125 | AF7: 0.80353439 | AG7: 0.79445684 | AH7: 0.78001601 | AI7: 0.74697423 | AJ7: 0.73972285 | AK7: 0.74533218 | AL7: 0.76307589 | AM7: 0.79251611 | AN7: 0.82947719 | AO7: 0.85852492 | AP7: 0.87586832 | AQ7: 0.88152933 | AR7: 0.8755098
A8: Output | B8: RealTaxRev | C8: Mill$ | D8: YOY | E8: US | F8: Chemicals | G8: _Macro | I8: -51.223572 | J8: 89.879623 | K8: 97.507492 | L8: 102.51268 | M8: 105.24519 | N8: 105.96253 | O8: 131.80357 | P8: 130.33311 | Q8: 128.04567 | R8: 125.20867 | S8: 122.01554 | T8: 118.6935 | U8: 115.68843 | V8: 113.09103 | W8: 110.89098 | X8: 109.07887 | Y8: 83.310608 | Z8: 82.003792 | AA8: 81.369698 | AB8: 81.388557 | AC8: 82.022278 | AD8: 83.127304 | AE8: 84.347916 | AF8: 85.573334 | AG8: 86.781845 | AH8: 87.947502 | AI8: 86.667183 | AJ8: 87.32518 | AK8: 87.645164 | AL8: 87.670761 | AM8: 87.434433 | AN8: 86.979401 | AO8: 86.385071 | AP8: 85.682854 | AQ8: 84.884529 | AR8: 83.999611
A9: FirmDem | B9: Quantity | C9: Mill$ | D9: YOY% | E9: US | F9: Chemicals | G9: Capital | I9: 5.8179483 | J9: 3.7031987 | K9: 3.8953209 | L9: 4.041544 | M9: 4.145401 | N9: 4.2084813 | O9: 3.9451838 | P9: 3.94153 | Q9: 3.9013016 | R9: 3.837409 | S9: 3.7593584 | T9: 3.6777048 | U9: 3.6109104 | V9: 3.5606811 | W9: 3.5242658 | X9: 3.4991868 | Y9: 3.6344719 | Z9: 3.6097131 | AA9: 3.5837379 | AB9: 3.5576379 | AC9: 3.5318732 | AD9: 3.5063348 | AE9: 3.481195 | AF9: 3.4558151 | AG9: 3.4295704 | AH9: 3.4018986 | AI9: 3.4110026 | AJ9: 3.3647838 | AK9: 3.3084118 | AL9: 3.2436957 | AM9: 3.1721022 | AN9: 3.0954196 | AO9: 3.0164225 | AP9: 2.9363103 | AQ9: 2.8556628 | AR9: 2.7749305
A10: FirmDem | B10: Price | C10: Unit$ | D10: YOY% | E10: US | F10: Chemicals | G10: Capital | I10: 1.1407044 | J10: -0.83042634 | K10: -1.046042 | L10: -1.2049221 | M10: -1.3161957 | N10: -1.3877952 | O10: -1.6655661 | P10: -1.6373426 | Q10: -1.5863498 | R10: -1.5217603 | S10: -1.4503137 | T10: -1.3787453 | U10: -1.3169303 | V10: -1.2656505 | W10: -1.2233979 | X10: -1.1887885 | Y10: -0.92295355 | Z10: -0.90968895 | AA10: -0.9010092 | AB10: -0.89515728 | AC10: -0.89067507 | AD10: -0.8853398 | AE10: -0.87524819 | AF10: -0.8597911 | AG10: -0.83939409 | AH10: -0.8144834 | AI10: -0.78406715 | AJ10: -0.75787431 | AK10: -0.73490685 | AL10: -0.71589953 | AM10: -0.70126802 | AN10: -0.69025087 | AO10: -0.67885143 | AP10: -0.66656011 | AQ10: -0.6538893 | AR10: -0.64127064
A11: FirmDem | B11: RealTaxRev | C11: Mill$ | D11: YOY | E11: US | F11: Chemicals | G11: Capital | I11: 222.82092 | J11: 133.86298 | K11: 139.61432 | L11: 143.44681 | M11: 145.43802 | N11: 145.59932 | O11: 120.89893 | P11: 118.91563 | Q11: 116.80743 | R11: 114.73415 | S11: 112.81957 | T11: 111.13781 | U11: 109.68672 | V11: 108.43603 | W11: 107.35831 | X11: 106.42702 | Y11: 117.91558 | Z11: 117.33562 | AA11: 117.17924 | AB11: 117.50271 | AC11: 118.34003 | AD11: 119.63042 | AE11: 121.09834 | AF11: 122.64648 | AG11: 124.24654 | AH11: 125.86703 | AI11: 130.63899 | AJ11: 131.63864 | AK11: 132.10448 | AL11: 132.05911 | AM11: 131.52216 | AN11: 130.58998 | AO11: 129.58502 | AP11: 128.59009 | AQ11: 127.60687 | AR11: 126.63287

Sheet US SAM
A1: ASAM | B1: 1 m_pdr | C1: 2 m_wht | D1: 3 m_gro | E1: 4 m_v_f | F1: 5 m_osd | G1: 6 m_c_b | H1: 7 m_pfb | I1: 8 m_ocr | J1: 9 m_ctl | K1: 10 m_oap | L1: 11 m_rmk | M1: 12 m_wol | N1: 13 m_frs | O1: 14 m_fsh | P1: 15 m_coa | Q1: 16 m_oil | R1: 17 m_gas | S1: 18 m_oxt | T1: 19 m_cmt | U1: 20 m_omt | V1: 21 m_vol | W1: 22 m_mil | X1: 23 m_pcr | Y1: 24 m_sgr | Z1: 25 m_ofd | AA1: 26 m_b_t | AB1: 27 m_tex | AC1: 28 m_wap | AD1: 29 m_lea | AE1: 30 m_lum | AF1: 31 m_ppp | AG1: 32 m_p_c | AH1: 33 m_chm | AI1: 34 m_bph | AJ1: 35 m_rpp | AK1: 36 m_nmm | AL1: 37 m_i_s | AM1: 38 m_nfm | AN1: 39 m_fmp | AO1: 40 m_ele | AP1: 41 m_eeq | AQ1: 42 m_ome | AR1: 43 m_mvh | AS1: 44 m_otn | AT1: 45 m_omf | AU1: 46 m_TnD | AV1: 47 m_NuclearBL | AW1: 48 m_CoalBL | AX1: 49 m_GasBL | AY1: 50 m_WindBL | AZ1: 51 m_HydroBL | BA1: 52 m_OilBL | BB1: 53 m_OtherBL | BC1: 54 m_GasP | BD1: 55 m_HydroP | BE1: 56 m_OilP | BF1: 57 m_SolarP | BG1: 58 m_gdt | BH1: 59 m_wtr | BI1: 60 m_cns | BJ1: 61 m_trd | BK1: 62 m_afs | BL1: 63 m_otp | BM1: 64 m_wtp | BN1: 65 m_atp | BO1: 66 m_whs | BP1: 67 m_cmn | BQ1: 68 m_ofi | BR1: 69 m_ins | BS1: 70 m_rsa | BT1: 71 m_obs | BU1: 72 m_ros | BV1: 73 m_osg | BW1: 74 m_edu | BX1: 75 m_hht | BY1: 76 m_dwe | BZ1: 77 d_pdr | CA1: 78 d_wht | CB1: 79 d_gro | CC1: 80 d_v_f | CD1: 81 d_osd | CE1: 82 d_c_b | CF1: 83 d_pfb | CG1: 84 d_ocr | CH1: 85 d_ctl | CI1: 86 d_oap | CJ1: 87 d_rmk | CK1: 88 d_wol | CL1: 89 d_frs | CM1: 90 d_fsh | CN1: 91 d_coa | CO1: 92 d_oil | CP1: 93 d_gas | CQ1: 94 d_oxt | CR1: 95 d_cmt | CS1: 96 d_omt | CT1: 97 d_vol | CU1: 98 d_mil | CV1: 99 d_pcr | CW1: 100 d_sgr | CX1: 101 d_ofd | CY1: 102 d_b_t | CZ1: 103 d_tex | DA1: 104 d_wap | DB1: 105 d_lea | DC1: 106 d_lum | DD1: 107 d_ppp | DE1: 108 d_p_c | DF1: 109 d_chm | DG1: 110 d_bph | DH1: 111 d_rpp | DI1: 112 d_nmm | DJ1: 113 d_i_s | DK1: 114 d_nfm | DL1: 115 d_fmp | DM1: 116 d_ele | DN1: 117 d_eeq | DO1: 118 d_ome | DP1: 119 d_mvh | DQ1: 120 d_otn | DR1: 121 d_omf | DS1: 122 d_TnD | DT1: 123 d_NuclearBL | DU1: 124 d_CoalBL | DV1: 125 d_GasBL | DW1: 126 d_WindBL | DX1: 127 d_HydroBL | DY1: 128 d_OilBL | DZ1: 129 d_OtherBL | EA1: 130 d_GasP | EB1: 131 d_HydroP | EC1: 132 d_OilP | ED1: 133 d_SolarP | EE1: 134 d_gdt | EF1: 135 d_wtr | EG1: 136 d_cns | EH1: 137 d_trd | EI1: 138 d_afs | EJ1: 139 d_otp | EK1: 140 d_wtp | EL1: 141 d_atp | EM1: 142 d_whs | EN1: 143 d_cmn | EO1: 144 d_ofi | EP1: 145 d_ins | EQ1: 146 d_rsa | ER1: 147 d_obs | ES1: 148 d_ros | ET1: 149 d_osg | EU1: 150 d_edu | EV1: 151 d_hht | EW1: 152 d_dwe | EX1: 153 a_pdr | EY1: 154 a_wht | EZ1: 155 a_gro | FA1: 156 a_v_f | FB1: 157 a_osd | FC1: 158 a_c_b | FD1: 159 a_pfb | FE1: 160 a_ocr | FF1: 161 a_ctl | FG1: 162 a_oap | FH1: 163 a_rmk | FI1: 164 a_wol | FJ1: 165 a_frs | FK1: 166 a_fsh | FL1: 167 a_coa | FM1: 168 a_oil | FN1: 169 a_gas | FO1: 170 a_oxt | FP1: 171 a_cmt | FQ1: 172 a_omt | FR1: 173 a_vol | FS1: 174 a_mil | FT1: 175 a_pcr | FU1: 176 a_sgr | FV1: 177 a_ofd | FW1: 178 a_b_t | FX1: 179 a_tex | FY1: 180 a_wap | FZ1: 181 a_lea | GA1: 182 a_lum | GB1: 183 a_ppp | GC1: 184 a_p_c | GD1: 185 a_chm | GE1: 186 a_bph | GF1: 187 a_rpp | GG1: 188 a_nmm | GH1: 189 a_i_s | GI1: 190 a_nfm | GJ1: 191 a_fmp | GK1: 192 a_ele | GL1: 193 a_eeq | GM1: 194 a_ome | GN1: 195 a_mvh | GO1: 196 a_otn | GP1: 197 a_omf | GQ1: 198 a_TnD | GR1: 199 a_NuclearBL | GS1: 200 a_CoalBL | GT1: 201 a_GasBL | GU1: 202 a_WindBL | GV1: 203 a_HydroBL | GW1: 204 a_OilBL | GX1: 205 a_OtherBL | GY1: 206 a_GasP | GZ1: 207 a_HydroP | HA1: 208 a_OilP | HB1: 209 a_SolarP | HC1: 210 a_gdt | HD1: 211 a_wtr | HE1: 212 a_cns | HF1: 213 a_trd | HG1: 214 a_afs | HH1: 215 a_otp | HI1: 216 a_wtp | HJ1: 217 a_atp | HK1: 218 a_whs | HL1: 219 a_cmn | HM1: 220 a_ofi | HN1: 221 a_ins | HO1: 222 a_rsa | HP1: 223 a_obs | HQ1: 224 a_ros | HR1: 225 a_osg | HS1: 226 a_edu | HT1: 227 a_hht | HU1: 228 a_dwe | HV1: 229 Land | HW1: 230 UnSklab | HX1: 231 SKlab | HY1: 232 Capital | HZ1: 233 NatlRes | IA1: 234 tmm_world | IB1: 235 tee_world | IC1: 236 tssm_T1pdr | ID1: 237 tssm_T2wht | IE1: 238 tssm_T3gro | IF1: 239 tssm_T4v_f | IG1: 240 tssm_T5osd | IH1: 241 tssm_T6c_b | II1: 242 tssm_T7pfb | IJ1: 243 tssm_T8ocr | IK1: 244 tssm_T9ctl | IL1: 245 tssm_T10oap | IM1: 246 tssm_T11rmk | IN1: 247 tssm_T12wol | IO1: 248 tssm_T13frs | IP1: 249 tssm_T14fsh | IQ1: 250 tssm_T15coa | IR1: 251 tssm_T16oil | IS1: 252 tssm_T17gas | IT1: 253 tssm_T18oxt | IU1: 254 tssm_T19cmt | IV1: 255 tssm_T20omt | IW1: 256 tssm_T21vol | IX1: 257 tssm_T22mil | IY1: 258 tssm_T23pcr | IZ1: 259 tssm_T24sgr | JA1: 260 tssm_T25ofd | JB1: 261 tssm_T26b_t | JC1: 262 tssm_T27tex | JD1: 263 tssm_T28wap | JE1: 264 tssm_T29lea | JF1: 265 tssm_T30lum | JG1: 266 tssm_T31ppp | JH1: 267 tssm_T32p_c | JI1: 268 tssm_T33chm | JJ1: 269 tssm_T34bph | JK1: 270 tssm_T35rpp | JL1: 271 tssm_T36nmm | JM1: 272 tssm_T37i_s | JN1: 273 tssm_T38nfm | JO1: 274 tssm_T39fmp | JP1: 275 tssm_T40ele | JQ1: 276 tssm_T41eeq | JR1: 277 tssm_T42ome | JS1: 278 tssm_T43mvh | JT1: 279 tssm_T44otn | JU1: 280 tssm_T45omf | JV1: 281 tssm_T46TnD | JW1: 282 tssm_T47Nucl | JX1: 283 tssm_T48Coal | JY1: 284 tssm_T49GasB | JZ1: 285 tssm_T50Wind | KA1: 286 tssm_T51Hydr | KB1: 287 tssm_T52OilB | KC1: 288 tssm_T53Othe | KD1: 289 tssm_T54GasP | KE1: 290 tssm_T55Hydr | KF1: 291 tssm_T56OilP | KG1: 292 tssm_T57Sola | KH1: 293 tssm_T58gdt | KI1: 294 tssm_T59wtr | KJ1: 295 tssm_T60cns | KK1: 296 tssm_T61trd | KL1: 297 tssm_T62afs | KM1: 298 tssm_T63otp | KN1: 299 tssm_T64wtp | KO1: 300 tssm_T65atp | KP1: 301 tssm_T66whs | KQ1: 302 tssm_T67cmn | KR1: 303 tssm_T68ofi | KS1: 304 tssm_T69ins | KT1: 305 tssm_T70rsa | KU1: 306 tssm_T71obs | KV1: 307 tssm_T72ros | KW1: 308 tssm_T73osg | KX1: 309 tssm_T74edu | KY1: 310 tssm_T75hht | KZ1: 311 tssm_T76dwe | LA1: 312 tssd_T1pdr | LB1: 313 tssd_T2wht | LC1: 314 tssd_T3gro | LD1: 315 tssd_T4v_f | LE1: 316 tssd_T5osd | LF1: 317 tssd_T6c_b | LG1: 318 tssd_T7pfb | LH1: 319 tssd_T8ocr | LI1: 320 tssd_T9ctl | LJ1: 321 tssd_T10oap | LK1: 322 tssd_T11rmk | LL1: 323 tssd_T12wol | LM1: 324 tssd_T13frs | LN1: 325 tssd_T14fsh | LO1: 326 tssd_T15coa | LP1: 327 tssd_T16oil | LQ1: 328 tssd_T17gas | LR1: 329 tssd_T18oxt | LS1: 330 tssd_T19cmt | LT1: 331 tssd_T20omt | LU1: 332 tssd_T21vol | LV1: 333 tssd_T22mil | LW1: 334 tssd_T23pcr | LX1: 335 tssd_T24sgr | LY1: 336 tssd_T25ofd | LZ1: 337 tssd_T26b_t | MA1: 338 tssd_T27tex | MB1: 339 tssd_T28wap | MC1: 340 tssd_T29lea | MD1: 341 tssd_T30lum | ME1: 342 tssd_T31ppp | MF1: 343 tssd_T32p_c | MG1: 344 tssd_T33chm | MH1: 345 tssd_T34bph | MI1: 346 tssd_T35rpp | MJ1: 347 tssd_T36nmm | MK1: 348 tssd_T37i_s | ML1: 349 tssd_T38nfm | MM1: 350 tssd_T39fmp | MN1: 351 tssd_T40ele | MO1: 352 tssd_T41eeq | MP1: 353 tssd_T42ome | MQ1: 354 tssd_T43mvh | MR1: 355 tssd_T44otn | MS1: 356 tssd_T45omf | MT1: 357 tssd_T46TnD | MU1: 358 tssd_T47Nucl | MV1: 359 tssd_T48Coal | MW1: 360 tssd_T49GasB | MX1: 361 tssd_T50Wind | MY1: 362 tssd_T51Hydr | MZ1: 363 tssd_T52OilB | NA1: 364 tssd_T53Othe | NB1: 365 tssd_T54GasP | NC1: 366 tssd_T55Hydr | ND1: 367 tssd_T56OilP | NE1: 368 tssd_T57Sola | NF1: 369 tssd_T58gdt | NG1: 370 tssd_T59wtr | NH1: 371 tssd_T60cns | NI1: 372 tssd_T61trd | NJ1: 373 tssd_T62afs | NK1: 374 tssd_T63otp | NL1: 375 tssd_T64wtp | NM1: 376 tssd_T65atp | NN1: 377 tssd_T66whs | NO1: 378 tssd_T67cmn | NP1: 379 tssd_T68ofi | NQ1: 380 tssd_T69ins | NR1: 381 tssd_T70rsa | NS1: 382 tssd_T71obs | NT1: 383 tssd_T72ros | NU1: 384 tssd_T73osg | NV1: 385 tssd_T74edu | NW1: 386 tssd_T75hht | NX1: 387 tssd_T76dwe | NY1: 388 tf_Land | NZ1: 389 tf_UnSklab | OA1: 390 tf_SKlab | OB1: 391 tf_Capital | OC1: 392 tf_NatlRes | OD1: 393 otp_world | OE1: 394 wtp_world | OF1: 395 atp_world | OG1: 396 otp_pvst | OH1: 397 wtp_pvst | OI1: 398 atp_pvst | OJ1: 399 ww_world | OK1: 400 REGHOUS | OL1: 401 PRIV | OM1: 402 PRODTAX | ON1: 403 DIRTAX | OO1: 404 GOVT | OP1: 405 CGDS | OQ1: Total
A2: 1 m_pdr | B2: 0 | C2: 0 | D2: 0 | E2: 0 | F2: 0 | G2: 0 | H2: 0 | I2: 0 | J2: 0 | K2: 0 | L2: 0 | M2: 0 | N2: 0 | O2: 0 | P2: 0 | Q2: 0 | R2: 0 | S2: 0 | T2: 0 | U2: 0 | V2: 0 | W2: 0 | X2: 0 | Y2: 0 | Z2: 0 | AA2: 0 | AB2: 0 | AC2: 0 | AD2: 0 | AE2: 0 | AF2: 0 | AG2: 0 | AH2: 0 | AI2: 0 | AJ2: 0 | AK2: 0 | AL2: 0 | AM2: 0 | AN2: 0 | AO2: 0 | AP2: 0 | AQ2: 0 | AR2: 0 | AS2: 0 | AT2: 0 | AU2: 0 | AV2: 0 | AW2: 0 | AX2: 0 | AY2: 0 | AZ2: 0 | BA2: 0 | BB2: 0 | BC2: 0 | BD2: 0 | BE2: 0 | BF2: 0 | BG2: 0 | BH2: 0 | BI2: 0 | BJ2: 0 | BK2: 0 | BL2: 0 | BM2: 0 | BN2: 0 | BO2: 0 | BP2: 0 | BQ2: 0 | BR2: 0 | BS2: 0 | BT2: 0 | BU2: 0 | BV2: 0 | BW2: 0 | BX2: 0 | BY2: 0 | BZ2: 0 | CA2: 0 | CB2: 0 | CC2: 0 | CD2: 0 | CE2: 0 | CF2: 0 | CG2: 0 | CH2: 0 | CI2: 0 | CJ2: 0 | CK2: 0 | CL2: 0 | CM2: 0 | CN2: 0 | CO2: 0 | CP2: 0 | CQ2: 0 | CR2: 0 | CS2: 0 | CT2: 0 | CU2: 0 | CV2: 0 | CW2: 0 | CX2: 0 | CY2: 0 | CZ2: 0 | DA2: 0 | DB2: 0 | DC2: 0 | DD2: 0 | DE2: 0 | DF2: 0 | DG2: 0 | DH2: 0 | DI2: 0 | DJ2: 0 | DK2: 0 | DL2: 0 | DM2: 0 | DN2: 0 | DO2: 0 | DP2: 0 | DQ2: 0 | DR2: 0 | DS2: 0 | DT2: 0 | DU2: 0 | DV2: 0 | DW2: 0 | DX2: 0 | DY2: 0 | DZ2: 0 | EA2: 0 | EB2: 0 | EC2: 0 | ED2: 0 | EE2: 0 | EF2: 0 | EG2: 0 | EH2: 0 | EI2: 0 | EJ2: 0 | EK2: 0 | EL2: 0 | EM2: 0 | EN2: 0 | EO2: 0 | EP2: 0 | EQ2: 0 | ER2: 0 | ES2: 0 | ET2: 0 | EU2: 0 | EV2: 0 | EW2: 0 | EX2: 0.144807 | EY2: 0.592334 | EZ2: 0.007381 | FA2: 0.001067 | FB2: 0.014947 | FC2: 3.9e-05 | FD2: 0.006424 | FE2: 0.000459 | FF2: 0.419314 | FG2: 0.883453 | FH2: 0.228135 | FI2: 0.000767 | FJ2: 0.009131 | FK2: 1.6e-05 | FL2: 0 | FM2: 5e-05 | FN2: 7e-06 | FO2: 1e-05 | FP2: 0.011069 | FQ2: 0.001212 | FR2: 0.002187 | FS2: 0.005053 | FT2: 0.137388 | FU2: 0.005251 | FV2: 14.939363 | FW2: 0.077516 | FX2: 0.00406 | FY2: 5.9e-05 | FZ2: 9e-06 | GA2: 0.00055 | GB2: 0.000721 | GC2: 0.002348 | GD2: 0.493525 | GE2: 0.002716 | GF2: 0.001449 | GG2: 8.7e-05 | GH2: 8e-05 | GI2: 0.003677 | GJ2: 1.6e-05 | GK2: 8e-05 | GL2: 0 | GM2: 9e-06 | GN2: 0 | GO2: 0 | GP2: 0.00285 | GQ2: 0 | GR2: 0 | GS2: 0 | GT2: 0 | GU2: 0 | GV2: 0 | GW2: 0 | GX2: 0 | GY2: 0 | GZ2: 0 | HA2: 0 | HB2: 0 | HC2: 1e-06 | HD2: 2e-06 | HE2: 0.000296 | HF2: 0.229912 | HG2: 0.121726 | HH2: 0.000767 | HI2: 0 | HJ2: 5.7e-05 | HK2: 0.000818 | HL2: 5.2e-05 | HM2: 6e-06 | HN2: 5e-06 | HO2: 3e-05 | HP2: 0.03884 | HQ2: 0.014068 | HR2: 2.1e-05 | HS2: 7.7e-05 | HT2: 7.3e-05 | HU2: 4.5e-05 | HV2: 0 | HW2: 0 | HX2: 0 | HY2: 0 | HZ2: 0 | IA2: 0 | IB2: 0 | IC2: 0 | ID2: 0 | IE2: 0 | IF2: 0 | IG2: 0 | IH2: 0 | II2: 0 | IJ2: 0 | IK2: 0 | IL2: 0 | IM2: 0 | IN2: 0 | IO2: 0 | IP2: 0 | IQ2: 0 | IR2: 0 | IS2: 0 | IT2: 0 | IU2: 0 | IV2: 0 | IW2: 0 | IX2: 0 | IY2: 0 | IZ2: 0 | JA2: 0 | JB2: 0 | JC2: 0 | JD2: 0 | JE2: 0 | JF2: 0 | JG2: 0 | JH2: 0 | JI2: 0 | JJ2: 0 | JK2: 0 | JL2: 0 | JM2: 0 | JN2: 0 | JO2: 0 | JP2: 0 | JQ2: 0 | JR2: 0 | JS2: 0 | JT2: 0 | JU2: 0 | JV2: 0 | JW2: 0 | JX2: 0 | JY2: 0 | JZ2: 0 | KA2: 0 | KB2: 0 | KC2: 0 | KD2: 0 | KE2: 0 | KF2: 0 | KG2: 0 | KH2: 0 | KI2: 0 | KJ2: 0 | KK2: 0 | KL2: 0 | KM2: 0 | KN2: 0 | KO2: 0 | KP2: 0 | KQ2: 0 | KR2: 0 | KS2: 0 | KT2: 0 | KU2: 0 | KV2: 0 | KW2: 0 | KX2: 0 | KY2: 0 | KZ2: 0 | LA2: 0 | LB2: 0 | LC2: 0 | LD2: 0 | LE2: 0 | LF2: 0 | LG2: 0 | LH2: 0 | LI2: 0 | LJ2: 0 | LK2: 0 | LL2: 0 | LM2: 0 | LN2: 0 | LO2: 0 | LP2: 0 | LQ2: 0 | LR2: 0 | LS2: 0 | LT2: 0 | LU2: 0 | LV2: 0 | LW2: 0 | LX2: 0 | LY2: 0 | LZ2: 0 | MA2: 0 | MB2: 0 | MC2: 0 | MD2: 0 | ME2: 0 | MF2: 0 | MG2: 0 | MH2: 0 | MI2: 0 | MJ2: 0 | MK2: 0 | ML2: 0 | MM2: 0 | MN2: 0 | MO2: 0 | MP2: 0 | MQ2: 0 | MR2: 0 | MS2: 0 | MT2: 0 | MU2: 0 | MV2: 0 | MW2: 0 | MX2: 0 | MY2: 0 | MZ2: 0 | NA2: 0 | NB2: 0 | NC2: 0 | ND2: 0 | NE2: 0 | NF2: 0 | NG2: 0 | NH2: 0 | NI2: 0 | NJ2: 0 | NK2: 0 | NL2: 0 | NM2: 0 | NN2: 0 | NO2: 0 | NP2: 0 | NQ2: 0 | NR2: 0 | NS2: 0 | NT2: 0 | NU2: 0 | NV2: 0 | NW2: 0 | NX2: 0 | NY2: 0 | NZ2: 0 | OA2: 0 | OB2: 0 | OC2: 0 | OD2: 0 | OE2: 0 | OF2: 0 | OG2: 0 | OH2: 0 | OI2: 0 | OJ2: 0 | OK2: 0 | OL2: 0.000693 | OM2: 0 | ON2: 0 | OO2: 2.9e-05 | OP2: 0.000162 | OQ2: 18.407297
A3: 2 m_wht | B3: 0 | C3: 0 | D3: 0 | E3: 0 | F3: 0 | G3: 0 | H3: 0 | I3: 0 | J3: 0 | K3: 0 | L3: 0 | M3: 0 | N3: 0 | O3: 0 | P3: 0 | Q3: 0 | R3: 0 | S3: 0 | T3: 0 | U3: 0 | V3: 0 | W3: 0 | X3: 0 | Y3: 0 | Z3: 0 | AA3: 0 | AB3: 0 | AC3: 0 | AD3: 0 | AE3: 0 | AF3: 0 | AG3: 0 | AH3: 0 | AI3: 0 | AJ3: 0 | AK3: 0 | AL3: 0 | AM3: 0 | AN3: 0 | AO3: 0 | AP3: 0 | AQ3: 0 | AR3: 0 | AS3: 0 | AT3: 0 | AU3: 0 | AV3: 0 | AW3: 0 | AX3: 0 | AY3: 0 | AZ3: 0 | BA3: 0 | BB3: 0 | BC3: 0 | BD3: 0 | BE3: 0 | BF3: 0 | BG3: 0 | BH3: 0 | BI3: 0 | BJ3: 0 | BK3: 0 | BL3: 0 | BM3: 0 | BN3: 0 | BO3: 0 | BP3: 0 | BQ3: 0 | BR3: 0 | BS3: 0 | BT3: 0 | BU3: 0 | BV3: 0 | BW3: 0 | BX3: 0 | BY3: 0 | BZ3: 0 | CA3: 0 | CB3: 0 | CC3: 0 | CD3: 0 | CE3: 0 | CF3: 0 | CG3: 0 | CH3: 0 | CI3: 0 | CJ3: 0 | CK3: 0 | CL3: 0 | CM3: 0 | CN3: 0 | CO3: 0 | CP3: 0 | CQ3: 0 | CR3: 0 | CS3: 0 | CT3: 0 | CU3: 0 | CV3: 0 | CW3: 0 | CX3: 0 | CY3: 0 | CZ3: 0 | DA3: 0 | DB3: 0 | DC3: 0 | DD3: 0 | DE3: 0 | DF3: 0 | DG3: 0 | DH3: 0 | DI3: 0 | DJ3: 0 | DK3: 0 | DL3: 0 | DM3: 0 | DN3: 0 | DO3: 0 | DP3: 0 | DQ3: 0 | DR3: 0 | DS3: 0 | DT3: 0 | DU3: 0 | DV3: 0 | DW3: 0 | DX3: 0 | DY3: 0 | DZ3: 0 | EA3: 0 | EB3: 0 | EC3: 0 | ED3: 0 | EE3: 0 | EF3: 0 | EG3: 0 | EH3: 0 | EI3: 0 | EJ3: 0 | EK3: 0 | EL3: 0 | EM3: 0 | EN3: 0 | EO3: 0 | EP3: 0 | EQ3: 0 | ER3: 0 | ES3: 0 | ET3: 0 | EU3: 0 | EV3: 0 | EW3: 0 | EX3: 5.857885 | EY3: 40.368114 | EZ3: 2.160688 | FA3: 0.222501 | FB3: 0.022575 | FC3: 0.000637 | FD3: 0.019936 | FE3: 0.066338 | FF3: 19.310255 | FG3: 39.103645 | FH3: 11.166458 | FI3: 0.034826 | FJ3: 0.339734 | FK3: 0.004347 | FL3: 2e-06 | FM3: 0.002624 | FN3: 0.000278 | FO3: 0.001533 | FP3: 1.156849 | FQ3: 1.203462 | FR3: 0.413914 | FS3: 2.315489 | FT3: 4.44275 | FU3: 1.089898 | FV3: 796.51617 | FW3: 17.112671 | FX3: 0.256419 | FY3: 0.087031 | FZ3: 0.128031 | GA3: 0.028992 | GB3: 0.008851 | GC3: 0.097985 | GD3: 13.33734 | GE3: 2.081834 | GF3: 5.588284 | GG3: 0.006182 | GH3: 0.003291 | GI3: 0.151581 | GJ3: 0.006868 | GK3: 0.003896 | GL3: 0.000332 | GM3: 0.000641 | GN3: 6.6e-05 | GO3: 4.4e-05 | GP3: 0.07056 | GQ3: 1.6e-05 | GR3: 1.1e-05 | GS3: 1.2e-05 | GT3: 2e-06 | GU3: 3e-06 | GV3: 1e-06 | GW3: 0 | GX3: 1e-06 | GY3: 1e-06 | GZ3: 0 | HA3: 1e-06 | HB3: 0 | HC3: 0.000934 | HD3: 0.075146 | HE3: 0.026627 | HF3: 0.031079 | HG3: 17.61566 | HH3: 0.032085 | HI3: 0.000303 | HJ3: 0.002369 | HK3: 0.025986 | HL3: 0.04345 | HM3: 0.060263 | HN3: 0.050848 | HO3: 0.032528 | HP3: 1.66095 | HQ3: 0.673325 | HR3: 1.757806 | HS3: 0.039228 | HT3: 2.204378 | HU3: 0.04085 | HV3: 0 | HW3: 0 | HX3: 0 | HY3: 0 | HZ3: 0 | IA3: 0 | IB3: 0 | IC3: 0 | ID3: 0 | IE3: 0 | IF3: 0 | IG3: 0 | IH3: 0 | II3: 0 | IJ3: 0 | IK3: 0 | IL3: 0 | IM3: 0 | IN3: 0 | IO3: 0 | IP3: 0 | IQ3: 0 | IR3: 0 | IS3: 0 | IT3: 0 | IU3: 0 | IV3: 0 | IW3: 0 | IX3: 0 | IY3: 0 | IZ3: 0 | JA3: 0 | JB3: 0 | JC3: 0 | JD3: 0 | JE3: 0 | JF3: 0 | JG3: 0 | JH3: 0 | JI3: 0 | JJ3: 0 | JK3: 0 | JL3: 0 | JM3: 0 | JN3: 0 | JO3: 0 | JP3: 0 | JQ3: 0 | JR3: 0 | JS3: 0 | JT3: 0 | JU3: 0 | JV3: 0 | JW3: 0 | JX3: 0 | JY3: 0 | JZ3: 0 | KA3: 0 | KB3: 0 | KC3: 0 | KD3: 0 | KE3: 0 | KF3: 0 | KG3: 0 | KH3: 0 | KI3: 0 | KJ3: 0 | KK3: 0 | KL3: 0 | KM3: 0 | KN3: 0 | KO3: 0 | KP3: 0 | KQ3: 0 | KR3: 0 | KS3: 0 | KT3: 0 | KU3: 0 | KV3: 0 | KW3: 0 | KX3: 0 | KY3: 0 | KZ3: 0 | LA3: 0 | LB3: 0 | LC3: 0 | LD3: 0 | LE3: 0 | LF3: 0 | LG3: 0 | LH3: 0 | LI3: 0 | LJ3: 0 | LK3: 0 | LL3: 0 | LM3: 0 | LN3: 0 | LO3: 0 | LP3: 0 | LQ3: 0 | LR3: 0 | LS3: 0 | LT3: 0 | LU3: 0 | LV3: 0 | LW3: 0 | LX3: 0 | LY3: 0 | LZ3: 0 | MA3: 0 | MB3: 0 | MC3: 0 | MD3: 0 | ME3: 0 | MF3: 0 | MG3: 0 | MH3: 0 | MI3: 0 | MJ3: 0 | MK3: 0 | ML3: 0 | MM3: 0 | MN3: 0 | MO3: 0 | MP3: 0 | MQ3: 0 | MR3: 0 | MS3: 0 | MT3: 0 | MU3: 0 | MV3: 0 | MW3: 0 | MX3: 0 | MY3: 0 | MZ3: 0 | NA3: 0 | NB3: 0 | NC3: 0 | ND3: 0 | NE3: 0 | NF3: 0 | NG3: 0 | NH3: 0 | NI3: 0 | NJ3: 0 | NK3: 0 | NL3: 0 | NM3: 0 | NN3: 0 | NO3: 0 | NP3: 0 | NQ3: 0 | NR3: 0 | NS3: 0 | NT3: 0 | NU3: 0 | NV3: 0 | NW3: 0 | NX3: 0 | NY3: 0 | NZ3: 0 | OA3: 0 | OB3: 0 | OC3: 0 | OD3: 0 | OE3: 0 | OF3: 0 | OG3: 0 | OH3: 0 | OI3: 0 | OJ3: 0 | OK3: 0 | OL3: 0.596011 | OM3: 0 | ON3: 0 | OO3: 0.034058 | OP3: 0.007682 | OQ3: 989.80342
A4: 3 m_gro | B4: 0 | C4: 0 | D4: 0 | E4: 0 | F4: 0 | G4: 0 | H4: 0 | I4: 0 | J4: 0 | K4: 0 | L4: 0 | M4: 0 | N4: 0 | O4: 0 | P4: 0 | Q4: 0 | R4: 0 | S4: 0 | T4: 0 | U4: 0 | V4: 0 | W4: 0 | X4: 0 | Y4: 0 | Z4: 0 | AA4: 0 | AB4: 0 | AC4: 0 | AD4: 0 | AE4: 0 | AF4: 0 | AG4: 0 | AH4: 0 | AI4: 0 | AJ4: 0 | AK4: 0 | AL4: 0 | AM4: 0 | AN4: 0 | AO4: 0 | AP4: 0 | AQ4: 0 | AR4: 0 | AS4: 0 | AT4: 0 | AU4: 0 | AV4: 0 | AW4: 0 | AX4: 0 | AY4: 0 | AZ4: 0 | BA4: 0 | BB4: 0 | BC4: 0 | BD4: 0 | BE4: 0 | BF4: 0 | BG4: 0 | BH4: 0 | BI4: 0 | BJ4: 0 | BK4: 0 | BL4: 0 | BM4: 0 | BN4: 0 | BO4: 0 | BP4: 0 | BQ4: 0 | BR4: 0 | BS4: 0 | BT4: 0 | BU4: 0 | BV4: 0 | BW4: 0 | BX4: 0 | BY4: 0 | BZ4: 0 | CA4: 0 | CB4: 0 | CC4: 0 | CD4: 0 | CE4: 0 | CF4: 0 | CG4: 0 | CH4: 0 | CI4: 0 | CJ4: 0 | CK4: 0 | CL4: 0 | CM4: 0 | CN4: 0 | CO4: 0 | CP4: 0 | CQ4: 0 | CR4: 0 | CS4: 0 | CT4: 0 | CU4: 0 | CV4: 0 | CW4: 0 | CX4: 0 | CY4: 0 | CZ4: 0 | DA4: 0 | DB4: 0 | DC4: 0 | DD4: 0 | DE4: 0 | DF4: 0 | DG4: 0 | DH4: 0 | DI4: 0 | DJ4: 0 | DK4: 0 | DL4: 0 | DM4: 0 | DN4: 0 | DO4: 0 | DP4: 0 | DQ4: 0 | DR4: 0 | DS4: 0 | DT4: 0 | DU4: 0 | DV4: 0 | DW4: 0 | DX4: 0 | DY4: 0 | DZ4: 0 | EA4: 0 | EB4: 0 | EC4: 0 | ED4: 0 | EE4: 0 | EF4: 0 | EG4: 0 | EH4: 0 | EI4: 0 | EJ4: 0 | EK4: 0 | EL4: 0 | EM4: 0 | EN4: 0 | EO4: 0 | EP4: 0 | EQ4: 0 | ER4: 0 | ES4: 0 | ET4: 0 | EU4: 0 | EV4: 0 | EW4: 0 | EX4: 0.008023 | EY4: 0.133456 | EZ4: 25.783201 | FA4: 0.153526 | FB4: 0.027958 | FC4: 0.000682 | FD4: 0.002274 | FE4: 0.002513 | FF4: 162.23567 | FG4: 157.6781 | FH4: 295.43399 | FI4: 0.352667 | FJ4: 7.07889 | FK4: 0.002362 | FL4: 1e-06 | FM4: 0.00075 | FN4: 0.002489 | FO4: 0.000794 | FP4: 10.95054 | FQ4: 8.318515 | FR4: 2.685355 | FS4: 15.356281 | FT4: 0.190273 | FU4: 2.818709 | FV4: 461.12146 | FW4: 89.161324 | FX4: 1.169749 | FY4: 0.80729 | FZ4: 0.240228 | GA4: 0.065765 | GB4: 0.028947 | GC4: 0.001809 | GD4: 5.426575 | GE4: 1.090778 | GF4: 2.273824 | GG4: 0.004978 | GH4: 3.3e-05 | GI4: 3e-06 | GJ4: 0.011598 | GK4: 0.005872 | GL4: 0.000472 | GM4: 0.000846 | GN4: 4.9e-05 | GO4: 0.000267 | GP4: 1.144199 | GQ4: 0.000128 | GR4: 8.4e-05 | GS4: 9.4e-05 | GT4: 1.4e-05 | GU4: 2e-05 | GV4: 6e-06 | GW4: 0 | GX4: 4e-06 | GY4: 1e-05 | GZ4: 0 | HA4: 9e-06 | HB4: 1e-06 | HC4: 0.025442 | HD4: 0.070321 | HE4: 2.098124 | HF4: 0.064917 | HG4: 51.856632 | HH4: 0.009003 | HI4: 0.000558 | HJ4: 0.025161 | HK4: 0.008959 | HL4: 0.170818 | HM4: 0.082853 | HN4: 0.069821 | HO4: 0.135057 | HP4: 8.903062 | HQ4: 7.224765 | HR4: 2.315092 | HS4: 0.06422 | HT4: 3.040934 | HU4: 0.076946 | HV4: 0 | HW4: 0 | HX4: 0 | HY4: 0 | HZ4: 0 | IA4: 0 | IB4: 0 | IC4: 0 | ID4: 0 | IE4: 0 | IF4: 0 | IG4: 0 | IH4: 0 | II4: 0 | IJ4: 0 | IK4: 0 | IL4: 0 | IM4: 0 | IN4: 0 | IO4: 0 | IP4: 0 | IQ4: 0 | IR4: 0 | IS4: 0 | IT4: 0 | IU4: 0 | IV4: 0 | IW4: 0 | IX4: 0 | IY4: 0 | IZ4: 0 | JA4: 0 | JB4: 0 | JC4: 0 | JD4: 0 | JE4: 0 | JF4: 0 | JG4: 0 | JH4: 0 | JI4: 0 | JJ4: 0 | JK4: 0 | JL4: 0 | JM4: 0 | JN4: 0 | JO4: 0 | JP4: 0 | JQ4: 0 | JR4: 0 | JS4: 0 | JT4: 0 | JU4: 0 | JV4: 0 | JW4: 0 | JX4: 0 | JY4: 0 | JZ4: 0 | KA4: 0 | KB4: 0 | KC4: 0 | KD4: 0 | KE4: 0 | KF4: 0 | KG4: 0 | KH4: 0 | KI4: 0 | KJ4: 0 | KK4: 0 | KL4: 0 | KM4: 0 | KN4: 0 | KO4: 0 | KP4: 0 | KQ4: 0 | KR4: 0 | KS4: 0 | KT4: 0 | KU4: 0 | KV4: 0 | KW4: 0 | KX4: 0 | KY4: 0 | KZ4: 0 | LA4: 0 | LB4: 0 | LC4: 0 | LD4: 0 | LE4: 0 | LF4: 0 | LG4: 0 | LH4: 0 | LI4: 0 | LJ4: 0 | LK4: 0 | LL4: 0 | LM4: 0 | LN4: 0 | LO4: 0 | LP4: 0 | LQ4: 0 | LR4: 0 | LS4: 0 | LT4: 0 | LU4: 0 | LV4: 0 | LW4: 0 | LX4: 0 | LY4: 0 | LZ4: 0 | MA4: 0 | MB4: 0 | MC4: 0 | MD4: 0 | ME4: 0 | MF4: 0 | MG4: 0 | MH4: 0 | MI4: 0 | MJ4: 0 | MK4: 0 | ML4: 0 | MM4: 0 | MN4: 0 | MO4: 0 | MP4: 0 | MQ4: 0 | MR4: 0 | MS4: 0 | MT4: 0 | MU4: 0 | MV4: 0 | MW4: 0 | MX4: 0 | MY4: 0 | MZ4: 0 | NA4: 0 | NB4: 0 | NC4: 0 | ND4: 0 | NE4: 0 | NF4: 0 | NG4: 0 | NH4: 0 | NI4: 0 | NJ4: 0 | NK4: 0 | NL4: 0 | NM4: 0 | NN4: 0 | NO4: 0 | NP4: 0 | NQ4: 0 | NR4: 0 | NS4: 0 | NT4: 0 | NU4: 0 | NV4: 0 | NW4: 0 | NX4: 0 | NY4: 0 | NZ4: 0 | OA4: 0 | OB4: 0 | OC4: 0 | OD4: 0 | OE4: 0 | OF4: 0 | OG4: 0 | OH4: 0 | OI4: 0 | OJ4: 0 | OK4: 0 | OL4: 292.83697 | OM4: 0 | ON4: 0 | OO4: 0.001669 | OP4: 2.544111 | OQ4: 1623.3989
A5: 4 m_v_f | B5: 0 | C5: 0 | D5: 0 | E5: 0 | F5: 0 | G5: 0 | H5: 0 | I5: 0 | J5: 0 | K5: 0 | L5: 0 | M5: 0 | N5: 0 | O5: 0 | P5: 0 | Q5: 0 | R5: 0 | S5: 0 | T5: 0 | U5: 0 | V5: 0 | W5: 0 | X5: 0 | Y5: 0 | Z5: 0 | AA5: 0 | AB5: 0 | AC5: 0 | AD5: 0 | AE5: 0 | AF5: 0 | AG5: 0 | AH5: 0 | AI5: 0 | AJ5: 0 | AK5: 0 | AL5: 0 | AM5: 0 | AN5: 0 | AO5: 0 | AP5: 0 | AQ5: 0 | AR5: 0 | AS5: 0 | AT5: 0 | AU5: 0 | AV5: 0 | AW5: 0 | AX5: 0 | AY5: 0 | AZ5: 0 | BA5: 0 | BB5: 0 | BC5: 0 | BD5: 0 | BE5: 0 | BF5: 0 | BG5: 0 | BH5: 0 | BI5: 0 | BJ5: 0 | BK5: 0 | BL5: 0 | BM5: 0 | BN5: 0 | BO5: 0 | BP5: 0 | BQ5: 0 | BR5: 0 | BS5: 0 | BT5: 0 | BU5: 0 | BV5: 0 | BW5: 0 | BX5: 0 | BY5: 0 | BZ5: 0 | CA5: 0 | CB5: 0 | CC5: 0 | CD5: 0 | CE5: 0 | CF5: 0 | CG5: 0 | CH5: 0 | CI5: 0 | CJ5: 0 | CK5: 0 | CL5: 0 | CM5: 0 | CN5: 0 | CO5: 0 | CP5: 0 | CQ5: 0 | CR5: 0 | CS5: 0 | CT5: 0 | CU5: 0 | CV5: 0 | CW5: 0 | CX5: 0 | CY5: 0 | CZ5: 0 | DA5: 0 | DB5: 0 | DC5: 0 | DD5: 0 | DE5: 0 | DF5: 0 | DG5: 0 | DH5: 0 | DI5: 0 | DJ5: 0 | DK5: 0 | DL5: 0 | DM5: 0 | DN5: 0 | DO5: 0 | DP5: 0 | DQ5: 0 | DR5: 0 | DS5: 0 | DT5: 0 | DU5: 0 | DV5: 0 | DW5: 0 | DX5: 0 | DY5: 0 | DZ5: 0 | EA5: 0 | EB5: 0 | EC5: 0 | ED5: 0 | EE5: 0 | EF5: 0 | EG5: 0 | EH5: 0 | EI5: 0 | EJ5: 0 | EK5: 0 | EL5: 0 | EM5: 0 | EN5: 0 | EO5: 0 | EP5: 0 | EQ5: 0 | ER5: 0 | ES5: 0 | ET5: 0 | EU5: 0 | EV5: 0 | EW5: 0 | EX5: 0.020067 | EY5: 0.099578 | EZ5: 0.571803 | FA5: 53.874329 | FB5: 0.291131 | FC5: 0.006552 | FD5: 0.004026 | FE5: 0.063401 | FF5: 57.982964 | FG5: 45.690456 | FH5: 36.686184 | FI5: 0.067565 | FJ5: 0.000276 | FK5: 0.024743 | FL5: 1.6e-05 | FM5: 0.009674 | FN5: 5e-05 | FO5: 0.002998 | FP5: 3.677377 | FQ5: 22.267759 | FR5: 8.263585 | FS5: 24.600365 | FT5: 50.793217 | FU5: 14.488631 | FV5: 7211.4814 | FW5: 524.09033 | FX5: 0.699389 | FY5: 0.512565 | FZ5: 0.40733 | GA5: 0.082817 | GB5: 0.042257 | GC5: 0.021593 | GD5: 8.22088 | GE5: 26.637333 | GF5: 0.278018 | GG5: 0.007736 | GH5: 1e-05 | GI5: 1.9e-05 | GJ5: 0.23169 | GK5: 0.258685 | GL5: 0.01669 | GM5: 0.031154 | GN5: 4.6e-05 | GO5: 0.064822 | GP5: 3.452574 | GQ5: 0.000578 | GR5: 0.000378 | GS5: 0.000424 | GT5: 6.1e-05 | GU5: 8.9e-05 | GV5: 2.8e-05 | GW5: 0 | GX5: 1.8e-05 | GY5: 4.7e-05 | GZ5: 0 | HA5: 3.9e-05 | HB5: 6e-06 | HC5: 0.11399 | HD5: 0.771111 | HE5: 0.473811 | HF5: 0.025496 | HG5: 189.45505 | HH5: 2.2e-05 | HI5: 0.029839 | HJ5: 1e-06 | HK5: 0.148042 | HL5: 0.123996 | HM5: 1.313133 | HN5: 0.879216 | HO5: 0.078745 | HP5: 2.831115 | HQ5: 792.51917 | HR5: 48.395622 | HS5: 0.358479 | HT5: 462.04514 | HU5: 0.120728 | HV5: 0 | HW5: 0 | HX5: 0 | HY5: 0 | HZ5: 0 | IA5: 0 | IB5: 0 | IC5: 0 | ID5: 0 | IE5: 0 | IF5: 0 | IG5: 0 | IH5: 0 | II5: 0 | IJ5: 0 | IK5: 0 | IL5: 0 | IM5: 0 | IN5: 0 | IO5: 0 | IP5: 0 | IQ5: 0 | IR5: 0 | IS5: 0 | IT5: 0 | IU5: 0 | IV5: 0 | IW5: 0 | IX5: 0 | IY5: 0 | IZ5: 0 | JA5: 0 | JB5: 0 | JC5: 0 | JD5: 0 | JE5: 0 | JF5: 0 | JG5: 0 | JH5: 0 | JI5: 0 | JJ5: 0 | JK5: 0 | JL5: 0 | JM5: 0 | JN5: 0 | JO5: 0 | JP5: 0 | JQ5: 0 | JR5: 0 | JS5: 0 | JT5: 0 | JU5: 0 | JV5: 0 | JW5: 0 | JX5: 0 | JY5: 0 | JZ5: 0 | KA5: 0 | KB5: 0 | KC5: 0 | KD5: 0 | KE5: 0 | KF5: 0 | KG5: 0 | KH5: 0 | KI5: 0 | KJ5: 0 | KK5: 0 | KL5: 0 | KM5: 0 | KN5: 0 | KO5: 0 | KP5: 0 | KQ5: 0 | KR5: 0 | KS5: 0 | KT5: 0 | KU5: 0 | KV5: 0 | KW5: 0 | KX5: 0 | KY5: 0 | KZ5: 0 | LA5: 0 | LB5: 0 | LC5: 0 | LD5: 0 | LE5: 0 | LF5: 0 | LG5: 0 | LH5: 0 | LI5: 0 | LJ5: 0 | LK5: 0 | LL5: 0 | LM5: 0 | LN5: 0 | LO5: 0 | LP5: 0 | LQ5: 0 | LR5: 0 | LS5: 0 | LT5: 0 | LU5: 0 | LV5: 0 | LW5: 0 | LX5: 0 | LY5: 0 | LZ5: 0 | MA5: 0 | MB5: 0 | MC5: 0 | MD5: 0 | ME5: 0 | MF5: 0 | MG5: 0 | MH5: 0 | MI5: 0 | MJ5: 0 | MK5: 0 | ML5: 0 | MM5: 0 | MN5: 0 | MO5: 0 | MP5: 0 | MQ5: 0 | MR5: 0 | MS5: 0 | MT5: 0 | MU5: 0 | MV5: 0 | MW5: 0 | MX5: 0 | MY5: 0 | MZ5: 0 | NA5: 0 | NB5: 0 | NC5: 0 | ND5: 0 | NE5: 0 | NF5: 0 | NG5: 0 | NH5: 0 | NI5: 0 | NJ5: 0 | NK5: 0 | NL5: 0 | NM5: 0 | NN5: 0 | NO5: 0 | NP5: 0 | NQ5: 0 | NR5: 0 | NS5: 0 | NT5: 0 | NU5: 0 | NV5: 0 | NW5: 0 | NX5: 0 | NY5: 0 | NZ5: 0 | OA5: 0 | OB5: 0 | OC5: 0 | OD5: 0 | OE5: 0 | OF5: 0 | OG5: 0 | OH5: 0 | OI5: 0 | OJ5: 0 | OK5: 0 | OL5: 10464.871 | OM5: 0 | ON5: 0 | OO5: 0.064376 | OP5: 0.431171 | OQ5: 20061.075
A6: 5 m_osd | B6: 0 | C6: 0 | D6: 0 | E6: 0 | F6: 0 | G6: 0 | H6: 0 | I6: 0 | J6: 0 | K6: 0 | L6: 0 | M6: 0 | N6: 0 | O6: 0 | P6: 0 | Q6: 0 | R6: 0 | S6: 0 | T6: 0 | U6: 0 | V6: 0 | W6: 0 | X6: 0 | Y6: 0 | Z6: 0 | AA6: 0 | AB6: 0 | AC6: 0 | AD6: 0 | AE6: 0 | AF6: 0 | AG6: 0 | AH6: 0 | AI6: 0 | AJ6: 0 | AK6: 0 | AL6: 0 | AM6: 0 | AN6: 0 | AO6: 0 | AP6: 0 | AQ6: 0 | AR6: 0 | AS6: 0 | AT6: 0 | AU6: 0 | AV6: 0 | AW6: 0 | AX6: 0 | AY6: 0 | AZ6: 0 | BA6: 0 | BB6: 0 | BC6: 0 | BD6: 0 | BE6: 0 | BF6: 0 | BG6: 0 | BH6: 0 | BI6: 0 | BJ6: 0 | BK6: 0 | BL6: 0 | BM6: 0 | BN6: 0 | BO6: 0 | BP6: 0 | BQ6: 0 | BR6: 0 | BS6: 0 | BT6: 0 | BU6: 0 | BV6: 0 | BW6: 0 | BX6: 0 | BY6: 0 | BZ6: 0 | CA6: 0 | CB6: 0 | CC6: 0 | CD6: 0 | CE6: 0 | CF6: 0 | CG6: 0 | CH6: 0 | CI6: 0 | CJ6: 0 | CK6: 0 | CL6: 0 | CM6: 0 | CN6: 0 | CO6: 0 | CP6: 0 | CQ6: 0 | CR6: 0 | CS6: 0 | CT6: 0 | CU6: 0 | CV6: 0 | CW6: 0 | CX6: 0 | CY6: 0 | CZ6: 0 | DA6: 0 | DB6: 0 | DC6: 0 | DD6: 0 | DE6: 0 | DF6: 0 | DG6: 0 | DH6: 0 | DI6: 0 | DJ6: 0 | DK6: 0 | DL6: 0 | DM6: 0 | DN6: 0 | DO6: 0 | DP6: 0 | DQ6: 0 | DR6: 0 | DS6: 0 | DT6: 0 | DU6: 0 | DV6: 0 | DW6: 0 | DX6: 0 | DY6: 0 | DZ6: 0 | EA6: 0 | EB6: 0 | EC6: 0 | ED6: 0 | EE6: 0 | EF6: 0 | EG6: 0 | EH6: 0 | EI6: 0 | EJ6: 0 | EK6: 0 | EL6: 0 | EM6: 0 | EN6: 0 | EO6: 0 | EP6: 0 | EQ6: 0 | ER6: 0 | ES6: 0 | ET6: 0 | EU6: 0 | EV6: 0 | EW6: 0 | EX6: 0.025701 | EY6: 0.102198 | EZ6: 0.525984 | FA6: 1.006569 | FB6: 174.45889 | FC6: 0.000671 | FD6: 0.014776 | FE6: 0.059039 | FF6: 9.549926 | FG6: 13.64735 | FH6: 5.91092 | FI6: 0.00745 | FJ6: 0.223592 | FK6: 0.005647 | FL6: 4e-06 | FM6: 0.030064 | FN6: 0.019238 | FO6: 0.000182 | FP6: 6.945862 | FQ6: 4.282421 | FR6: 1676.542 | FS6: 12.591805 | FT6: 0.175133 | FU6: 6.124818 | FV6: 252.40778 | FW6: 16.464819 | FX6: 2.325351 | FY6: 0.945673 | FZ6: 1.494475 | GA6: 0.297295 | GB6: 0.075287 | GC6: 0.002478 | GD6: 4.011809 | GE6: 0.047715 | GF6: 0.086443 | GG6: 0.030859 | GH6: 1.3e-05 | GI6: 0.000175 | GJ6: 0.011484 | GK6: 0.007351 | GL6: 0.003028 | GM6: 0.004963 | GN6: 0.000114 | GO6: 0.000132 | GP6: 0.076695 | GQ6: 0.000299 | GR6: 0.000196 | GS6: 0.00022 | GT6: 3.2e-05 | GU6: 4.6e-05 | GV6: 1.4e-05 | GW6: 0 | GX6: 1e-05 | GY6: 2.5e-05 | GZ6: 0 | HA6: 2e-05 | HB6: 3e-06 | HC6: 0.029329 | HD6: 0.006651 | HE6: 0.188247 | HF6: 0.535612 | HG6: 16.956064 | HH6: 0.014044 | HI6: 0.002546 | HJ6: 0.000647 | HK6: 0.014546 | HL6: 0.046524 | HM6: 0.093065 | HN6: 0.078328 | HO6: 0.033142 | HP6: 3.700973 | HQ6: 1.694964 | HR6: 23.277647 | HS6: 0.046419 | HT6: 1.609888 | HU6: 0.481892 | HV6: 0 | HW6: 0 | HX6: 0 | HY6: 0 | HZ6: 0 | IA6: 0 | IB6: 0 | IC6: 0 | ID6: 0 | IE6: 0 | IF6: 0 | IG6: 0 | IH6: 0 | II6: 0 | IJ6: 0 | IK6: 0 | IL6: 0 | IM6: 0 | IN6: 0 | IO6: 0 | IP6: 0 | IQ6: 0 | IR6: 0 | IS6: 0 | IT6: 0 | IU6: 0 | IV6: 0 | IW6: 0 | IX6: 0 | IY6: 0 | IZ6: 0 | JA6: 0 | JB6: 0 | JC6: 0 | JD6: 0 | JE6: 0 | JF6: 0 | JG6: 0 | JH6: 0 | JI6: 0 | JJ6: 0 | JK6: 0 | JL6: 0 | JM6: 0 | JN6: 0 | JO6: 0 | JP6: 0 | JQ6: 0 | JR6: 0 | JS6: 0 | JT6: 0 | JU6: 0 | JV6: 0 | JW6: 0 | JX6: 0 | JY6: 0 | JZ6: 0 | KA6: 0 | KB6: 0 | KC6: 0 | KD6: 0 | KE6: 0 | KF6: 0 | KG6: 0 | KH6: 0 | KI6: 0 | KJ6: 0 | KK6: 0 | KL6: 0 | KM6: 0 | KN6: 0 | KO6: 0 | KP6: 0 | KQ6: 0 | KR6: 0 | KS6: 0 | KT6: 0 | KU6: 0 | KV6: 0 | KW6: 0 | KX6: 0 | KY6: 0 | KZ6: 0 | LA6: 0 | LB6: 0 | LC6: 0 | LD6: 0 | LE6: 0 | LF6: 0 | LG6: 0 | LH6: 0 | LI6: 0 | LJ6: 0 | LK6: 0 | LL6: 0 | LM6: 0 | LN6: 0 | LO6: 0 | LP6: 0 | LQ6: 0 | LR6: 0 | LS6: 0 | LT6: 0 | LU6: 0 | LV6: 0 | LW6: 0 | LX6: 0 | LY6: 0 | LZ6: 0 | MA6: 0 | MB6: 0 | MC6: 0 | MD6: 0 | ME6: 0 | MF6: 0 | MG6: 0 | MH6: 0 | MI6: 0 | MJ6: 0 | MK6: 0 | ML6: 0 | MM6: 0 | MN6: 0 | MO6: 0 | MP6: 0 | MQ6: 0 | MR6: 0 | MS6: 0 | MT6: 0 | MU6: 0 | MV6: 0 | MW6: 0 | MX6: 0 | MY6: 0 | MZ6: 0 | NA6: 0 | NB6: 0 | NC6: 0 | ND6: 0 | NE6: 0 | NF6: 0 | NG6: 0 | NH6: 0 | NI6: 0 | NJ6: 0 | NK6: 0 | NL6: 0 | NM6: 0 | NN6: 0 | NO6: 0 | NP6: 0 | NQ6: 0 | NR6: 0 | NS6: 0 | NT6: 0 | NU6: 0 | NV6: 0 | NW6: 0 | NX6: 0 | NY6: 0 | NZ6: 0 | OA6: 0 | OB6: 0 | OC6: 0 | OD6: 0 | OE6: 0 | OF6: 0 | OG6: 0 | OH6: 0 | OI6: 0 | OJ6: 0 | OK6: 0 | OL6: 2.692938 | OM6: 0 | ON6: 0 | OO6: 9e-05 | OP6: 0.067752 | OQ6: 2242.1163
A7: 6 m_c_b | B7: 0 | C7: 0 | D7: 0 | E7: 0 | F7: 0 | G7: 0 | H7: 0 | I7: 0 | J7: 0 | K7: 0 | L7: 0 | M7: 0 | N7: 0 | O7: 0 | P7: 0 | Q7: 0 | R7: 0 | S7: 0 | T7: 0 | U7: 0 | V7: 0 | W7: 0 | X7: 0 | Y7: 0 | Z7: 0 | AA7: 0 | AB7: 0 | AC7: 0 | AD7: 0 | AE7: 0 | AF7: 0 | AG7: 0 | AH7: 0 | AI7: 0 | AJ7: 0 | AK7: 0 | AL7: 0 | AM7: 0 | AN7: 0 | AO7: 0 | AP7: 0 | AQ7: 0 | AR7: 0 | AS7: 0 | AT7: 0 | AU7: 0 | AV7: 0 | AW7: 0 | AX7: 0 | AY7: 0 | AZ7: 0 | BA7: 0 | BB7: 0 | BC7: 0 | BD7: 0 | BE7: 0 | BF7: 0 | BG7: 0 | BH7: 0 | BI7: 0 | BJ7: 0 | BK7: 0 | BL7: 0 | BM7: 0 | BN7: 0 | BO7: 0 | BP7: 0 | BQ7: 0 | BR7: 0 | BS7: 0 | BT7: 0 | BU7: 0 | BV7: 0 | BW7: 0 | BX7: 0 | BY7: 0 | BZ7: 0 | CA7: 0 | CB7: 0 | CC7: 0 | CD7: 0 | CE7: 0 | CF7: 0 | CG7: 0 | CH7: 0 | CI7: 0 | CJ7: 0 | CK7: 0 | CL7: 0 | CM7: 0 | CN7: 0 | CO7: 0 | CP7: 0 | CQ7: 0 | CR7: 0 | CS7: 0 | CT7: 0 | CU7: 0 | CV7: 0 | CW7: 0 | CX7: 0 | CY7: 0 | CZ7: 0 | DA7: 0 | DB7: 0 | DC7: 0 | DD7: 0 | DE7: 0 | DF7: 0 | DG7: 0 | DH7: 0 | DI7: 0 | DJ7: 0 | DK7: 0 | DL7: 0 | DM7: 0 | DN7: 0 | DO7: 0 | DP7: 0 | DQ7: 0 | DR7: 0 | DS7: 0 | DT7: 0 | DU7: 0 | DV7: 0 | DW7: 0 | DX7: 0 | DY7: 0 | DZ7: 0 | EA7: 0 | EB7: 0 | EC7: 0 | ED7: 0 | EE7: 0 | EF7: 0 | EG7: 0 | EH7: 0 | EI7: 0 | EJ7: 0 | EK7: 0 | EL7: 0 | EM7: 0 | EN7: 0 | EO7: 0 | EP7: 0 | EQ7: 0 | ER7: 0 | ES7: 0 | ET7: 0 | EU7: 0 | EV7: 0 | EW7: 0 | EX7: 0.000534 | EY7: 0.005632 | EZ7: 0.000761 | FA7: 0.002202 | FB7: 0.01891 | FC7: 0.000181 | FD7: 0.000363 | FE7: 0.00134 | FF7: 0.001255 | FG7: 0.001487 | FH7: 1.6e-05 | FI7: 2.1e-05 | FJ7: 1.8e-05 | FK7: 3.5e-05 | FL7: 1e-06 | FM7: 1.7e-05 | FN7: 2e-06 | FO7: 1e-06 | FP7: 0.001336 | FQ7: 0.001944 | FR7: 0.011737 | FS7: 0.002426 | FT7: 0.016875 | FU7: 5.713717 | FV7: 0.058692 | FW7: 0.030836 | FX7: 0.011505 | FY7: 0.000241 | FZ7: 4e-05 | GA7: 0.001713 | GB7: 0.002265 | GC7: 1e-06 | GD7: 0.000998 | GE7: 0.028009 | GF7: 3.6e-05 | GG7: 1e-06 | GH7: 0 | GI7: 1e-06 | GJ7: 2.3e-05 | GK7: 1e-06 | GL7: 2e-06 | GM7: 3.2e-05 | GN7: 0 | GO7: 1e-06 | GP7: 0.000855 | GQ7: 9e-06 | GR7: 6e-06 | GS7: 7e-06 | GT7: 1e-06 | GU7: 1e-06 | GV7: 0 | GW7: 0 | GX7: 0 | GY7: 1e-06 | GZ7: 0 | HA7: 1e-06 | HB7: 0 | HC7: 8e-06 | HD7: 7.3e-05 | HE7: 0.001088 | HF7: 0.006083 | HG7: 0.002939 | HH7: 7e-06 | HI7: 0 | HJ7: 0 | HK7: 0.000838 | HL7: 0.000212 | HM7: 3.3e-05 | HN7: 2.6e-05 | HO7: 0.000124 | HP7: 0.008936 | HQ7: 0.000371 | HR7: 0.000838 | HS7: 0.000801 | HT7: 0.001499 | HU7: 0.000152 | HV7: 0 | HW7: 0 | HX7: 0 | HY7: 0 | HZ7: 0 | IA7: 0 | IB7: 0 | IC7: 0 | ID7: 0 | IE7: 0 | IF7: 0 | IG7: 0 | IH7: 0 | II7: 0 | IJ7: 0 | IK7: 0 | IL7: 0 | IM7: 0 | IN7: 0 | IO7: 0 | IP7: 0 | IQ7: 0 | IR7: 0 | IS7: 0 | IT7: 0 | IU7: 0 | IV7: 0 | IW7: 0 | IX7: 0 | IY7: 0 | IZ7: 0 | JA7: 0 | JB7: 0 | JC7: 0 | JD7: 0 | JE7: 0 | JF7: 0 | JG7: 0 | JH7: 0 | JI7: 0 | JJ7: 0 | JK7: 0 | JL7: 0 | JM7: 0 | JN7: 0 | JO7: 0 | JP7: 0 | JQ7: 0 | JR7: 0 | JS7: 0 | JT7: 0 | JU7: 0 | JV7: 0 | JW7: 0 | JX7: 0 | JY7: 0 | JZ7: 0 | KA7: 0 | KB7: 0 | KC7: 0 | KD7: 0 | KE7: 0 | KF7: 0 | KG7: 0 | KH7: 0 | KI7: 0 | KJ7: 0 | KK7: 0 | KL7: 0 | KM7: 0 | KN7: 0 | KO7: 0 | KP7: 0 | KQ7: 0 | KR7: 0 | KS7: 0 | KT7: 0 | KU7: 0 | KV7: 0 | KW7: 0 | KX7: 0 | KY7: 0 | KZ7: 0 | LA7: 0 | LB7: 0 | LC7: 0 | LD7: 0 | LE7: 0 | LF7: 0 | LG7: 0 | LH7: 0 | LI7: 0 | LJ7: 0 | LK7: 0 | LL7: 0 | LM7: 0 | LN7: 0 | LO7: 0 | LP7: 0 | LQ7: 0 | LR7: 0 | LS7: 0 | LT7: 0 | LU7: 0 | LV7: 0 | LW7: 0 | LX7: 0 | LY7: 0 | LZ7: 0 | MA7: 0 | MB7: 0 | MC7: 0 | MD7: 0 | ME7: 0 | MF7: 0 | MG7: 0 | MH7: 0 | MI7: 0 | MJ7: 0 | MK7: 0 | ML7: 0 | MM7: 0 | MN7: 0 | MO7: 0 | MP7: 0 | MQ7: 0 | MR7: 0 | MS7: 0 | MT7: 0 | MU7: 0 | MV7: 0 | MW7: 0 | MX7: 0 | MY7: 0 | MZ7: 0 | NA7: 0 | NB7: 0 | NC7: 0 | ND7: 0 | NE7: 0 | NF7: 0 | NG7: 0 | NH7: 0 | NI7: 0 | NJ7: 0 | NK7: 0 | NL7: 0 | NM7: 0 | NN7: 0 | NO7: 0 | NP7: 0 | NQ7: 0 | NR7: 0 | NS7: 0 | NT7: 0 | NU7: 0 | NV7: 0 | NW7: 0 | NX7: 0 | NY7: 0 | NZ7: 0 | OA7: 0 | OB7: 0 | OC7: 0 | OD7: 0 | OE7: 0 | OF7: 0 | OG7: 0 | OH7: 0 | OI7: 0 | OJ7: 0 | OK7: 0 | OL7: 0.034192 | OM7: 0 | ON7: 0 | OO7: 0.00034 | OP7: 0.001303 | OQ7: 5.97595
A8: 7 m_pfb | B8: 0 | C8: 0 | D8: 0 | E8: 0 | F8: 0 | G8: 0 | H8: 0 | I8: 0 | J8: 0 | K8: 0 | L8: 0 | M8: 0 | N8: 0 | O8: 0 | P8: 0 | Q8: 0 | R8: 0 | S8: 0 | T8: 0 | U8: 0 | V8: 0 | W8: 0 | X8: 0 | Y8: 0 | Z8: 0 | AA8: 0 | AB8: 0 | AC8: 0 | AD8: 0 | AE8: 0 | AF8: 0 | AG8: 0 | AH8: 0 | AI8: 0 | AJ8: 0 | AK8: 0 | AL8: 0 | AM8: 0 | AN8: 0 | AO8: 0 | AP8: 0 | AQ8: 0 | AR8: 0 | AS8: 0 | AT8: 0 | AU8: 0 | AV8: 0 | AW8: 0 | AX8: 0 | AY8: 0 | AZ8: 0 | BA8: 0 | BB8: 0 | BC8: 0 | BD8: 0 | BE8: 0 | BF8: 0 | BG8: 0 | BH8: 0 | BI8: 0 | BJ8: 0 | BK8: 0 | BL8: 0 | BM8: 0 | BN8: 0 | BO8: 0 | BP8: 0 | BQ8: 0 | BR8: 0 | BS8: 0 | BT8: 0 | BU8: 0 | BV8: 0 | BW8: 0 | BX8: 0 | BY8: 0 | BZ8: 0 | CA8: 0 | CB8: 0 | CC8: 0 | CD8: 0 | CE8: 0 | CF8: 0 | CG8: 0 | CH8: 0 | CI8: 0 | CJ8: 0 | CK8: 0 | CL8: 0 | CM8: 0 | CN8: 0 | CO8: 0 | CP8: 0 | CQ8: 0 | CR8: 0 | CS8: 0 | CT8: 0 | CU8: 0 | CV8: 0 | CW8: 0 | CX8: 0 | CY8: 0 | CZ8: 0 | DA8: 0 | DB8: 0 | DC8: 0 | DD8: 0 | DE8: 0 | DF8: 0 | DG8: 0 | DH8: 0 | DI8: 0 | DJ8: 0 | DK8: 0 | DL8: 0 | DM8: 0 | DN8: 0 | DO8: 0 | DP8: 0 | DQ8: 0 | DR8: 0 | DS8: 0 | DT8: 0 | DU8: 0 | DV8: 0 | DW8: 0 | DX8: 0 | DY8: 0 | DZ8: 0 | EA8: 0 | EB8: 0 | EC8: 0 | ED8: 0 | EE8: 0 | EF8: 0 | EG8: 0 | EH8: 0 | EI8: 0 | EJ8: 0 | EK8: 0 | EL8: 0 | EM8: 0 | EN8: 0 | EO8: 0 | EP8: 0 | EQ8: 0 | ER8: 0 | ES8: 0 | ET8: 0 | EU8: 0 | EV8: 0 | EW8: 0 | EX8: 0.004191 | EY8: 0.016412 | EZ8: 0.01877 | FA8: 0.056067 | FB8: 0.01965 | FC8: 4.6e-05 | FD8: 2.474076 | FE8: 0.000614 | FF8: 0.037554 | FG8: 0.022966 | FH8: 0.022845 | FI8: 1.3e-05 | FJ8: 0.002597 | FK8: 0.001689 | FL8: 0.000143 | FM8: 0.000203 | FN8: 0.000874 | FO8: 0.000327 | FP8: 1.188532 | FQ8: 1.075333 | FR8: 0.378811 | FS8: 1.873234 | FT8: 0.022419 | FU8: 0.347623 | FV8: 8.023641 | FW8: 1.376144 | FX8: 48.632614 | FY8: 0.201228 | FZ8: 0.129677 | GA8: 0.029455 | GB8: 0.00693 | GC8: 0.000139 | GD8: 0.917453 | GE8: 0.145562 | GF8: 0.415423 | GG8: 0.002711 | GH8: 2e-06 | GI8: 0 | GJ8: 0.00259 | GK8: 0.000835 | GL8: 0.000216 | GM8: 0.000365 | GN8: 6e-06 | GO8: 3e-06 | GP8: 0.129821 | GQ8: 8.2e-05 | GR8: 5.3e-05 | GS8: 6e-05 | GT8: 9e-06 | GU8: 1.2e-05 | GV8: 4e-06 | GW8: 0 | GX8: 3e-06 | GY8: 7e-06 | GZ8: 0 | HA8: 5e-06 | HB8: 1e-06 | HC8: 0.001414 | HD8: 0.018036 | HE8: 0.20049 | HF8: 0.62297 | HG8: 0.368278 | HH8: 0.00087 | HI8: 0.00019 | HJ8: 9e-06 | HK8: 0.001013 | HL8: 0.004571 | HM8: 0.004766 | HN8: 0.00402 | HO8: 0.003259 | HP8: 0.147292 | HQ8: 0.093463 | HR8: 0.298489 | HS8: 0.297338 | HT8: 0.491199 | HU8: 0.041836 | HV8: 0 | HW8: 0 | HX8: 0 | HY8: 0 | HZ8: 0 | IA8: 0 | IB8: 0 | IC8: 0 | ID8: 0 | IE8: 0 | IF8: 0 | IG8: 0 | IH8: 0 | II8: 0 | IJ8: 0 | IK8: 0 | IL8: 0 | IM8: 0 | IN8: 0 | IO8: 0 | IP8: 0 | IQ8: 0 | IR8: 0 | IS8: 0 | IT8: 0 | IU8: 0 | IV8: 0 | IW8: 0 | IX8: 0 | IY8: 0 | IZ8: 0 | JA8: 0 | JB8: 0 | JC8: 0 | JD8: 0 | JE8: 0 | JF8: 0 | JG8: 0 | JH8: 0 | JI8: 0 | JJ8: 0 | JK8: 0 | JL8: 0 | JM8: 0 | JN8: 0 | JO8: 0 | JP8: 0 | JQ8: 0 | JR8: 0 | JS8: 0 | JT8: 0 | JU8: 0 | JV8: 0 | JW8: 0 | JX8: 0 | JY8: 0 | JZ8: 0 | KA8: 0 | KB8: 0 | KC8: 0 | KD8: 0 | KE8: 0 | KF8: 0 | KG8: 0 | KH8: 0 | KI8: 0 | KJ8: 0 | KK8: 0 | KL8: 0 | KM8: 0 | KN8: 0 | KO8: 0 | KP8: 0 | KQ8: 0 | KR8: 0 | KS8: 0 | KT8: 0 | KU8: 0 | KV8: 0 | KW8: 0 | KX8: 0 | KY8: 0 | KZ8: 0 | LA8: 0 | LB8: 0 | LC8: 0 | LD8: 0 | LE8: 0 | LF8: 0 | LG8: 0 | LH8: 0 | LI8: 0 | LJ8: 0 | LK8: 0 | LL8: 0 | LM8: 0 | LN8: 0 | LO8: 0 | LP8: 0 | LQ8: 0 | LR8: 0 | LS8: 0 | LT8: 0 | LU8: 0 | LV8: 0 | LW8: 0 | LX8: 0 | LY8: 0 | LZ8: 0 | MA8: 0 | MB8: 0 | MC8: 0 | MD8: 0 | ME8: 0 | MF8: 0 | MG8: 0 | MH8: 0 | MI8: 0 | MJ8: 0 | MK8: 0 | ML8: 0 | MM8: 0 | MN8: 0 | MO8: 0 | MP8: 0 | MQ8: 0 | MR8: 0 | MS8: 0 | MT8: 0 | MU8: 0 | MV8: 0 | MW8: 0 | MX8: 0 | MY8: 0 | MZ8: 0 | NA8: 0 | NB8: 0 | NC8: 0 | ND8: 0 | NE8: 0 | NF8: 0 | NG8: 0 | NH8: 0 | NI8: 0 | NJ8: 0 | NK8: 0 | NL8: 0 | NM8: 0 | NN8: 0 | NO8: 0 | NP8: 0 | NQ8: 0 | NR8: 0 | NS8: 0 | NT8: 0 | NU8: 0 | NV8: 0 | NW8: 0 | NX8: 0 | NY8: 0 | NZ8: 0 | OA8: 0 | OB8: 0 | OC8: 0 | OD8: 0 | OE8: 0 | OF8: 0 | OG8: 0 | OH8: 0 | OI8: 0 | OJ8: 0 | OK8: 0 | OL8: 73.654938 | OM8: 0 | ON8: 0 | OO8: 0.000656 | OP8: 2.678479 | OQ8: 146.51361
A9: 8 m_ocr | B9: 0 | C9: 0 | D9: 0 | E9: 0 | F9: 0 | G9: 0 | H9: 0 | I9: 0 | J9: 0 | K9: 0 | L9: 0 | M9: 0 | N9: 0 | O9: 0 | P9: 0 | Q9: 0 | R9: 0 | S9: 0 | T9: 0 | U9: 0 | V9: 0 | W9: 0 | X9: 0 | Y9: 0 | Z9: 0 | AA9: 0 | AB9: 0 | AC9: 0 | AD9: 0 | AE9: 0 | AF9: 0 | AG9: 0 | AH9: 0 | AI9: 0 | AJ9: 0 | AK9: 0 | AL9: 0 | AM9: 0 | AN9: 0 | AO9: 0 | AP9: 0 | AQ9: 0 | AR9: 0 | AS9: 0 | AT9: 0 | AU9: 0 | AV9: 0 | AW9: 0 | AX9: 0 | AY9: 0 | AZ9: 0 | BA9: 0 | BB9: 0 | BC9: 0 | BD9: 0 | BE9: 0 | BF9: 0 | BG9: 0 | BH9: 0 | BI9: 0 | BJ9: 0 | BK9: 0 | BL9: 0 | BM9: 0 | BN9: 0 | BO9: 0 | BP9: 0 | BQ9: 0 | BR9: 0 | BS9: 0 | BT9: 0 | BU9: 0 | BV9: 0 | BW9: 0 | BX9: 0 | BY9: 0 | BZ9: 0 | CA9: 0 | CB9: 0 | CC9: 0 | CD9: 0 | CE9: 0 | CF9: 0 | CG9: 0 | CH9: 0 | CI9: 0 | CJ9: 0 | CK9: 0 | CL9: 0 | CM9: 0 | CN9: 0 | CO9: 0 | CP9: 0 | CQ9: 0 | CR9: 0 | CS9: 0 | CT9: 0 | CU9: 0 | CV9: 0 | CW9: 0 | CX9: 0 | CY9: 0 | CZ9: 0 | DA9: 0 | DB9: 0 | DC9: 0 | DD9: 0 | DE9: 0 | DF9: 0 | DG9: 0 | DH9: 0 | DI9: 0 | DJ9: 0 | DK9: 0 | DL9: 0 | DM9: 0 | DN9: 0 | DO9: 0 | DP9: 0 | DQ9: 0 | DR9: 0 | DS9: 0 | DT9: 0 | DU9: 0 | DV9: 0 | DW9: 0 | DX9: 0 | DY9: 0 | DZ9: 0 | EA9: 0 | EB9: 0 | EC9: 0 | ED9: 0 | EE9: 0 | EF9: 0 | EG9: 0 | EH9: 0 | EI9: 0 | EJ9: 0 | EK9: 0 | EL9: 0 | EM9: 0 | EN9: 0 | EO9: 0 | EP9: 0 | EQ9: 0 | ER9: 0 | ES9: 0 | ET9: 0 | EU9: 0 | EV9: 0 | EW9: 0 | EX9: 0.043855 | EY9: 0.141674 | EZ9: 139.07692 | FA9: 21.418362 | FB9: 2.129413 | FC9: 0.045036 | FD9: 0.04366 | FE9: 130.15205 | FF9: 13.073321 | FG9: 11.161088 | FH9: 12.949824 | FI9: 0.013052 | FJ9: 17.189631 | FK9: 0.005122 | FL9: 0.038562 | FM9: 0.132154 | FN9: 0.017109 | FO9: 0.031727 | FP9: 9.114198 | FQ9: 6.690672 | FR9: 180.07349 | FS9: 9.745085 | FT9: 0.232488 | FU9: 3.562186 | FV9: 1470.8158 | FW9: 457.15939 | FX9: 72.088058 | FY9: 0.783049 | FZ9: 0.114989 | GA9: 0.923138 | GB9: 1.70379 | GC9: 1.068017 | GD9: 4.100191 | GE9: 16.502026 | GF9: 205.4779 | GG9: 0.141359 | GH9: 0.069557 | GI9: 1.675024 | GJ9: 0.487304 | GK9: 0.654075 | GL9: 0.019739 | GM9: 0.054095 | GN9: 0.174094 | GO9: 0.155388 | GP9: 56.724777 | GQ9: 0.067717 | GR9: 0.044353 | GS9: 0.04967 | GT9: 0.007172 | GU9: 0.010381 | GV9: 0.003232 | GW9: 0 | GX9: 0.002168 | GY9: 0.005551 | GZ9: 0 | HA9: 0.004557 | HB9: 0.000649 | HC9: 0.052866 | HD9: 0.19352 | HE9: 807.03845 | HF9: 42.395824 | HG9: 108.75184 | HH9: 0.224449 | HI9: 0.082693 | HJ9: 0.187697 | HK9: 0.5484 | HL9: 45.173382 | HM9: 3.47982 | HN9: 1.249956 | HO9: 38.288441 | HP9: 2173.2725 | HQ9: 191.85152 | HR9: 90.810196 | HS9: 50.368267 | HT9: 105.80873 | HU9: 22.461918 | HV9: 0 | HW9: 0 | HX9: 0 | HY9: 0 | HZ9: 0 | IA9: 0 | IB9: 0 | IC9: 0 | ID9: 0 | IE9: 0 | IF9: 0 | IG9: 0 | IH9: 0 | II9: 0 | IJ9: 0 | IK9: 0 | IL9: 0 | IM9: 0 | IN9: 0 | IO9: 0 | IP9: 0 | IQ9: 0 | IR9: 0 | IS9: 0 | IT9: 0 | IU9: 0 | IV9: 0 | IW9: 0 | IX9: 0 | IY9: 0 | IZ9: 0 | JA9: 0 | JB9: 0 | JC9: 0 | JD9: 0 | JE9: 0 | JF9: 0 | JG9: 0 | JH9: 0 | JI9: 0 | JJ9: 0 | JK9: 0 | JL9: 0 | JM9: 0 | JN9: 0 | JO9: 0 | JP9: 0 | JQ9: 0 | JR9: 0 | JS9: 0 | JT9: 0 | JU9: 0 | JV9: 0 | JW9: 0 | JX9: 0 | JY9: 0 | JZ9: 0 | KA9: 0 | KB9: 0 | KC9: 0 | KD9: 0 | KE9: 0 | KF9: 0 | KG9: 0 | KH9: 0 | KI9: 0 | KJ9: 0 | KK9: 0 | KL9: 0 | KM9: 0 | KN9: 0 | KO9: 0 | KP9: 0 | KQ9: 0 | KR9: 0 | KS9: 0 | KT9: 0 | KU9: 0 | KV9: 0 | KW9: 0 | KX9: 0 | KY9: 0 | KZ9: 0 | LA9: 0 | LB9: 0 | LC9: 0 | LD9: 0 | LE9: 0 | LF9: 0 | LG9: 0 | LH9: 0 | LI9: 0 | LJ9: 0 | LK9: 0 | LL9: 0 | LM9: 0 | LN9: 0 | LO9: 0 | LP9: 0 | LQ9: 0 | LR9: 0 | LS9: 0 | LT9: 0 | LU9: 0 | LV9: 0 | LW9: 0 | LX9: 0 | LY9: 0 | LZ9: 0 | MA9: 0 | MB9: 0 | MC9: 0 | MD9: 0 | ME9: 0 | MF9: 0 | MG9: 0 | MH9: 0 | MI9: 0 | MJ9: 0 | MK9: 0 | ML9: 0 | MM9: 0 | MN9: 0 | MO9: 0 | MP9: 0 | MQ9: 0 | MR9: 0 | MS9: 0 | MT9: 0 | MU9: 0 | MV9: 0 | MW9: 0 | MX9: 0 | MY9: 0 | MZ9: 0 | NA9: 0 | NB9: 0 | NC9: 0 | ND9: 0 | NE9: 0 | NF9: 0 | NG9: 0 | NH9: 0 | NI9: 0 | NJ9: 0 | NK9: 0 | NL9: 0 | NM9: 0 | NN9: 0 | NO9: 0 | NP9: 0 | NQ9: 0 | NR9: 0 | NS9: 0 | NT9: 0 | NU9: 0 | NV9: 0 | NW9: 0 | NX9: 0 | NY9: 0 | NZ9: 0 | OA9: 0 | OB9: 0 | OC9: 0 | OD9: 0 | OE9: 0 | OF9: 0 | OG9: 0 | OH9: 0 | OI9: 0 | OJ9: 0 | OK9: 0 | OL9: 4077.4011 | OM9: 0 | ON9: 0 | OO9: 0.157147 | OP9: 1.323498 | OQ9: 10609.29
A10: 9 m_ctl | B10: 0 | C10: 0 | D10: 0 | E10: 0 | F10: 0 | G10: 0 | H10: 0 | I10: 0 | J10: 0 | K10: 0 | L10: 0 | M10: 0 | N10: 0 | O10: 0 | P10: 0 | Q10: 0 | R10: 0 | S10: 0 | T10: 0 | U10: 0 | V10: 0 | W10: 0 | X10: 0 | Y10: 0 | Z10: 0 | AA10: 0 | AB10: 0 | AC10: 0 | AD10: 0 | AE10: 0 | AF10: 0 | AG10: 0 | AH10: 0 | AI10: 0 | AJ10: 0 | AK10: 0 | AL10: 0 | AM10: 0 | AN10: 0 | AO10: 0 | AP10: 0 | AQ10: 0 | AR10: 0 | AS10: 0 | AT10: 0 | AU10: 0 | AV10: 0 | AW10: 0 | AX10: 0 | AY10: 0 | AZ10: 0 | BA10: 0 | BB10: 0 | BC10: 0 | BD10: 0 | BE10: 0 | BF10: 0 | BG10: 0 | BH10: 0 | BI10: 0 | BJ10: 0 | BK10: 0 | BL10: 0 | BM10: 0 | BN10: 0 | BO10: 0 | BP10: 0 | BQ10: 0 | BR10: 0 | BS10: 0 | BT10: 0 | BU10: 0 | BV10: 0 | BW10: 0 | BX10: 0 | BY10: 0 | BZ10: 0 | CA10: 0 | CB10: 0 | CC10: 0 | CD10: 0 | CE10: 0 | CF10: 0 | CG10: 0 | CH10: 0 | CI10: 0 | CJ10: 0 | CK10: 0 | CL10: 0 | CM10: 0 | CN10: 0 | CO10: 0 | CP10: 0 | CQ10: 0 | CR10: 0 | CS10: 0 | CT10: 0 | CU10: 0 | CV10: 0 | CW10: 0 | CX10: 0 | CY10: 0 | CZ10: 0 | DA10: 0 | DB10: 0 | DC10: 0 | DD10: 0 | DE10: 0 | DF10: 0 | DG10: 0 | DH10: 0 | DI10: 0 | DJ10: 0 | DK10: 0 | DL10: 0 | DM10: 0 | DN10: 0 | DO10: 0 | DP10: 0 | DQ10: 0 | DR10: 0 | DS10: 0 | DT10: 0 | DU10: 0 | DV10: 0 | DW10: 0 | DX10: 0 | DY10: 0 | DZ10: 0 | EA10: 0 | EB10: 0 | EC10: 0 | ED10: 0 | EE10: 0 | EF10: 0 | EG10: 0 | EH10: 0 | EI10: 0 | EJ10: 0 | EK10: 0 | EL10: 0 | EM10: 0 | EN10: 0 | EO10: 0 | EP10: 0 | EQ10: 0 | ER10: 0 | ES10: 0 | ET10: 0 | EU10: 0 | EV10: 0 | EW10: 0 | EX10: 6.9e-05 | EY10: 2.8e-05 | EZ10: 7.7e-05 | FA10: 0.000534 | FB10: 0.000244 | FC10: 1.5e-05 | FD10: 3.8e-05 | FE10: 0.000686 | FF10: 327.88211 | FG10: 0.001694 | FH10: 0.000201 | FI10: 0.557103 | FJ10: 0.00015 | FK10: 0.023345 | FL10: 4e-06 | FM10: 4e-06 | FN10: 3e-06 | FO10: 1e-06 | FP10: 2517.7185 | FQ10: 100.77512 | FR10: 0.000362 | FS10: 0.067932 | FT10: 9.3e-05 | FU10: 0.000187 | FV10: 4.360673 | FW10: 0.037996 | FX10: 0.926544 | FY10: 0.021391 | FZ10: 5.449371 | GA10: 0.005903 | GB10: 0.005366 | GC10: 1e-06 | GD10: 0.004133 | GE10: 0.176494 | GF10: 0.000375 | GG10: 0.002215 | GH10: 1e-06 | GI10: 4e-06 | GJ10: 0.000343 | GK10: 0.001889 | GL10: 0.00036 | GM10: 0.000704 | GN10: 4e-06 | GO10: 5.2e-05 | GP10: 0.145875 | GQ10: 1.3e-05 | GR10: 9e-06 | GS10: 1e-05 | GT10: 1e-06 | GU10: 2e-06 | GV10: 1e-06 | GW10: 0 | GX10: 0 | GY10: 1e-06 | GZ10: 0 | HA10: 1e-06 | HB10: 0 | HC10: 0.000119 | HD10: 6.2e-05 | HE10: 0.000167 | HF10: 0.172382 | HG10: 16.302769 | HH10: 0.00278 | HI10: 7e-06 | HJ10: 0.009227 | HK10: 0.002005 | HL10: 0.11687 | HM10: 1.7e-05 | HN10: 9e-06 | HO10: 0.098273 | HP10: 13.595312 | HQ10: 1.745246 | HR10: 4.2e-05 | HS10: 0.000617 | HT10: 0.018586 | HU10: 0.000105 | HV10: 0 | HW10: 0 | HX10: 0 | HY10: 0 | HZ10: 0 | IA10: 0 | IB10: 0 | IC10: 0 | ID10: 0 | IE10: 0 | IF10: 0 | IG10: 0 | IH10: 0 | II10: 0 | IJ10: 0 | IK10: 0 | IL10: 0 | IM10: 0 | IN10: 0 | IO10: 0 | IP10: 0 | IQ10: 0 | IR10: 0 | IS10: 0 | IT10: 0 | IU10: 0 | IV10: 0 | IW10: 0 | IX10: 0 | IY10: 0 | IZ10: 0 | JA10: 0 | JB10: 0 | JC10: 0 | JD10: 0 | JE10: 0 | JF10: 0 | JG10: 0 | JH10: 0 | JI10: 0 | JJ10: 0 | JK10: 0 | JL10: 0 | JM10: 0 | JN10: 0 | JO10: 0 | JP10: 0 | JQ10: 0 | JR10: 0 | JS10: 0 | JT10: 0 | JU10: 0 | JV10: 0 | JW10: 0 | JX10: 0 | JY10: 0 | JZ10: 0 | KA10: 0 | KB10: 0 | KC10: 0 | KD10: 0 | KE10: 0 | KF10: 0 | KG10: 0 | KH10: 0 | KI10: 0 | KJ10: 0 | KK10: 0 | KL10: 0 | KM10: 0 | KN10: 0 | KO10: 0 | KP10: 0 | KQ10: 0 | KR10: 0 | KS10: 0 | KT10: 0 | KU10: 0 | KV10: 0 | KW10: 0 | KX10: 0 | KY10: 0 | KZ10: 0 | LA10: 0 | LB10: 0 | LC10: 0 | LD10: 0 | LE10: 0 | LF10: 0 | LG10: 0 | LH10: 0 | LI10: 0 | LJ10: 0 | LK10: 0 | LL10: 0 | LM10: 0 | LN10: 0 | LO10: 0 | LP10: 0 | LQ10: 0 | LR10: 0 | LS10: 0 | LT10: 0 | LU10: 0 | LV10: 0 | LW10: 0 | LX10: 0 | LY10: 0 | LZ10: 0 | MA10: 0 | MB10: 0 | MC10: 0 | MD10: 0 | ME10: 0 | MF10: 0 | MG10: 0 | MH10: 0 | MI10: 0 | MJ10: 0 | MK10: 0 | ML10: 0 | MM10: 0 | MN10: 0 | MO10: 0 | MP10: 0 | MQ10: 0 | MR10: 0 | MS10: 0 | MT10: 0 | MU10: 0 | MV10: 0 | MW10: 0 | MX10: 0 | MY10: 0 | MZ10: 0 | NA10: 0 | NB10: 0 | NC10: 0 | ND10: 0 | NE10: 0 | NF10: 0 | NG10: 0 | NH10: 0 | NI10: 0 | NJ10: 0 | NK10: 0 | NL10: 0 | NM10: 0 | NN10: 0 | NO10: 0 | NP10: 0 | NQ10: 0 | NR10: 0 | NS10: 0 | NT10: 0 | NU10: 0 | NV10: 0 | NW10: 0 | NX10: 0 | NY10: 0 | NZ10: 0 | OA10: 0 | OB10: 0 | OC10: 0 | OD10: 0 | OE10: 0 | OF10: 0 | OG10: 0 | OH10: 0 | OI10: 0 | OJ10: 0 | OK10: 0 | OL10: 2.996736 | OM10: 0 | ON10: 0 | OO10: 5.2e-05 | OP10: 4.525798 | OQ10: 2997.7554
A11: 10 m_oap | B11: 0 | C11: 0 | D11: 0 | E11: 0 | F11: 0 | G11: 0 | H11: 0 | I11: 0 | J11: 0 | K11: 0 | L11: 0 | M11: 0 | N11: 0 | O11: 0 | P11: 0 | Q11: 0 | R11: 0 | S11: 0 | T11: 0 | U11: 0 | V11: 0 | W11: 0 | X11: 0 | Y11: 0 | Z11: 0 | AA11: 0 | AB11: 0 | AC11: 0 | AD11: 0 | AE11: 0 | AF11: 0 | AG11: 0 | AH11: 0 | AI11: 0 | AJ11: 0 | AK11: 0 | AL11: 0 | AM11: 0 | AN11: 0 | AO11: 0 | AP11: 0 | AQ11: 0 | AR11: 0 | AS11: 0 | AT11: 0 | AU11: 0 | AV11: 0 | AW11: 0 | AX11: 0 | AY11: 0 | AZ11: 0 | BA11: 0 | BB11: 0 | BC11: 0 | BD11: 0 | BE11: 0 | BF11: 0 | BG11: 0 | BH11: 0 | BI11: 0 | BJ11: 0 | BK11: 0 | BL11: 0 | BM11: 0 | BN11: 0 | BO11: 0 | BP11: 0 | BQ11: 0 | BR11: 0 | BS11: 0 | BT11: 0 | BU11: 0 | BV11: 0 | BW11: 0 | BX11: 0 | BY11: 0 | BZ11: 0 | CA11: 0 | CB11: 0 | CC11: 0 | CD11: 0 | CE11: 0 | CF11: 0 | CG11: 0 | CH11: 0 | CI11: 0 | CJ11: 0 | CK11: 0 | CL11: 0 | CM11: 0 | CN11: 0 | CO11: 0 | CP11: 0 | CQ11: 0 | CR11: 0 | CS11: 0 | CT11: 0 | CU11: 0 | CV11: 0 | CW11: 0 | CX11: 0 | CY11: 0 | CZ11: 0 | DA11: 0 | DB11: 0 | DC11: 0 | DD11: 0 | DE11: 0 | DF11: 0 | DG11: 0 | DH11: 0 | DI11: 0 | DJ11: 0 | DK11: 0 | DL11: 0 | DM11: 0 | DN11: 0 | DO11: 0 | DP11: 0 | DQ11: 0 | DR11: 0 | DS11: 0 | DT11: 0 | DU11: 0 | DV11: 0 | DW11: 0 | DX11: 0 | DY11: 0 | DZ11: 0 | EA11: 0 | EB11: 0 | EC11: 0 | ED11: 0 | EE11: 0 | EF11: 0 | EG11: 0 | EH11: 0 | EI11: 0 | EJ11: 0 | EK11: 0 | EL11: 0 | EM11: 0 | EN11: 0 | EO11: 0 | EP11: 0 | EQ11: 0 | ER11: 0 | ES11: 0 | ET11: 0 | EU11: 0 | EV11: 0 | EW11: 0 | EX11: 0.000105 | EY11: 0.000275 | EZ11: 0.000727 | FA11: 0.000918 | FB11: 0.006262 | FC11: 3.9e-05 | FD11: 0.000496 | FE11: 0.003477 | FF11: 0.002382 | FG11: 168.66248 | FH11: 0.000438 | FI11: 0.11506 | FJ11: 55.090977 | FK11: 0.028088 | FL11: 1e-06 | FM11: 4.9e-05 | FN11: 5e-06 | FO11: 0.000544 | FP11: 44.024342 | FQ11: 97.80246 | FR11: 0.157015 | FS11: 7.61903 | FT11: 0.005423 | FU11: 0.0401 | FV11: 686.54962 | FW11: 2.163389 | FX11: 238.38318 | FY11: 10.03979 | FZ11: 0.450977 | GA11: 0.033367 | GB11: 0.163608 | GC11: 0.024955 | GD11: 1.008929 | GE11: 49.819275 | GF11: 0.037888 | GG11: 0.009897 | GH11: 4e-06 | GI11: 0.017943 | GJ11: 0.095453 | GK11: 0.026688 | GL11: 0.008759 | GM11: 0.019049 | GN11: 0.003567 | GO11: 3e-05 | GP11: 4.796813 | GQ11: 5.6e-05 | GR11: 3.6e-05 | GS11: 4.1e-05 | GT11: 6e-06 | GU11: 9e-06 | GV11: 3e-06 | GW11: 0 | GX11: 2e-06 | GY11: 5e-06 | GZ11: 0 | HA11: 4e-06 | HB11: 1e-06 | HC11: 2.6e-05 | HD11: 0.00091 | HE11: 0.007148 | HF11: 0.02114 | HG11: 6.786994 | HH11: 5.5e-05 | HI11: 0.000136 | HJ11: 0 | HK11: 0.001822 | HL11: 0.548725 | HM11: 0.416582 | HN11: 3.7e-05 | HO11: 1.037794 | HP11: 52.140011 | HQ11: 37.589687 | HR11: 0.084513 | HS11: 0.024384 | HT11: 20.240368 | HU11: 0.020544 | HV11: 0 | HW11: 0 | HX11: 0 | HY11: 0 | HZ11: 0 | IA11: 0 | IB11: 0 | IC11: 0 | ID11: 0 | IE11: 0 | IF11: 0 | IG11: 0 | IH11: 0 | II11: 0 | IJ11: 0 | IK11: 0 | IL11: 0 | IM11: 0 | IN11: 0 | IO11: 0 | IP11: 0 | IQ11: 0 | IR11: 0 | IS11: 0 | IT11: 0 | IU11: 0 | IV11: 0 | IW11: 0 | IX11: 0 | IY11: 0 | IZ11: 0 | JA11: 0 | JB11: 0 | JC11: 0 | JD11: 0 | JE11: 0 | JF11: 0 | JG11: 0 | JH11: 0 | JI11: 0 | JJ11: 0 | JK11: 0 | JL11: 0 | JM11: 0 | JN11: 0 | JO11: 0 | JP11: 0 | JQ11: 0 | JR11: 0 | JS11: 0 | JT11: 0 | JU11: 0 | JV11: 0 | JW11: 0 | JX11: 0 | JY11: 0 | JZ11: 0 | KA11: 0 | KB11: 0 | KC11: 0 | KD11: 0 | KE11: 0 | KF11: 0 | KG11: 0 | KH11: 0 | KI11: 0 | KJ11: 0 | KK11: 0 | KL11: 0 | KM11: 0 | KN11: 0 | KO11: 0 | KP11: 0 | KQ11: 0 | KR11: 0 | KS11: 0 | KT11: 0 | KU11: 0 | KV11: 0 | KW11: 0 | KX11: 0 | KY11: 0 | KZ11: 0 | LA11: 0 | LB11: 0 | LC11: 0 | LD11: 0 | LE11: 0 | LF11: 0 | LG11: 0 | LH11: 0 | LI11: 0 | LJ11: 0 | LK11: 0 | LL11: 0 | LM11: 0 | LN11: 0 | LO11: 0 | LP11: 0 | LQ11: 0 | LR11: 0 | LS11: 0 | LT11: 0 | LU11: 0 | LV11: 0 | LW11: 0 | LX11: 0 | LY11: 0 | LZ11: 0 | MA11: 0 | MB11: 0 | MC11: 0 | MD11: 0 | ME11: 0 | MF11: 0 | MG11: 0 | MH11: 0 | MI11: 0 | MJ11: 0 | MK11: 0 | ML11: 0 | MM11: 0 | MN11: 0 | MO11: 0 | MP11: 0 | MQ11: 0 | MR11: 0 | MS11: 0 | MT11: 0 | MU11: 0 | MV11: 0 | MW11: 0 | MX11: 0 | MY11: 0 | MZ11: 0 | NA11: 0 | NB11: 0 | NC11: 0 | ND11: 0 | NE11: 0 | NF11: 0 | NG11: 0 | NH11: 0 | NI11: 0 | NJ11: 0 | NK11: 0 | NL11: 0 | NM11: 0 | NN11: 0 | NO11: 0 | NP11: 0 | NQ11: 0 | NR11: 0 | NS11: 0 | NT11: 0 | NU11: 0 | NV11: 0 | NW11: 0 | NX11: 0 | NY11: 0 | NZ11: 0 | OA11: 0 | OB11: 0 | OC11: 0 | OD11: 0 | OE11: 0 | OF11: 0 | OG11: 0 | OH11: 0 | OI11: 0 | OJ11: 0 | OK11: 0 | OL11: 1052.9811 | OM11: 0 | ON11: 0 | OO11: 0.001428 | OP11: 9.229697 | OQ11: 2548.3471
A12: 11 m_rmk | B12: 0 | C12: 0 | D12: 0 | E12: 0 | F12: 0 | G12: 0 | H12: 0 | I12: 0 | J12: 0 | K12: 0 | L12: 0 | M12: 0 | N12: 0 | O12: 0 | P12: 0 | Q12: 0 | R12: 0 | S12: 0 | T12: 0 | U12: 0 | V12: 0 | W12: 0 | X12: 0 | Y12: 0 | Z12: 0 | AA12: 0 | AB12: 0 | AC12: 0 | AD12: 0 | AE12: 0 | AF12: 0 | AG12: 0 | AH12: 0 | AI12: 0 | AJ12: 0 | AK12: 0 | AL12: 0 | AM12: 0 | AN12: 0 | AO12: 0 | AP12: 0 | AQ12: 0 | AR12: 0 | AS12: 0 | AT12: 0 | AU12: 0 | AV12: 0 | AW12: 0 | AX12: 0 | AY12: 0 | AZ12: 0 | BA12: 0 | BB12: 0 | BC12: 0 | BD12: 0 | BE12: 0 | BF12: 0 | BG12: 0 | BH12: 0 | BI12: 0 | BJ12: 0 | BK12: 0 | BL12: 0 | BM12: 0 | BN12: 0 | BO12: 0 | BP12: 0 | BQ12: 0 | BR12: 0 | BS12: 0 | BT12: 0 | BU12: 0 | BV12: 0 | BW12: 0 | BX12: 0 | BY12: 0 | BZ12: 0 | CA12: 0 | CB12: 0 | CC12: 0 | CD12: 0 | CE12: 0 | CF12: 0 | CG12: 0 | CH12: 0 | CI12: 0 | CJ12: 0 | CK12: 0 | CL12: 0 | CM12: 0 | CN12: 0 | CO12: 0 | CP12: 0 | CQ12: 0 | CR12: 0 | CS12: 0 | CT12: 0 | CU12: 0 | CV12: 0 | CW12: 0 | CX12: 0 | CY12: 0 | CZ12: 0 | DA12: 0 | DB12: 0 | DC12: 0 | DD12: 0 | DE12: 0 | DF12: 0 | DG12: 0 | DH12: 0 | DI12: 0 | DJ12: 0 | DK12: 0 | DL12: 0 | DM12: 0 | DN12: 0 | DO12: 0 | DP12: 0 | DQ12: 0 | DR12: 0 | DS12: 0 | DT12: 0 | DU12: 0 | DV12: 0 | DW12: 0 | DX12: 0 | DY12: 0 | DZ12: 0 | EA12: 0 | EB12: 0 | EC12: 0 | ED12: 0 | EE12: 0 | EF12: 0 | EG12: 0 | EH12: 0 | EI12: 0 | EJ12: 0 | EK12: 0 | EL12: 0 | EM12: 0 | EN12: 0 | EO12: 0 | EP12: 0 | EQ12: 0 | ER12: 0 | ES12: 0 | ET12: 0 | EU12: 0 | EV12: 0 | EW12: 0 | EX12: 0 | EY12: 7e-06 | EZ12: 1.7e-05 | FA12: 1e-06 | FB12: 1e-06 | FC12: 1e-06 | FD12: 0 | FE12: 0.000121 | FF12: 8e-06 | FG12: 1.3e-05 | FH12: 0.001156 | FI12: 0 | FJ12: 0 | FK12: 2e-06 | FL12: 0 | FM12: 0 | FN12: 0 | FO12: 0 | FP12: 0.002214 | FQ12: 0.034178 | FR12: 4e-06 | FS12: 41.413212 | FT12: 0 | FU12: 1e-06 | FV12: 1.573156 | FW12: 0.239897 | FX12: 5e-05 | FY12: 3e-06 | FZ12: 8e-06 | GA12: 0 | GB12: 0 | GC12: 0 | GD12: 0.035061 | GE12: 0.008539 | GF12: 0.015067 | GG12: 0 | GH12: 0 | GI12: 0 | GJ12: 0 | GK12: 0 | GL12: 0 | GM12: 0 | GN12: 0 | GO12: 0 | GP12: 6e-06 | GQ12: 0 | GR12: 0 | GS12: 0 | GT12: 0 | GU12: 0 | GV12: 0 | GW12: 0 | GX12: 0 | GY12: 0 | GZ12: 0 | HA12: 0 | HB12: 0 | HC12: 0 | HD12: 1e-06 | HE12: 0 | HF12: 0.268873 | HG12: 0.120115 | HH12: 0 | HI12: 0 | HJ12: 0 | HK12: 0 | HL12: 1e-06 | HM12: 0 | HN12: 0 | HO12: 1e-06 | HP12: 1e-06 | HQ12: 2e-06 | HR12: 2.1e-05 | HS12: 0 | HT12: 0 | HU12: 1e-06 | HV12: 0 | HW12: 0 | HX12: 0 | HY12: 0 | HZ12: 0 | IA12: 0 | IB12: 0 | IC12: 0 | ID12: 0 | IE12: 0 | IF12: 0 | IG12: 0 | IH12: 0 | II12: 0 | IJ12: 0 | IK12: 0 | IL12: 0 | IM12: 0 | IN12: 0 | IO12: 0 | IP12: 0 | IQ12: 0 | IR12: 0 | IS12: 0 | IT12: 0 | IU12: 0 | IV12: 0 | IW12: 0 | IX12: 0 | IY12: 0 | IZ12: 0 | JA12: 0 | JB12: 0 | JC12: 0 | JD12: 0 | JE12: 0 | JF12: 0 | JG12: 0 | JH12: 0 | JI12: 0 | JJ12: 0 | JK12: 0 | JL12: 0 | JM12: 0 | JN12: 0 | JO12: 0 | JP12: 0 | JQ12: 0 | JR12: 0 | JS12: 0 | JT12: 0 | JU12: 0 | JV12: 0 | JW12: 0 | JX12: 0 | JY12: 0 | JZ12: 0 | KA12: 0 | KB12: 0 | KC12: 0 | KD12: 0 | KE12: 0 | KF12: 0 | KG12: 0 | KH12: 0 | KI12: 0 | KJ12: 0 | KK12: 0 | KL12: 0 | KM12: 0 | KN12: 0 | KO12: 0 | KP12: 0 | KQ12: 0 | KR12: 0 | KS12: 0 | KT12: 0 | KU12: 0 | KV12: 0 | KW12: 0 | KX12: 0 | KY12: 0 | KZ12: 0 | LA12: 0 | LB12: 0 | LC12: 0 | LD12: 0 | LE12: 0 | LF12: 0 | LG12: 0 | LH12: 0 | LI12: 0 | LJ12: 0 | LK12: 0 | LL12: 0 | LM12: 0 | LN12: 0 | LO12: 0 | LP12: 0 | LQ12: 0 | LR12: 0 | LS12: 0 | LT12: 0 | LU12: 0 | LV12: 0 | LW12: 0 | LX12: 0 | LY12: 0 | LZ12: 0 | MA12: 0 | MB12: 0 | MC12: 0 | MD12: 0 | ME12: 0 | MF12: 0 | MG12: 0 | MH12: 0 | MI12: 0 | MJ12: 0 | MK12: 0 | ML12: 0 | MM12: 0 | MN12: 0 | MO12: 0 | MP12: 0 | MQ12: 0 | MR12: 0 | MS12: 0 | MT12: 0 | MU12: 0 | MV12: 0 | MW12: 0 | MX12: 0 | MY12: 0 | MZ12: 0 | NA12: 0 | NB12: 0 | NC12: 0 | ND12: 0 | NE12: 0 | NF12: 0 | NG12: 0 | NH12: 0 | NI12: 0 | NJ12: 0 | NK12: 0 | NL12: 0 | NM12: 0 | NN12: 0 | NO12: 0 | NP12: 0 | NQ12: 0 | NR12: 0 | NS12: 0 | NT12: 0 | NU12: 0 | NV12: 0 | NW12: 0 | NX12: 0 | NY12: 0 | NZ12: 0 | OA12: 0 | OB12: 0 | OC12: 0 | OD12: 0 | OE12: 0 | OF12: 0 | OG12: 0 | OH12: 0 | OI12: 0 | OJ12: 0 | OK12: 0 | OL12: 0.005116 | OM12: 0 | ON12: 0 | OO12: 3e-06 | OP12: 3.4e-05 | OQ12: 43.716894
A13: 12 m_wol | B13: 0 | C13: 0 | D13: 0 | E13: 0 | F13: 0 | G13: 0 | H13: 0 | I13: 0 | J13: 0 | K13: 0 | L13: 0 | M13: 0 | N13: 0 | O13: 0 | P13: 0 | Q13: 0 | R13: 0 | S13: 0 | T13: 0 | U13: 0 | V13: 0 | W13: 0 | X13: 0 | Y13: 0 | Z13: 0 | AA13: 0 | AB13: 0 | AC13: 0 | AD13: 0 | AE13: 0 | AF13: 0 | AG13: 0 | AH13: 0 | AI13: 0 | AJ13: 0 | AK13: 0 | AL13: 0 | AM13: 0 | AN13: 0 | AO13: 0 | AP13: 0 | AQ13: 0 | AR13: 0 | AS13: 0 | AT13: 0 | AU13: 0 | AV13: 0 | AW13: 0 | AX13: 0 | AY13: 0 | AZ13: 0 | BA13: 0 | BB13: 0 | BC13: 0 | BD13: 0 | BE13: 0 | BF13: 0 | BG13: 0 | BH13: 0 | BI13: 0 | BJ13: 0 | BK13: 0 | BL13: 0 | BM13: 0 | BN13: 0 | BO13: 0 | BP13: 0 | BQ13: 0 | BR13: 0 | BS13: 0 | BT13: 0 | BU13: 0 | BV13: 0 | BW13: 0 | BX13: 0 | BY13: 0 | BZ13: 0 | CA13: 0 | CB13: 0 | CC13: 0 | CD13: 0 | CE13: 0 | CF13: 0 | CG13: 0 | CH13: 0 | CI13: 0 | CJ13: 0 | CK13: 0 | CL13: 0 | CM13: 0 | CN13: 0 | CO13: 0 | CP13: 0 | CQ13: 0 | CR13: 0 | CS13: 0 | CT13: 0 | CU13: 0 | CV13: 0 | CW13: 0 | CX13: 0 | CY13: 0 | CZ13: 0 | DA13: 0 | DB13: 0 | DC13: 0 | DD13: 0 | DE13: 0 | DF13: 0 | DG13: 0 | DH13: 0 | DI13: 0 | DJ13: 0 | DK13: 0 | DL13: 0 | DM13: 0 | DN13: 0 | DO13: 0 | DP13: 0 | DQ13: 0 | DR13: 0 | DS13: 0 | DT13: 0 | DU13: 0 | DV13: 0 | DW13: 0 | DX13: 0 | DY13: 0 | DZ13: 0 | EA13: 0 | EB13: 0 | EC13: 0 | ED13: 0 | EE13: 0 | EF13: 0 | EG13: 0 | EH13: 0 | EI13: 0 | EJ13: 0 | EK13: 0 | EL13: 0 | EM13: 0 | EN13: 0 | EO13: 0 | EP13: 0 | EQ13: 0 | ER13: 0 | ES13: 0 | ET13: 0 | EU13: 0 | EV13: 0 | EW13: 0 | EX13: 0.048949 | EY13: 0.20059 | EZ13: 0.88319 | FA13: 0.363753 | FB13: 3.966105 | FC13: 0.025046 | FD13: 0.346999 | FE13: 1.242024 | FF13: 5.553854 | FG13: 1.453867 | FH13: 0.007036 | FI13: 0.132858 | FJ13: 0.536273 | FK13: 0.000727 | FL13: 2e-05 | FM13: 9e-05 | FN13: 0.000121 | FO13: 4e-05 | FP13: 43.268711 | FQ13: 2.946536 | FR13: 0.031292 | FS13: 0.570116 | FT13: 0.276696 | FU13: 0.011174 | FV13: 13.792482 | FW13: 0.182712 | FX13: 246.06706 | FY13: 0.673799 | FZ13: 1.449315 | GA13: 0.018583 | GB13: 0.003283 | GC13: 0.004974 | GD13: 0.140494 | GE13: 4.748311 | GF13: 0.009862 | GG13: 0.006509 | GH13: 0.00031 | GI13: 0.001902 | GJ13: 0.016042 | GK13: 0.064516 | GL13: 0.036336 | GM13: 0.082794 | GN13: 0.012094 | GO13: 0.002627 | GP13: 0.440049 | GQ13: 0.000224 | GR13: 0.000147 | GS13: 0.000165 | GT13: 2.4e-05 | GU13: 3.4e-05 | GV13: 1.1e-05 | GW13: 0 | GX13: 7e-06 | GY13: 1.8e-05 | GZ13: 0 | HA13: 1.5e-05 | HB13: 2e-06 | HC13: 0.001414 | HD13: 9.8e-05 | HE13: 0.171457 | HF13: 0.091057 | HG13: 4.76703 | HH13: 0.000798 | HI13: 0.000152 | HJ13: 0.000608 | HK13: 0.000543 | HL13: 0.000422 | HM13: 0.003644 | HN13: 0.000193 | HO13: 3.3e-05 | HP13: 1.256653 | HQ13: 0.396615 | HR13: 0.000526 | HS13: 10.400936 | HT13: 0.487826 | HU13: 0.002671 | HV13: 0 | HW13: 0 | HX13: 0 | HY13: 0 | HZ13: 0 | IA13: 0 | IB13: 0 | IC13: 0 | ID13: 0 | IE13: 0 | IF13: 0 | IG13: 0 | IH13: 0 | II13: 0 | IJ13: 0 | IK13: 0 | IL13: 0 | IM13: 0 | IN13: 0 | IO13: 0 | IP13: 0 | IQ13: 0 | IR13: 0 | IS13: 0 | IT13: 0 | IU13: 0 | IV13: 0 | IW13: 0 | IX13: 0 | IY13: 0 | IZ13: 0 | JA13: 0 | JB13: 0 | JC13: 0 | JD13: 0 | JE13: 0 | JF13: 0 | JG13: 0 | JH13: 0 | JI13: 0 | JJ13: 0 | JK13: 0 | JL13: 0 | JM13: 0 | JN13: 0 | JO13: 0 | JP13: 0 | JQ13: 0 | JR13: 0 | JS13: 0 | JT13: 0 | JU13: 0 | JV13: 0 | JW13: 0 | JX13: 0 | JY13: 0 | JZ13: 0 | KA13: 0 | KB13: 0 | KC13: 0 | KD13: 0 | KE13: 0 | KF13: 0 | KG13: 0 | KH13: 0 | KI13: 0 | KJ13: 0 | KK13: 0 | KL13: 0 | KM13: 0 | KN13: 0 | KO13: 0 | KP13: 0 | KQ13: 0 | KR13: 0 | KS13: 0 | KT13: 0 | KU13: 0 | KV13: 0 | KW13: 0 | KX13: 0 | KY13: 0 | KZ13: 0 | LA13: 0 | LB13: 0 | LC13: 0 | LD13: 0 | LE13: 0 | LF13: 0 | LG13: 0 | LH13: 0 | LI13: 0 | LJ13: 0 | LK13: 0 | LL13: 0 | LM13: 0 | LN13: 0 | LO13: 0 | LP13: 0 | LQ13: 0 | LR13: 0 | LS13: 0 | LT13: 0 | LU13: 0 | LV13: 0 | LW13: 0 | LX13: 0 | LY13: 0 | LZ13: 0 | MA13: 0 | MB13: 0 | MC13: 0 | MD13: 0 | ME13: 0 | MF13: 0 | MG13: 0 | MH13: 0 | MI13: 0 | MJ13: 0 | MK13: 0 | ML13: 0 | MM13: 0 | MN13: 0 | MO13: 0 | MP13: 0 | MQ13: 0 | MR13: 0 | MS13: 0 | MT13: 0 | MU13: 0 | MV13: 0 | MW13: 0 | MX13: 0 | MY13: 0 | MZ13: 0 | NA13: 0 | NB13: 0 | NC13: 0 | ND13: 0 | NE13: 0 | NF13: 0 | NG13: 0 | NH13: 0 | NI13: 0 | NJ13: 0 | NK13: 0 | NL13: 0 | NM13: 0 | NN13: 0 | NO13: 0 | NP13: 0 | NQ13: 0 | NR13: 0 | NS13: 0 | NT13: 0 | NU13: 0 | NV13: 0 | NW13: 0 | NX13: 0 | NY13: 0 | NZ13: 0 | OA13: 0 | OB13: 0 | OC13: 0 | OD13: 0 | OE13: 0 | OF13: 0 | OG13: 0 | OH13: 0 | OI13: 0 | OJ13: 0 | OK13: 0 | OL13: 23.441673 | OM13: 0 | ON13: 0 | OO13: 0.219907 | OP13: 14.473713 | OQ13: 385.33874
... A407: Total | B407: 18.407295 | C407: 989.80363 | D407: 1623.3983 | E407: 20061.091 | F407: 2242.1161 | G407: 5.975951 | H407: 146.51361 | I407: 10609.291 | J407: 2997.7552 | K407: 2548.3451 | L407: 43.716892 | M407: 385.33881 | N407: 433.73141 | O407: 2788.8462 | P407: 905.1122 | Q407: 238890.4 | R407: 34987.065 | S407: 6294.5788 | T407: 6849.6929 | U407: 2858.4851 | V407: 7464.9828 | W407: 2453.0359 | X407: 973.86555 | Y407: 2651.1082 | Z407: 51954.521 | AA407: 22406.957 | AB407: 33086.218 | AC407: 102131.06 | AD407: 45307.08 | AE407: 18286.431 | AF407: 25831.857 | AG407: 68047.124 | AH407: 121400.92 | AI407: 78539.605 | AJ407: 59871.2 | AK407: 22988.316 | AL407: 50277.819 | AM407: 61662.7 | AN407: 48274.628 | AO407: 322163.22 | AP407: 126088.42 | AQ407: 161683.54 | AR407: 278193.78 | AS407: 68531.883 | AT407: 110060.62 | AU407: 1270.2731 | AV407: 423.5867 | AW407: 445.97601 | AX407: 163.65146 | AY407: 148.68751 | AZ407: 1513.6121 | BA407: 32.256054 | BB407: 88.594254 | BC407: 512.07092 | BD407: 64.115952 | BE407: 218.20967 | BF407: 30.568249 | BG407: 2180.5315 | BH407: 607.31348 | BI407: 3787.4534 | BJ407: 23309.17 | BK407: 8207.1387 | BL407: 46900.758 | BM407: 2885.0686 | BN407: 43775.965 | BO407: 6138.3813 | BP407: 31861.145 | BQ407: 42658.27 | BR407: 41471.34 | BS407: 3834.8516 | BT407: 85249.008 | BU407: 14163.092 | BV407: 11841.667 | BW407: 30092.748 | BX407: 6301.6245 | BY407: 1e-06 | BZ407: 2634.9536 | CA407: 10918.241 | CB407: 50541.016 | CC407: 64457.48 | CD407: 38187.52 | CE407: 2505.848 | CF407: 6343.8174 | CG407: 11892.922 | CH407: 60469.113 | CI407: 70952.312 | CJ407: 47498.468 | CK407: 108.68649 | CL407: 30550.639 | CM407: 7161.6999 | CN407: 74097.337 | CO407: 298816.61 | CP407: 40921.765 | CQ407: 56489.284 | CR407: 134751.19 | CS407: 106204.86 | CT407: 27830.168 | CU407: 118285.2 | CV407: 3614.9041 | CW407: 20532.338 | CX407: 429324.19 | CY407: 168242.22 | CZ407: 178439.77 | DA407: 115162.62 | DB407: 17646.426 | DC407: 348819.85 | DD407: 427672.69 | DE407: 685153.59 | DF407: 611060.95 | DG407: 188508.71 | DH407: 339528.14 | DI407: 175939.12 | DJ407: 218320.72 | DK407: 197644.62 | DL407: 437268.54 | DM407: 714215.84 | DN407: 298711.29 | DO407: 701355.68 | DP407: 720730.38 | DQ407: 320532.12 | DR407: 306799.46 | DS407: 74566.898 | DT407: 69733.492 | DU407: 148795.55 | DV407: 38341.238 | DW407: 19832.645 | DX407: 20845.025 | DY407: 0 | DZ407: 5851.0591 | EA407: 42087.199 | EB407: 0 | EC407: 20317.797 | ED407: 2274.0371 | EE407: 100676 | EF407: 354241.72 | EG407: 2139655.8 | EH407: 2691226.2 | EI407: 906718.38 | EJ407: 566514 | EK407: 74840.633 | EL407: 287708.88 | EM407: 189213.06 | EN407: 1054372 | EO407: 1886554.2 | EP407: 680967.38 | EQ407: 692902.38 | ER407: 1720120.1 | ES407: 1558191.2 | ET407: 1445514.4 | EU407: 1429111.9 | EV407: 2325318.8 | EW407: 1727847.6 | EX407: 2634.9536 | EY407: 10918.24 | EZ407: 50541.018 | FA407: 64457.474 | FB407: 38149.993 | FC407: 2505.8472 | FD407: 6343.8173 | FE407: 11892.921 | FF407: 60469.113 | FG407: 70952.331 | FH407: 47498.466 | FI407: 108.6757 | FJ407: 30550.208 | FK407: 7161.54 | FL407: 74086.683 | FM407: 298815.17 | FN407: 40920.294 | FO407: 56488.196 | FP407: 134751.17 | FQ407: 106204.86 | FR407: 27830.171 | FS407: 118285.2 | FT407: 3614.9041 | FU407: 20532.344 | FV407: 429324.15 | FW407: 168242.21 | FX407: 178430.18 | FY407: 115161.97 | FZ407: 17645.939 | GA407: 348799.32 | GB407: 427610.36 | GC407: 684618.56 | GD407: 610454.01 | GE407: 188173.34 | GF407: 339424.28 | GG407: 175921.44 | GH407: 218318.55 | GI407: 197601.26 | GJ407: 437181.9 | GK407: 713352.05 | GL407: 298535.64 | GM407: 700863.84 | GN407: 720571.74 | GO407: 320459.55 | GP407: 306567.16 | GQ407: 74566.896 | GR407: 69733.498 | GS407: 148795.55 | GT407: 38341.241 | GU407: 19832.644 | GV407: 20845.025 | GW407: 0 | GX407: 5851.0588 | GY407: 42087.191 | GZ407: 0 | HA407: 20317.795 | HB407: 2274.0372 | HC407: 100675.99 | HD407: 354241.67 | HE407: 2139655.7 | HF407: 2691226.3 | HG407: 906718.39 | HH407: 566513.92 | HI407: 74840.627 | HJ407: 287708.84 | HK407: 189213.06 | HL407: 1054372 | HM407: 1886554.1 | HN407: 680967.38 | HO407: 692902.39 | HP407: 1720120.2 | HQ407: 1558191.3 | HR407: 1445514.4 | HS407: 1429111.9 | HT407: 2325318.9 | HU407: 1727847.7 | HV407: 46802.559 | HW407: 4255884 | HX407: 5858668 | HY407: 4321008 | HZ407: 102926.12 | IA407: 28215.215 | IB407: 3871.8977 | IC407: -0.004821 | ID407: -0.65261 | IE407: -9.23468 | IF407: 450.79504 | IG407: -4.620017 | IH407: 0 | II407: 0.00251 | IJ407: 617.56335 | IK407: -8.45558 | IL407: 38.747688 | IM407: 0.017428 | IN407: 0.493381 | IO407: 0.363416 | IP407: 16.382103 | IQ407: 0.315282 | IR407: 0.015625 | IS407: 40.714264 | IT407: 10.717628 | IU407: 125.66819 | IV407: 82.025215 | IW407: 72.983604 | IX407: 42.504311 | IY407: 22.527235 | IZ407: 2.965127 | JA407: 1171.3262 | JB407: 2583.6963 | JC407: 1085.6919 | JD407: 10323.584 | JE407: 3391.3345 | JF407: 740.12353 | JG407: 333.52951 | JH407: 11313.744 | JI407: 2581.1182 | JJ407: 1747.9961 | JK407: 1244.2517 | JL407: 740.40723 | JM407: 378.25055 | JN407: 116.86881 | JO407: 1423.7339 | JP407: 7917.5527 | JQ407: 4740.2695 | JR407: 4633.4243 | JS407: 8586.5312 | JT407: 882.75977 | JU407: 6026.2749 | JV407: 0.067218 | JW407: 0.022415 | JX407: 0.023599 | JY407: 0.00866 | JZ407: 0.007868 | KA407: 0.080093 | KB407: 0.001707 | KC407: 0.004688 | KD407: 0.027097 | KE407: 0.003393 | KF407: 0.011547 | KG407: 0.001617 | KH407: 0 | KI407: 1.193327 | KJ407: 0 | KK407: -341.69568 | KL407: 93.827553 | KM407: -40.745102 | KN407: -0.729549 | KO407: 248.41721 | KP407: 65.428062 | KQ407: -212.63748 | KR407: -0.359837 | KS407: -17.723209 | KT407: 116.35716 | KU407: 282.29715 | KV407: 1.25403 | KW407: -27.532398 | KX407: -30.029343 | KY407: 88.332352 | KZ407: 0 | LA407: -1.54819 | LB407: -2.663672 | LC407: -693.22485 | LD407: 1236.1759 | LE407: -25.785633 | LF407: -0.720362 | LG407: 1.559849 | LH407: 367.17233 | LI407: -142.20013 | LJ407: 411.95566 | LK407: 1.074275 | LL407: 0.893492 | LM407: 159.49142 | LN407: 38.31263 | LO407: 39.383102 | LP407: 6.9e-05 | LQ407: 17.358994 | LR407: 48.295437 | LS407: 2403.8206 | LT407: 1934.7419 | LU407: 4.32275 | LV407: 1874.7876 | LW407: 36.322784 | LX407: 190.16702 | LY407: 7161.5215 | LZ407: 52097.125 | MA407: 4268.3906 | MB407: 8793.8916 | MC407: 768.35608 | MD407: 10137.896 | ME407: 2867.7288 | MF407: 96606.641 | MG407: 9567.4219 | MH407: 3092.1516 | MI407: 5266.5859 | MJ407: 1975.9524 | MK407: 396.04922 | ML407: 223.88701 | MM407: 6404.0586 | MN407: 7632.3711 | MO407: 5537.5508 | MP407: 13071.918 | MQ407: 17767.504 | MR407: 2455.3604 | MS407: 6779.3057 | MT407: 2333.7441 | MU407: 2182.4727 | MV407: 4656.9053 | MW407: 1199.9788 | MX407: 620.70911 | MY407: 652.39374 | MZ407: 0 | NA407: 183.12265 | NB407: 1317.2172 | NC407: 0 | ND407: 635.89307 | NE407: 71.17131 | NF407: 2176.8213 | NG407: -899.58081 | NH407: -234.5415 | NI407: 15308.127 | NJ407: 9135.9297 | NK407: 102.77023 | NL407: 2.522858 | NM407: 10064.984 | NN407: 1064.8137 | NO407: 14559.135 | NP407: 874.41077 | NQ407: -59.062504 | NR407: 15808.057 | NS407: 16972.18 | NT407: 42728.352 | NU407: -5261.2754 | NV407: 10021.012 | NW407: -1760.6406 | NX407: 0.100025 | NY407: -7140.2705 | NZ407: 586105.06 | OA407: 803475.88 | OB407: 135935.69 | OC407: 3376.5293 | OD407: 9745.7031 | OE407: 46626.559 | OF407: 10938.972 | OG407: 9745.7031 | OH407: 46626.558 | OI407: 10938.972 | OJ407: 2540661.4 | OK407: 15194167 | OL407: 11984587 | OM407: 720059.94 | ON407: 1936971.6 | OO407: 2574440.2 | OP407: 3402733 | OQ407: 1.2007097e+08

Sheet World SAM
A1: ASAM | B1: 1 m_pdr | C1: 2 m_wht | D1: 3 m_gro | E1: 4 m_v_f | F1: 5 m_osd | G1: 6 m_c_b | H1: 7 m_pfb | I1: 8 m_ocr | J1: 9 m_ctl | K1: 10 m_oap | L1: 11 m_rmk | M1: 12 m_wol | N1: 13 m_frs | O1: 14 m_fsh | P1: 15 m_coa | Q1: 16 m_oil | R1: 17 m_gas | S1: 18 m_oxt | T1: 19 m_cmt | U1: 20 m_omt | V1: 21 m_vol | W1: 22 m_mil | X1: 23 m_pcr | Y1: 24 m_sgr | Z1: 25 m_ofd | AA1: 26 m_b_t | AB1: 27 m_tex | AC1: 28 m_wap | AD1: 29 m_lea | AE1: 30 m_lum | AF1: 31 m_ppp | AG1: 32 m_p_c | AH1: 33 m_chm | AI1: 34 m_bph | AJ1: 35 m_rpp | AK1: 36 m_nmm | AL1: 37 m_i_s | AM1: 38 m_nfm | AN1: 39 m_fmp | AO1: 40 m_ele | AP1: 41 m_eeq | AQ1: 42 m_ome | AR1: 43 m_mvh | AS1: 44 m_otn | AT1: 45 m_omf | AU1: 46 m_TnD | AV1: 47 m_NuclearBL | AW1: 48 m_CoalBL | AX1: 49 m_GasBL | AY1: 50 m_WindBL | AZ1: 51 m_HydroBL | BA1: 52 m_OilBL | BB1: 53 m_OtherBL | BC1: 54 m_GasP | BD1: 55 m_HydroP | BE1: 56 m_OilP | BF1: 57 m_SolarP | BG1: 58 m_gdt | BH1: 59 m_wtr | BI1: 60 m_cns | BJ1: 61 m_trd | BK1: 62 m_afs | BL1: 63 m_otp | BM1: 64 m_wtp | BN1: 65 m_atp | BO1: 66 m_whs | BP1: 67 m_cmn | BQ1: 68 m_ofi | BR1: 69 m_ins | BS1: 70 m_rsa | BT1: 71 m_obs | BU1: 72 m_ros | BV1: 73 m_osg | BW1: 74 m_edu | BX1: 75 m_hht | BY1: 76 m_dwe | BZ1: 77 d_pdr | CA1: 78 d_wht | CB1: 79 d_gro | CC1: 80 d_v_f | CD1: 81 d_osd | CE1: 82 d_c_b | CF1: 83 d_pfb | CG1: 84 d_ocr | CH1: 85 d_ctl | CI1: 86 d_oap | CJ1: 87 d_rmk | CK1: 88 d_wol | CL1: 89 d_frs | CM1: 90 d_fsh | CN1: 91 d_coa | CO1: 92 d_oil | CP1: 93 d_gas | CQ1: 94 d_oxt | CR1: 95 d_cmt | CS1: 96 d_omt | CT1: 97 d_vol | CU1: 98 d_mil | CV1: 99 d_pcr | CW1: 100 d_sgr | CX1: 101 d_ofd | CY1: 102 d_b_t | CZ1: 103 d_tex | DA1: 104 d_wap | DB1: 105 d_lea | DC1: 106 d_lum | DD1: 107 d_ppp | DE1: 108 d_p_c | DF1: 109 d_chm | DG1: 110 d_bph | DH1: 111 d_rpp | DI1: 112 d_nmm | DJ1: 113 d_i_s | DK1: 114 d_nfm | DL1: 115 d_fmp | DM1: 116 d_ele | DN1: 117 d_eeq | DO1: 118 d_ome | DP1: 119 d_mvh | DQ1: 120 d_otn | DR1: 121 d_omf | DS1: 122 d_TnD | DT1: 123 d_NuclearBL | DU1: 124 d_CoalBL | DV1: 125 d_GasBL | DW1: 126 d_WindBL | DX1: 127 d_HydroBL | DY1: 128 d_OilBL | DZ1: 129 d_OtherBL | EA1: 130 d_GasP | EB1: 131 d_HydroP | EC1: 132 d_OilP | ED1: 133 d_SolarP | EE1: 134 d_gdt | EF1: 135 d_wtr | EG1: 136 d_cns | EH1: 137 d_trd | EI1: 138 d_afs | EJ1: 139 d_otp | EK1: 140 d_wtp | EL1: 141 d_atp | EM1: 142 d_whs | EN1: 143 d_cmn | EO1: 144 d_ofi | EP1: 145 d_ins | EQ1: 146 d_rsa | ER1: 147 d_obs | ES1: 148 d_ros | ET1: 149 d_osg | EU1: 150 d_edu | EV1: 151 d_hht | EW1: 152 d_dwe | EX1: 153 a_pdr | EY1: 154 a_wht | EZ1: 155 a_gro | FA1: 156 a_v_f | FB1: 157 a_osd | FC1: 158 a_c_b | FD1: 159 a_pfb | FE1: 160 a_ocr | FF1: 161 a_ctl | FG1: 162 a_oap | FH1: 163 a_rmk | FI1: 164 a_wol | FJ1: 165 a_frs | FK1: 166 a_fsh | FL1: 167 a_coa | FM1: 168 a_oil | FN1: 169 a_gas | FO1: 170 a_oxt | FP1: 171 a_cmt | FQ1: 172 a_omt | FR1: 173 a_vol | FS1: 174 a_mil | FT1: 175 a_pcr | FU1: 176 a_sgr | FV1: 177 a_ofd | FW1: 178 a_b_t | FX1: 179 a_tex | FY1: 180 a_wap | FZ1: 181 a_lea | GA1: 182 a_lum | GB1: 183 a_ppp | GC1: 184 a_p_c | GD1: 185 a_chm | GE1: 186 a_bph | GF1: 187 a_rpp | GG1: 188 a_nmm | GH1: 189 a_i_s | GI1: 190 a_nfm | GJ1: 191 a_fmp | GK1: 192 a_ele | GL1: 193 a_eeq | GM1: 194 a_ome | GN1: 195 a_mvh | GO1: 196 a_otn | GP1: 197 a_omf | GQ1: 198 a_TnD | GR1: 199 a_NuclearBL | GS1: 200 a_CoalBL | GT1: 201 a_GasBL | GU1: 202 a_WindBL | GV1: 203 a_HydroBL | GW1: 204 a_OilBL | GX1: 205 a_OtherBL | GY1: 206 a_GasP | GZ1: 207 a_HydroP | HA1: 208 a_OilP | HB1: 209 a_SolarP | HC1: 210 a_gdt | HD1: 211 a_wtr | HE1: 212 a_cns | HF1: 213 a_trd | HG1: 214 a_afs | HH1: 215 a_otp | HI1: 216 a_wtp | HJ1: 217 a_atp | HK1: 218 a_whs | HL1: 219 a_cmn | HM1: 220 a_ofi | HN1: 221 a_ins | HO1: 222 a_rsa | HP1: 223 a_obs | HQ1: 224 a_ros | HR1: 225 a_osg | HS1: 226 a_edu | HT1: 227 a_hht | HU1: 228 a_dwe | HV1: 229 Land | HW1: 230 UnSklab | HX1: 231 SKlab | HY1: 232 Capital | HZ1: 233 NatlRes | IA1: 234 tmm_world | IB1: 235 tee_world | IC1: 236 tssm_T1pdr | ID1: 237 tssm_T2wht | IE1: 238 tssm_T3gro | IF1: 239 tssm_T4v_f | IG1: 240 tssm_T5osd | IH1: 241 tssm_T6c_b | II1: 242 tssm_T7pfb | IJ1: 243 tssm_T8ocr | IK1: 244 tssm_T9ctl | IL1: 245 tssm_T10oap | IM1: 246 tssm_T11rmk | IN1: 247 tssm_T12wol | IO1: 248 tssm_T13frs | IP1: 249 tssm_T14fsh | IQ1: 250 tssm_T15coa | IR1: 251 tssm_T16oil | IS1: 252 tssm_T17gas | IT1: 253 tssm_T18oxt | IU1: 254 tssm_T19cmt | IV1: 255 tssm_T20omt | IW1: 256 tssm_T21vol | IX1: 257 tssm_T22mil | IY1: 258 tssm_T23pcr | IZ1: 259 tssm_T24sgr | JA1: 260 tssm_T25ofd | JB1: 261 tssm_T26b_t | JC1: 262 tssm_T27tex | JD1: 263 tssm_T28wap | JE1: 264 tssm_T29lea | JF1: 265 tssm_T30lum | JG1: 266 tssm_T31ppp | JH1: 267 tssm_T32p_c | JI1: 268 tssm_T33chm | JJ1: 269 tssm_T34bph | JK1: 270 tssm_T35rpp | JL1: 271 tssm_T36nmm | JM1: 272 tssm_T37i_s | JN1: 273 tssm_T38nfm | JO1: 274 tssm_T39fmp | JP1: 275 tssm_T40ele | JQ1: 276 tssm_T41eeq | JR1: 277 tssm_T42ome | JS1: 278 tssm_T43mvh | JT1: 279 tssm_T44otn | JU1: 280 tssm_T45omf | JV1: 281 tssm_T46TnD | JW1: 282 tssm_T47Nucl | JX1: 283 tssm_T48Coal | JY1: 284 tssm_T49GasB | JZ1: 285 tssm_T50Wind | KA1: 286 tssm_T51Hydr | KB1: 287 tssm_T52OilB | KC1: 288 tssm_T53Othe | KD1: 289 tssm_T54GasP | KE1: 290 tssm_T55Hydr | KF1: 291 tssm_T56OilP | KG1: 292 tssm_T57Sola | KH1: 293 tssm_T58gdt | KI1: 294 tssm_T59wtr | KJ1: 295 tssm_T60cns | KK1: 296 tssm_T61trd | KL1: 297 tssm_T62afs | KM1: 298 tssm_T63otp | KN1: 299 tssm_T64wtp | KO1: 300 tssm_T65atp | KP1: 301 tssm_T66whs | KQ1: 302 tssm_T67cmn | KR1: 303 tssm_T68ofi | KS1: 304 tssm_T69ins | KT1: 305 tssm_T70rsa | KU1: 306 tssm_T71obs | KV1: 307 tssm_T72ros | KW1: 308 tssm_T73osg | KX1: 309 tssm_T74edu | KY1: 310 tssm_T75hht | KZ1: 311 tssm_T76dwe | LA1: 312 tssd_T1pdr | LB1: 313 tssd_T2wht | LC1: 314 tssd_T3gro | LD1: 315 tssd_T4v_f | LE1: 316 tssd_T5osd | LF1: 317 tssd_T6c_b | LG1: 318 tssd_T7pfb | LH1: 319 tssd_T8ocr | LI1: 320 tssd_T9ctl | LJ1: 321 tssd_T10oap | LK1: 322 tssd_T11rmk | LL1: 323 tssd_T12wol | LM1: 324 tssd_T13frs | LN1: 325 tssd_T14fsh | LO1: 326 tssd_T15coa | LP1: 327 tssd_T16oil | LQ1: 328 tssd_T17gas | LR1: 329 tssd_T18oxt | LS1: 330 tssd_T19cmt | LT1: 331 tssd_T20omt | LU1: 332 tssd_T21vol | LV1: 333 tssd_T22mil | LW1: 334 tssd_T23pcr | LX1: 335 tssd_T24sgr | LY1: 336 tssd_T25ofd | LZ1: 337 tssd_T26b_t | MA1: 338 tssd_T27tex | MB1: 339 tssd_T28wap | MC1: 340 tssd_T29lea | MD1: 341 tssd_T30lum | ME1: 342 tssd_T31ppp | MF1: 343 tssd_T32p_c | MG1: 344 tssd_T33chm | MH1: 345 tssd_T34bph | MI1: 346 tssd_T35rpp | MJ1: 347 tssd_T36nmm | MK1: 348 tssd_T37i_s | ML1: 349 tssd_T38nfm | MM1: 350 tssd_T39fmp | MN1: 351 tssd_T40ele | MO1: 352 tssd_T41eeq | MP1: 353 tssd_T42ome | MQ1: 354 tssd_T43mvh | MR1: 355 tssd_T44otn | MS1: 356 tssd_T45omf | MT1: 357 tssd_T46TnD | MU1: 358 tssd_T47Nucl | MV1: 359 tssd_T48Coal | MW1: 360 tssd_T49GasB | MX1: 361 tssd_T50Wind | MY1: 362 tssd_T51Hydr | MZ1: 363 tssd_T52OilB | NA1: 364 tssd_T53Othe | NB1: 365 tssd_T54GasP | NC1: 366 tssd_T55Hydr | ND1: 367 tssd_T56OilP | NE1: 368 tssd_T57Sola | NF1: 369 tssd_T58gdt | NG1: 370 tssd_T59wtr | NH1: 371 tssd_T60cns | NI1: 372 tssd_T61trd | NJ1: 373 tssd_T62afs | NK1: 374 tssd_T63otp | NL1: 375 tssd_T64wtp | NM1: 376 tssd_T65atp | NN1: 377 tssd_T66whs | NO1: 378 tssd_T67cmn | NP1: 379 tssd_T68ofi | NQ1: 380 tssd_T69ins | NR1: 381 tssd_T70rsa | NS1: 382 tssd_T71obs | NT1: 383 tssd_T72ros | NU1: 384 tssd_T73osg | NV1: 385 tssd_T74edu | NW1: 386 tssd_T75hht | NX1: 387 tssd_T76dwe | NY1: 388 tf_Land | NZ1: 389 tf_UnSklab | OA1: 390 tf_SKlab | OB1: 391 tf_Capital | OC1: 392 tf_NatlRes | OD1: 393 otp_world | OE1: 394 wtp_world | OF1: 395 atp_world | OG1: 396 otp_pvst | OH1: 397 wtp_pvst | OI1: 398 atp_pvst | OJ1: 399 ww_world | OK1: 400 REGHOUS | OL1: 401 PRIV | OM1: 402 PRODTAX | ON1: 403 DIRTAX | OO1: 404 GOVT | OP1: 405 CGDS | OQ1: Total
A2: 1 m_pdr | B2: 0 | C2: 0 | D2: 0 | E2: 0 | F2: 0 | G2: 0 | H2: 0 | I2: 0 | J2: 0 | K2: 0 | L2: 0 | M2: 0 | N2: 0 | O2: 0 | P2: 0 | Q2: 0 | R2: 0 | S2: 0 | T2: 0 | U2: 0 | V2: 0 | W2: 0 | X2: 0 | Y2: 0 | Z2: 0 | AA2: 0 | AB2: 0 | AC2: 0 | AD2: 0 | AE2: 0 | AF2: 0 | AG2: 0 | AH2: 0 | AI2: 0 | AJ2: 0 | AK2: 0 | AL2: 0 | AM2: 0 | AN2: 0 | AO2: 0 | AP2: 0 | AQ2: 0 | AR2: 0 | AS2: 0 | AT2: 0 | AU2: 0 | AV2: 0 | AW2: 0 | AX2: 0 | AY2: 0 | AZ2: 0 | BA2: 0 | BB2: 0 | BC2: 0 | BD2: 0 | BE2: 0 | BF2: 0 | BG2: 0 | BH2: 0 | BI2: 0 | BJ2: 0 | BK2: 0 | BL2: 0 | BM2: 0 | BN2: 0 | BO2: 0 | BP2: 0 | BQ2: 0 | BR2: 0 | BS2: 0 | BT2: 0 | BU2: 0 | BV2: 0 | BW2: 0 | BX2: 0 | BY2: 0 | BZ2: 0 | CA2: 0 | CB2: 0 | CC2: 0 | CD2: 0 | CE2: 0 | CF2: 0 | CG2: 0 | CH2: 0 | CI2: 0 | CJ2: 0 | CK2: 0 | CL2: 0 | CM2: 0 | CN2: 0 | CO2: 0 | CP2: 0 | CQ2: 0 | CR2: 0 | CS2: 0 | CT2: 0 | CU2: 0 | CV2: 0 | CW2: 0 | CX2: 0 | CY2: 0 | CZ2: 0 | DA2: 0 | DB2: 0 | DC2: 0 | DD2: 0 | DE2: 0 | DF2: 0 | DG2: 0 | DH2: 0 | DI2: 0 | DJ2: 0 | DK2: 0 | DL2: 0 | DM2: 0 | DN2: 0 | DO2: 0 | DP2: 0 | DQ2: 0 | DR2: 0 | DS2: 0 | DT2: 0 | DU2: 0 | DV2: 0 | DW2: 0 | DX2: 0 | DY2: 0 | DZ2: 0 | EA2: 0 | EB2: 0 | EC2: 0 | ED2: 0 | EE2: 0 | EF2: 0 | EG2: 0 | EH2: 0 | EI2: 0 | EJ2: 0 | EK2: 0 | EL2: 0 | EM2: 0 | EN2: 0 | EO2: 0 | EP2: 0 | EQ2: 0 | ER2: 0 | ES2: 0 | ET2: 0 | EU2: 0 | EV2: 0 | EW2: 0 | EX2: 25.017222 | EY2: 3.623175 | EZ2: 58.058899 | FA2: 8.415138 | FB2: 9.4365 | FC2: 1.140165 | FD2: 1.849309 | FE2: 5.938427 | FF2: 81.604566 | FG2: 6.542892 | FH2: 5.940721 | FI2: 0.818002 | FJ2: 2.413057 | FK2: 0.877803 | FL2: 0.005564 | FM2: 0.012541 | FN2: 0.048747 | FO2: 0.032617 | FP2: 18.104198 | FQ2: 16.085472 | FR2: 17.420127 | FS2: 51.004676 | FT2: 265.95467 | FU2: 15.727909 | FV2: 549.48065 | FW2: 41.785374 | FX2: 12.047135 | FY2: 5.769018 | FZ2: 3.499582 | GA2: 0.475496 | GB2: 0.75399 | GC2: 2.063793 | GD2: 4.11137 | GE2: 1.321537 | GF2: 0.237106 | GG2: 0.164846 | GH2: 0.00734 | GI2: 0.097217 | GJ2: 0.114352 | GK2: 0.034375 | GL2: 0.024033 | GM2: 0.053051 | GN2: 0.042718 | GO2: 1.81957 | GP2: 8.934391 | GQ2: 0.029527 | GR2: 0.000104 | GS2: 0.002776 | GT2: 0.002187 | GU2: 0.000276 | GV2: 0.004849 | GW2: 0.000982 | GX2: 0.002522 | GY2: 0.000349 | GZ2: 0.000375 | HA2: 0.000764 | HB2: 0.000203 | HC2: 0.008772 | HD2: 1.806841 | HE2: 3.077947 | HF2: 26.08251 | HG2: 13.721679 | HH2: 4.967847 | HI2: 0.139745 | HJ2: 0.021171 | HK2: 1.248377 | HL2: 0.319835 | HM2: 0.036801 | HN2: 0.025145 | HO2: 0.083111 | HP2: 10.917145 | HQ2: 1.688819 | HR2: 2.013556 | HS2: 1.428579 | HT2: 0.072953 | HU2: 2.49289 | HV2: 0 | HW2: 0 | HX2: 0 | HY2: 0 | HZ2: 0 | IA2: 0 | IB2: 0 | IC2: 0 | ID2: 0 | IE2: 0 | IF2: 0 | IG2: 0 | IH2: 0 | II2: 0 | IJ2: 0 | IK2: 0 | IL2: 0 | IM2: 0 | IN2: 0 | IO2: 0 | IP2: 0 | IQ2: 0 | IR2: 0 | IS2: 0 | IT2: 0 | IU2: 0 | IV2: 0 | IW2: 0 | IX2: 0 | IY2: 0 | IZ2: 0 | JA2: 0 | JB2: 0 | JC2: 0 | JD2: 0 | JE2: 0 | JF2: 0 | JG2: 0 | JH2: 0 | JI2: 0 | JJ2: 0 | JK2: 0 | JL2: 0 | JM2: 0 | JN2: 0 | JO2: 0 | JP2: 0 | JQ2: 0 | JR2: 0 | JS2: 0 | JT2: 0 | JU2: 0 | JV2: 0 | JW2: 0 | JX2: 0 | JY2: 0 | JZ2: 0 | KA2: 0 | KB2: 0 | KC2: 0 | KD2: 0 | KE2: 0 | KF2: 0 | KG2: 0 | KH2: 0 | KI2: 0 | KJ2: 0 | KK2: 0 | KL2: 0 | KM2: 0 | KN2: 0 | KO2: 0 | KP2: 0 | KQ2: 0 | KR2: 0 | KS2: 0 | KT2: 0 | KU2: 0 | KV2: 0 | KW2: 0 | KX2: 0 | KY2: 0 | KZ2: 0 | LA2: 0 | LB2: 0 | LC2: 0 | LD2: 0 | LE2: 0 | LF2: 0 | LG2: 0 | LH2: 0 | LI2: 0 | LJ2: 0 | LK2: 0 | LL2: 0 | LM2: 0 | LN2: 0 | LO2: 0 | LP2: 0 | LQ2: 0 | LR2: 0 | LS2: 0 | LT2: 0 | LU2: 0 | LV2: 0 | LW2: 0 | LX2: 0 | LY2: 0 | LZ2: 0 | MA2: 0 | MB2: 0 | MC2: 0 | MD2: 0 | ME2: 0 | MF2: 0 | MG2: 0 | MH2: 0 | MI2: 0 | MJ2: 0 | MK2: 0 | ML2: 0 | MM2: 0 | MN2: 0 | MO2: 0 | MP2: 0 | MQ2: 0 | MR2: 0 | MS2: 0 | MT2: 0 | MU2: 0 | MV2: 0 | MW2: 0 | MX2: 0 | MY2: 0 | MZ2: 0 | NA2: 0 | NB2: 0 | NC2: 0 | ND2: 0 | NE2: 0 | NF2: 0 | NG2: 0 | NH2: 0 | NI2: 0 | NJ2: 0 | NK2: 0 | NL2: 0 | NM2: 0 | NN2: 0 | NO2: 0 | NP2: 0 | NQ2: 0 | NR2: 0 | NS2: 0 | NT2: 0 | NU2: 0 | NV2: 0 | NW2: 0 | NX2: 0 | NY2: 0 | NZ2: 0 | OA2: 0 | OB2: 0 | OC2: 0 | OD2: 0 | OE2: 0 | OF2: 0 | OG2: 0 | OH2: 0 | OI2: 0 | OJ2: 0 | OK2: 0 | OL2: 20.251108 | OM2: 0 | ON2: 0 | OO2: 0.583291 | OP2: 2.304746 | OQ2: 1322.2471
A3: 2 m_wht | B3: 0 | C3: 0 | D3: 0 | E3: 0 | F3: 0 | G3: 0 | H3: 0 | I3: 0 | J3: 0 | K3: 0 | L3: 0 | M3: 0 | N3: 0 | O3: 0 | P3: 0 | Q3: 0 | R3: 0 | S3: 0 | T3: 0 | U3: 0 | V3: 0 | W3: 0 | X3: 0 | Y3: 0 | Z3: 0 | AA3: 0 | AB3: 0 | AC3: 0 | AD3: 0 | AE3: 0 | AF3: 0 | AG3: 0 | AH3: 0 | AI3: 0 | AJ3: 0 | AK3: 0 | AL3: 0 | AM3: 0 | AN3: 0 | AO3: 0 | AP3: 0 | AQ3: 0 | AR3: 0 | AS3: 0 | AT3: 0 | AU3: 0 | AV3: 0 | AW3: 0 | AX3: 0 | AY3: 0 | AZ3: 0 | BA3: 0 | BB3: 0 | BC3: 0 | BD3: 0 | BE3: 0 | BF3: 0 | BG3: 0 | BH3: 0 | BI3: 0 | BJ3: 0 | BK3: 0 | BL3: 0 | BM3: 0 | BN3: 0 | BO3: 0 | BP3: 0 | BQ3: 0 | BR3: 0 | BS3: 0 | BT3: 0 | BU3: 0 | BV3: 0 | BW3: 0 | BX3: 0 | BY3: 0 | BZ3: 0 | CA3: 0 | CB3: 0 | CC3: 0 | CD3: 0 | CE3: 0 | CF3: 0 | CG3: 0 | CH3: 0 | CI3: 0 | CJ3: 0 | CK3: 0 | CL3: 0 | CM3: 0 | CN3: 0 | CO3: 0 | CP3: 0 | CQ3: 0 | CR3: 0 | CS3: 0 | CT3: 0 | CU3: 0 | CV3: 0 | CW3: 0 | CX3: 0 | CY3: 0 | CZ3: 0 | DA3: 0 | DB3: 0 | DC3: 0 | DD3: 0 | DE3: 0 | DF3: 0 | DG3: 0 | DH3: 0 | DI3: 0 | DJ3: 0 | DK3: 0 | DL3: 0 | DM3: 0 | DN3: 0 | DO3: 0 | DP3: 0 | DQ3: 0 | DR3: 0 | DS3: 0 | DT3: 0 | DU3: 0 | DV3: 0 | DW3: 0 | DX3: 0 | DY3: 0 | DZ3: 0 | EA3: 0 | EB3: 0 | EC3: 0 | ED3: 0 | EE3: 0 | EF3: 0 | EG3: 0 | EH3: 0 | EI3: 0 | EJ3: 0 | EK3: 0 | EL3: 0 | EM3: 0 | EN3: 0 | EO3: 0 | EP3: 0 | EQ3: 0 | ER3: 0 | ES3: 0 | ET3: 0 | EU3: 0 | EV3: 0 | EW3: 0 | EX3: 15.001913 | EY3: 1296.8348 | EZ3: 129.0375 | FA3: 30.528615 | FB3: 34.603272 | FC3: 15.958788 | FD3: 9.533296 | FE3: 180.73333 | FF3: 358.93468 | FG3: 1468.76 | FH3: 649.20334 | FI3: 64.57997 | FJ3: 13.29696 | FK3: 19.689332 | FL3: 0.087406 | FM3: 0.548701 | FN3: 0.891837 | FO3: 4.00642 | FP3: 157.79031 | FQ3: 84.169141 | FR3: 489.66123 | FS3: 1449.6362 | FT3: 1230.0661 | FU3: 266.99447 | FV3: 32194.972 | FW3: 3061.9621 | FX3: 166.16438 | FY3: 40.98696 | FZ3: 12.206476 | GA3: 125.67284 | GB3: 21.288617 | GC3: 17.637127 | GD3: 136.81987 | GE3: 55.148368 | GF3: 66.106323 | GG3: 5.662763 | GH3: 0.684813 | GI3: 7.163084 | GJ3: 5.918455 | GK3: 2.946452 | GL3: 2.984063 | GM3: 5.604439 | GN3: 9.349987 | GO3: 1.882696 | GP3: 24.67887 | GQ3: 2.208366 | GR3: 0.030568 | GS3: 0.127792 | GT3: 0.094764 | GU3: 0.039504 | GV3: 0.203751 | GW3: 0.252091 | GX3: 0.105381 | GY3: 0.008561 | GZ3: 0.007541 | HA3: 0.09564 | HB3: 0.04853 | HC3: 2.226399 | HD3: 26.220225 | HE3: 42.674535 | HF3: 165.089 | HG3: 1327.1113 | HH3: 54.019634 | HI3: 10.280017 | HJ3: 4.407825 | HK3: 32.011141 | HL3: 101.89232 | HM3: 7.729484 | HN3: 4.299331 | HO3: 42.447625 | HP3: 258.40309 | HQ3: 67.712909 | HR3: 197.5374 | HS3: 42.799048 | HT3: 192.51007 | HU3: 7.588413 | HV3: 0 | HW3: 0 | HX3: 0 | HY3: 0 | HZ3: 0 | IA3: 0 | IB3: 0 | IC3: 0 | ID3: 0 | IE3: 0 | IF3: 0 | IG3: 0 | IH3: 0 | II3: 0 | IJ3: 0 | IK3: 0 | IL3: 0 | IM3: 0 | IN3: 0 | IO3: 0 | IP3: 0 | IQ3: 0 | IR3: 0 | IS3: 0 | IT3: 0 | IU3: 0 | IV3: 0 | IW3: 0 | IX3: 0 | IY3: 0 | IZ3: 0 | JA3: 0 | JB3: 0 | JC3: 0 | JD3: 0 | JE3: 0 | JF3: 0 | JG3: 0 | JH3: 0 | JI3: 0 | JJ3: 0 | JK3: 0 | JL3: 0 | JM3: 0 | JN3: 0 | JO3: 0 | JP3: 0 | JQ3: 0 | JR3: 0 | JS3: 0 | JT3: 0 | JU3: 0 | JV3: 0 | JW3: 0 | JX3: 0 | JY3: 0 | JZ3: 0 | KA3: 0 | KB3: 0 | KC3: 0 | KD3: 0 | KE3: 0 | KF3: 0 | KG3: 0 | KH3: 0 | KI3: 0 | KJ3: 0 | KK3: 0 | KL3: 0 | KM3: 0 | KN3: 0 | KO3: 0 | KP3: 0 | KQ3: 0 | KR3: 0 | KS3: 0 | KT3: 0 | KU3: 0 | KV3: 0 | KW3: 0 | KX3: 0 | KY3: 0 | KZ3: 0 | LA3: 0 | LB3: 0 | LC3: 0 | LD3: 0 | LE3: 0 | LF3: 0 | LG3: 0 | LH3: 0 | LI3: 0 | LJ3: 0 | LK3: 0 | LL3: 0 | LM3: 0 | LN3: 0 | LO3: 0 | LP3: 0 | LQ3: 0 | LR3: 0 | LS3: 0 | LT3: 0 | LU3: 0 | LV3: 0 | LW3: 0 | LX3: 0 | LY3: 0 | LZ3: 0 | MA3: 0 | MB3: 0 | MC3: 0 | MD3: 0 | ME3: 0 | MF3: 0 | MG3: 0 | MH3: 0 | MI3: 0 | MJ3: 0 | MK3: 0 | ML3: 0 | MM3: 0 | MN3: 0 | MO3: 0 | MP3: 0 | MQ3: 0 | MR3: 0 | MS3: 0 | MT3: 0 | MU3: 0 | MV3: 0 | MW3: 0 | MX3: 0 | MY3: 0 | MZ3: 0 | NA3: 0 | NB3: 0 | NC3: 0 | ND3: 0 | NE3: 0 | NF3: 0 | NG3: 0 | NH3: 0 | NI3: 0 | NJ3: 0 | NK3: 0 | NL3: 0 | NM3: 0 | NN3: 0 | NO3: 0 | NP3: 0 | NQ3: 0 | NR3: 0 | NS3: 0 | NT3: 0 | NU3: 0 | NV3: 0 | NW3: 0 | NX3: 0 | NY3: 0 | NZ3: 0 | OA3: 0 | OB3: 0 | OC3: 0 | OD3: 0 | OE3: 0 | OF3: 0 | OG3: 0 | OH3: 0 | OI3: 0 | OJ3: 0 | OK3: 0 | OL3: 11407.006 | OM3: 0 | ON3: 0 | OO3: 45.9975 | OP3: 364.29474 | OQ3: 58343.869
A4: 3 m_gro | B4: 0 | C4: 0 | D4: 0 | E4: 0 | F4: 0 | G4: 0 | H4: 0 | I4: 0 | J4: 0 | K4: 0 | L4: 0 | M4: 0 | N4: 0 | O4: 0 | P4: 0 | Q4: 0 | R4: 0 | S4: 0 | T4: 0 | U4: 0 | V4: 0 | W4: 0 | X4: 0 | Y4: 0 | Z4: 0 | AA4: 0 | AB4: 0 | AC4: 0 | AD4: 0 | AE4: 0 | AF4: 0 | AG4: 0 | AH4: 0 | AI4: 0 | AJ4: 0 | AK4: 0 | AL4: 0 | AM4: 0 | AN4: 0 | AO4: 0 | AP4: 0 | AQ4: 0 | AR4: 0 | AS4: 0 | AT4: 0 | AU4: 0 | AV4: 0 | AW4: 0 | AX4: 0 | AY4: 0 | AZ4: 0 | BA4: 0 | BB4: 0 | BC4: 0 | BD4: 0 | BE4: 0 | BF4: 0 | BG4: 0 | BH4: 0 | BI4: 0 | BJ4: 0 | BK4: 0 | BL4: 0 | BM4: 0 | BN4: 0 | BO4: 0 | BP4: 0 | BQ4: 0 | BR4: 0 | BS4: 0 | BT4: 0 | BU4: 0 | BV4: 0 | BW4: 0 | BX4: 0 | BY4: 0 | BZ4: 0 | CA4: 0 | CB4: 0 | CC4: 0 | CD4: 0 | CE4: 0 | CF4: 0 | CG4: 0 | CH4: 0 | CI4: 0 | CJ4: 0 | CK4: 0 | CL4: 0 | CM4: 0 | CN4: 0 | CO4: 0 | CP4: 0 | CQ4: 0 | CR4: 0 | CS4: 0 | CT4: 0 | CU4: 0 | CV4: 0 | CW4: 0 | CX4: 0 | CY4: 0 | CZ4: 0 | DA4: 0 | DB4: 0 | DC4: 0 | DD4: 0 | DE4: 0 | DF4: 0 | DG4: 0 | DH4: 0 | DI4: 0 | DJ4: 0 | DK4: 0 | DL4: 0 | DM4: 0 | DN4: 0 | DO4: 0 | DP4: 0 | DQ4: 0 | DR4: 0 | DS4: 0 | DT4: 0 | DU4: 0 | DV4: 0 | DW4: 0 | DX4: 0 | DY4: 0 | DZ4: 0 | EA4: 0 | EB4: 0 | EC4: 0 | ED4: 0 | EE4: 0 | EF4: 0 | EG4: 0 | EH4: 0 | EI4: 0 | EJ4: 0 | EK4: 0 | EL4: 0 | EM4: 0 | EN4: 0 | EO4: 0 | EP4: 0 | EQ4: 0 | ER4: 0 | ES4: 0 | ET4: 0 | EU4: 0 | EV4: 0 | EW4: 0 | EX4: 59.802111 | EY4: 87.164694 | EZ4: 441.72793 | FA4: 69.924324 | FB4: 64.91331 | FC4: 18.745122 | FD4: 13.756233 | FE4: 57.662929 | FF4: 811.81079 | FG4: 2149.6917 | FH4: 1287.1184 | FI4: 24.819653 | FJ4: 21.372057 | FK4: 42.870421 | FL4: 0.20323 | FM4: 1.270526 | FN4: 2.291293 | FO4: 3.265323 | FP4: 197.34046 | FQ4: 210.841 | FR4: 1400.195 | FS4: 1096.3702 | FT4: 1282.9928 | FU4: 315.41018 | FV4: 29160.721 | FW4: 2666.3526 | FX4: 819.12312 | FY4: 81.712041 | FZ4: 23.591558 | GA4: 112.42585 | GB4: 73.946739 | GC4: 3.417835 | GD4: 211.21865 | GE4: 184.44258 | GF4: 83.103761 | GG4: 5.874729 | GH4: 5.862619 | GI4: 4.870434 | GJ4: 6.895675 | GK4: 49.412344 | GL4: 4.085866 | GM4: 7.660664 | GN4: 9.775244 | GO4: 8.162673 | GP4: 62.095424 | GQ4: 2.336303 | GR4: 0.105689 | GS4: 0.325265 | GT4: 0.076223 | GU4: 0.080757 | GV4: 0.378014 | GW4: 0.163893 | GX4: 0.082389 | GY4: 0.024513 | GZ4: 0.026762 | HA4: 0.098835 | HB4: 0.054595 | HC4: 1.756976 | HD4: 22.064161 | HE4: 89.374672 | HF4: 132.70697 | HG4: 1936.2013 | HH4: 58.01094 | HI4: 11.709584 | HJ4: 4.23145 | HK4: 106.02124 | HL4: 81.598034 | HM4: 5.596125 | HN4: 3.055962 | HO4: 27.694171 | HP4: 385.40497 | HQ4: 105.58097 | HR4: 262.01481 | HS4: 30.426676 | HT4: 277.51559 | HU4: 12.591838 | HV4: 0 | HW4: 0 | HX4: 0 | HY4: 0 | HZ4: 0 | IA4: 0 | IB4: 0 | IC4: 0 | ID4: 0 | IE4: 0 | IF4: 0 | IG4: 0 | IH4: 0 | II4: 0 | IJ4: 0 | IK4: 0 | IL4: 0 | IM4: 0 | IN4: 0 | IO4: 0 | IP4: 0 | IQ4: 0 | IR4: 0 | IS4: 0 | IT4: 0 | IU4: 0 | IV4: 0 | IW4: 0 | IX4: 0 | IY4: 0 | IZ4: 0 | JA4: 0 | JB4: 0 | JC4: 0 | JD4: 0 | JE4: 0 | JF4: 0 | JG4: 0 | JH4: 0 | JI4: 0 | JJ4: 0 | JK4: 0 | JL4: 0 | JM4: 0 | JN4: 0 | JO4: 0 | JP4: 0 | JQ4: 0 | JR4: 0 | JS4: 0 | JT4: 0 | JU4: 0 | JV4: 0 | JW4: 0 | JX4: 0 | JY4: 0 | JZ4: 0 | KA4: 0 | KB4: 0 | KC4: 0 | KD4: 0 | KE4: 0 | KF4: 0 | KG4: 0 | KH4: 0 | KI4: 0 | KJ4: 0 | KK4: 0 | KL4: 0 | KM4: 0 | KN4: 0 | KO4: 0 | KP4: 0 | KQ4: 0 | KR4: 0 | KS4: 0 | KT4: 0 | KU4: 0 | KV4: 0 | KW4: 0 | KX4: 0 | KY4: 0 | KZ4: 0 | LA4: 0 | LB4: 0 | LC4: 0 | LD4: 0 | LE4: 0 | LF4: 0 | LG4: 0 | LH4: 0 | LI4: 0 | LJ4: 0 | LK4: 0 | LL4: 0 | LM4: 0 | LN4: 0 | LO4: 0 | LP4: 0 | LQ4: 0 | LR4: 0 | LS4: 0 | LT4: 0 | LU4: 0 | LV4: 0 | LW4: 0 | LX4: 0 | LY4: 0 | LZ4: 0 | MA4: 0 | MB4: 0 | MC4: 0 | MD4: 0 | ME4: 0 | MF4: 0 | MG4: 0 | MH4: 0 | MI4: 0 | MJ4: 0 | MK4: 0 | ML4: 0 | MM4: 0 | MN4: 0 | MO4: 0 | MP4: 0 | MQ4: 0 | MR4: 0 | MS4: 0 | MT4: 0 | MU4: 0 | MV4: 0 | MW4: 0 | MX4: 0 | MY4: 0 | MZ4: 0 | NA4: 0 | NB4: 0 | NC4: 0 | ND4: 0 | NE4: 0 | NF4: 0 | NG4: 0 | NH4: 0 | NI4: 0 | NJ4: 0 | NK4: 0 | NL4: 0 | NM4: 0 | NN4: 0 | NO4: 0 | NP4: 0 | NQ4: 0 | NR4: 0 | NS4: 0 | NT4: 0 | NU4: 0 | NV4: 0 | NW4: 0 | NX4: 0 | NY4: 0 | NZ4: 0 | OA4: 0 | OB4: 0 | OC4: 0 | OD4: 0 | OE4: 0 | OF4: 0 | OG4: 0 | OH4: 0 | OI4: 0 | OJ4: 0 | OK4: 0 | OL4: 12074.411 | OM4: 0 | ON4: 0 | OO4: 86.524537 | OP4: 415.99214 | OQ4: 59380.548
A5: 4 m_v_f | B5: 0 | C5: 0 | D5: 0 | E5: 0 | F5: 0 | G5: 0 | H5: 0 | I5: 0 | J5: 0 | K5: 0 | L5: 0 | M5: 0 | N5: 0 | O5: 0 | P5: 0 | Q5: 0 | R5: 0 | S5: 0 | T5: 0 | U5: 0 | V5: 0 | W5: 0 | X5: 0 | Y5: 0 | Z5: 0 | AA5: 0 | AB5: 0 | AC5: 0 | AD5: 0 | AE5: 0 | AF5: 0 | AG5: 0 | AH5: 0 | AI5: 0 | AJ5: 0 | AK5: 0 | AL5: 0 | AM5: 0 | AN5: 0 | AO5: 0 | AP5: 0 | AQ5: 0 | AR5: 0 | AS5: 0 | AT5: 0 | AU5: 0 | AV5: 0 | AW5: 0 | AX5: 0 | AY5: 0 | AZ5: 0 | BA5: 0 | BB5: 0 | BC5: 0 | BD5: 0 | BE5: 0 | BF5: 0 | BG5: 0 | BH5: 0 | BI5: 0 | BJ5: 0 | BK5: 0 | BL5: 0 | BM5: 0 | BN5: 0 | BO5: 0 | BP5: 0 | BQ5: 0 | BR5: 0 | BS5: 0 | BT5: 0 | BU5: 0 | BV5: 0 | BW5: 0 | BX5: 0 | BY5: 0 | BZ5: 0 | CA5: 0 | CB5: 0 | CC5: 0 | CD5: 0 | CE5: 0 | CF5: 0 | CG5: 0 | CH5: 0 | CI5: 0 | CJ5: 0 | CK5: 0 | CL5: 0 | CM5: 0 | CN5: 0 | CO5: 0 | CP5: 0 | CQ5: 0 | CR5: 0 | CS5: 0 | CT5: 0 | CU5: 0 | CV5: 0 | CW5: 0 | CX5: 0 | CY5: 0 | CZ5: 0 | DA5: 0 | DB5: 0 | DC5: 0 | DD5: 0 | DE5: 0 | DF5: 0 | DG5: 0 | DH5: 0 | DI5: 0 | DJ5: 0 | DK5: 0 | DL5: 0 | DM5: 0 | DN5: 0 | DO5: 0 | DP5: 0 | DQ5: 0 | DR5: 0 | DS5: 0 | DT5: 0 | DU5: 0 | DV5: 0 | DW5: 0 | DX5: 0 | DY5: 0 | DZ5: 0 | EA5: 0 | EB5: 0 | EC5: 0 | ED5: 0 | EE5: 0 | EF5: 0 | EG5: 0 | EH5: 0 | EI5: 0 | EJ5: 0 | EK5: 0 | EL5: 0 | EM5: 0 | EN5: 0 | EO5: 0 | EP5: 0 | EQ5: 0 | ER5: 0 | ES5: 0 | ET5: 0 | EU5: 0 | EV5: 0 | EW5: 0 | EX5: 131.31509 | EY5: 97.266578 | EZ5: 206.61621 | FA5: 3283.3051 | FB5: 136.31586 | FC5: 41.92572 | FD5: 33.955108 | FE5: 124.34108 | FF5: 1707.2173 | FG5: 4947.5209 | FH5: 2371.0961 | FI5: 230.85322 | FJ5: 81.14235 | FK5: 92.60647 | FL5: 1.299674 | FM5: 8.658621 | FN5: 2.611968 | FO5: 5.939336 | FP5: 519.22246 | FQ5: 848.29567 | FR5: 4366.2251 | FS5: 2378.1913 | FT5: 1689.2962 | FU5: 1734.0156 | FV5: 28990.43 | FW5: 8076.6378 | FX5: 1574.8476 | FY5: 402.595 | FZ5: 105.71283 | GA5: 133.70382 | GB5: 207.54368 | GC5: 4.359918 | GD5: 311.35496 | GE5: 785.66395 | GF5: 67.534792 | GG5: 11.323707 | GH5: 7.882014 | GI5: 40.035366 | GJ5: 20.086595 | GK5: 6.199685 | GL5: 5.652898 | GM5: 10.888092 | GN5: 9.926201 | GO5: 5.862162 | GP5: 133.31767 | GQ5: 4.243238 | GR5: 0.325346 | GS5: 1.823762 | GT5: 0.128632 | GU5: 0.179922 | GV5: 0.563824 | GW5: 0.090044 | GX5: 0.277122 | GY5: 0.071115 | GZ5: 0.083452 | HA5: 0.198812 | HB5: 0.136907 | HC5: 5.397639 | HD5: 19.185373 | HE5: 178.79762 | HF5: 12.228009 | HG5: 5913.0041 | HH5: 154.27533 | HI5: 23.624253 | HJ5: 0.3256 | HK5: 298.33602 | HL5: 63.602048 | HM5: 25.277192 | HN5: 10.861277 | HO5: 17.977848 | HP5: 486.43357 | HQ5: 1208.9807 | HR5: 236.08148 | HS5: 11.267352 | HT5: 1686.0943 | HU5: 38.475129 | HV5: 0 | HW5: 0 | HX5: 0 | HY5: 0 | HZ5: 0 | IA5: 0 | IB5: 0 | IC5: 0 | ID5: 0 | IE5: 0 | IF5: 0 | IG5: 0 | IH5: 0 | II5: 0 | IJ5: 0 | IK5: 0 | IL5: 0 | IM5: 0 | IN5: 0 | IO5: 0 | IP5: 0 | IQ5: 0 | IR5: 0 | IS5: 0 | IT5: 0 | IU5: 0 | IV5: 0 | IW5: 0 | IX5: 0 | IY5: 0 | IZ5: 0 | JA5: 0 | JB5: 0 | JC5: 0 | JD5: 0 | JE5: 0 | JF5: 0 | JG5: 0 | JH5: 0 | JI5: 0 | JJ5: 0 | JK5: 0 | JL5: 0 | JM5: 0 | JN5: 0 | JO5: 0 | JP5: 0 | JQ5: 0 | JR5: 0 | JS5: 0 | JT5: 0 | JU5: 0 | JV5: 0 | JW5: 0 | JX5: 0 | JY5: 0 | JZ5: 0 | KA5: 0 | KB5: 0 | KC5: 0 | KD5: 0 | KE5: 0 | KF5: 0 | KG5: 0 | KH5: 0 | KI5: 0 | KJ5: 0 | KK5: 0 | KL5: 0 | KM5: 0 | KN5: 0 | KO5: 0 | KP5: 0 | KQ5: 0 | KR5: 0 | KS5: 0 | KT5: 0 | KU5: 0 | KV5: 0 | KW5: 0 | KX5: 0 | KY5: 0 | KZ5: 0 | LA5: 0 | LB5: 0 | LC5: 0 | LD5: 0 | LE5: 0 | LF5: 0 | LG5: 0 | LH5: 0 | LI5: 0 | LJ5: 0 | LK5: 0 | LL5: 0 | LM5: 0 | LN5: 0 | LO5: 0 | LP5: 0 | LQ5: 0 | LR5: 0 | LS5: 0 | LT5: 0 | LU5: 0 | LV5: 0 | LW5: 0 | LX5: 0 | LY5: 0 | LZ5: 0 | MA5: 0 | MB5: 0 | MC5: 0 | MD5: 0 | ME5: 0 | MF5: 0 | MG5: 0 | MH5: 0 | MI5: 0 | MJ5: 0 | MK5: 0 | ML5: 0 | MM5: 0 | MN5: 0 | MO5: 0 | MP5: 0 | MQ5: 0 | MR5: 0 | MS5: 0 | MT5: 0 | MU5: 0 | MV5: 0 | MW5: 0 | MX5: 0 | MY5: 0 | MZ5: 0 | NA5: 0 | NB5: 0 | NC5: 0 | ND5: 0 | NE5: 0 | NF5: 0 | NG5: 0 | NH5: 0 | NI5: 0 | NJ5: 0 | NK5: 0 | NL5: 0 | NM5: 0 | NN5: 0 | NO5: 0 | NP5: 0 | NQ5: 0 | NR5: 0 | NS5: 0 | NT5: 0 | NU5: 0 | NV5: 0 | NW5: 0 | NX5: 0 | NY5: 0 | NZ5: 0 | OA5: 0 | OB5: 0 | OC5: 0 | OD5: 0 | OE5: 0 | OF5: 0 | OG5: 0 | OH5: 0 | OI5: 0 | OJ5: 0 | OK5: 0 | OL5: 95905.287 | OM5: 0 | ON5: 0 | OO5: 218.41431 | OP5: 2101.3085 | OQ5: 174574.15
A6: 5 m_osd | B6: 0 | C6: 0 | D6: 0 | E6: 0 | F6: 0 | G6: 0 | H6: 0 | I6: 0 | J6: 0 | K6: 0 | L6: 0 | M6: 0 | N6: 0 | O6: 0 | P6: 0 | Q6: 0 | R6: 0 | S6: 0 | T6: 0 | U6: 0 | V6: 0 | W6: 0 | X6: 0 | Y6: 0 | Z6: 0 | AA6: 0 | AB6: 0 | AC6: 0 | AD6: 0 | AE6: 0 | AF6: 0 | AG6: 0 | AH6: 0 | AI6: 0 | AJ6: 0 | AK6: 0 | AL6: 0 | AM6: 0 | AN6: 0 | AO6: 0 | AP6: 0 | AQ6: 0 | AR6: 0 | AS6: 0 | AT6: 0 | AU6: 0 | AV6: 0 | AW6: 0 | AX6: 0 | AY6: 0 | AZ6: 0 | BA6: 0 | BB6: 0 | BC6: 0 | BD6: 0 | BE6: 0 | BF6: 0 | BG6: 0 | BH6: 0 | BI6: 0 | BJ6: 0 | BK6: 0 | BL6: 0 | BM6: 0 | BN6: 0 | BO6: 0 | BP6: 0 | BQ6: 0 | BR6: 0 | BS6: 0 | BT6: 0 | BU6: 0 | BV6: 0 | BW6: 0 | BX6: 0 | BY6: 0 | BZ6: 0 | CA6: 0 | CB6: 0 | CC6: 0 | CD6: 0 | CE6: 0 | CF6: 0 | CG6: 0 | CH6: 0 | CI6: 0 | CJ6: 0 | CK6: 0 | CL6: 0 | CM6: 0 | CN6: 0 | CO6: 0 | CP6: 0 | CQ6: 0 | CR6: 0 | CS6: 0 | CT6: 0 | CU6: 0 | CV6: 0 | CW6: 0 | CX6: 0 | CY6: 0 | CZ6: 0 | DA6: 0 | DB6: 0 | DC6: 0 | DD6: 0 | DE6: 0 | DF6: 0 | DG6: 0 | DH6: 0 | DI6: 0 | DJ6: 0 | DK6: 0 | DL6: 0 | DM6: 0 | DN6: 0 | DO6: 0 | DP6: 0 | DQ6: 0 | DR6: 0 | DS6: 0 | DT6: 0 | DU6: 0 | DV6: 0 | DW6: 0 | DX6: 0 | DY6: 0 | DZ6: 0 | EA6: 0 | EB6: 0 | EC6: 0 | ED6: 0 | EE6: 0 | EF6: 0 | EG6: 0 | EH6: 0 | EI6: 0 | EJ6: 0 | EK6: 0 | EL6: 0 | EM6: 0 | EN6: 0 | EO6: 0 | EP6: 0 | EQ6: 0 | ER6: 0 | ES6: 0 | ET6: 0 | EU6: 0 | EV6: 0 | EW6: 0 | EX6: 67.701677 | EY6: 41.742804 | EZ6: 84.148946 | FA6: 891.81685 | FB6: 1967.9176 | FC6: 11.831287 | FD6: 32.23805 | FE6: 94.237807 | FF6: 347.83252 | FG6: 1347.5833 | FH6: 511.8026 | FI6: 53.406258 | FJ6: 191.51003 | FK6: 39.513713 | FL6: 0.101044 | FM6: 0.629071 | FN6: 16.851862 | FO6: 1.434125 | FP6: 168.2311 | FQ6: 122.25242 | FR6: 35716.246 | FS6: 486.42591 | FT6: 882.67411 | FU6: 1499.1264 | FV6: 9509.2301 | FW6: 1285.2626 | FX6: 877.37481 | FY6: 164.09388 | FZ6: 110.27488 | GA6: 98.830112 | GB6: 101.23195 | GC6: 9.412132 | GD6: 271.70192 | GE6: 203.11241 | GF6: 15.560544 | GG6: 4.13454 | GH6: 1.121751 | GI6: 1.146171 | GJ6: 3.180897 | GK6: 3.132644 | GL6: 2.830879 | GM6: 5.904166 | GN6: 8.787581 | GO6: 2.162244 | GP6: 31.073463 | GQ6: 1.615553 | GR6: 0.193197 | GS6: 0.558379 | GT6: 0.034135 | GU6: 0.11317 | GV6: 0.574083 | GW6: 0.004323 | GX6: 0.066101 | GY6: 0.043937 | GZ6: 0.038943 | HA6: 0.076955 | HB6: 0.046659 | HC6: 1.00332 | HD6: 1.798135 | HE6: 111.48627 | HF6: 84.043132 | HG6: 1460.972 | HH6: 118.51167 | HI6: 20.488776 | HJ6: 1.234482 | HK6: 131.30893 | HL6: 19.45472 | HM6: 1.992596 | HN6: 0.92018 | HO6: 6.843724 | HP6: 845.44123 | HQ6: 68.148275 | HR6: 2342.0338 | HS6: 4.4037 | HT6: 33.854961 | HU6: 10.41688 | HV6: 0 | HW6: 0 | HX6: 0 | HY6: 0 | HZ6: 0 | IA6: 0 | IB6: 0 | IC6: 0 | ID6: 0 | IE6: 0 | IF6: 0 | IG6: 0 | IH6: 0 | II6: 0 | IJ6: 0 | IK6: 0 | IL6: 0 | IM6: 0 | IN6: 0 | IO6: 0 | IP6: 0 | IQ6: 0 | IR6: 0 | IS6: 0 | IT6: 0 | IU6: 0 | IV6: 0 | IW6: 0 | IX6: 0 | IY6: 0 | IZ6: 0 | JA6: 0 | JB6: 0 | JC6: 0 | JD6: 0 | JE6: 0 | JF6: 0 | JG6: 0 | JH6: 0 | JI6: 0 | JJ6: 0 | JK6: 0 | JL6: 0 | JM6: 0 | JN6: 0 | JO6: 0 | JP6: 0 | JQ6: 0 | JR6: 0 | JS6: 0 | JT6: 0 | JU6: 0 | JV6: 0 | JW6: 0 | JX6: 0 | JY6: 0 | JZ6: 0 | KA6: 0 | KB6: 0 | KC6: 0 | KD6: 0 | KE6: 0 | KF6: 0 | KG6: 0 | KH6: 0 | KI6: 0 | KJ6: 0 | KK6: 0 | KL6: 0 | KM6: 0 | KN6: 0 | KO6: 0 | KP6: 0 | KQ6: 0 | KR6: 0 | KS6: 0 | KT6: 0 | KU6: 0 | KV6: 0 | KW6: 0 | KX6: 0 | KY6: 0 | KZ6: 0 | LA6: 0 | LB6: 0 | LC6: 0 | LD6: 0 | LE6: 0 | LF6: 0 | LG6: 0 | LH6: 0 | LI6: 0 | LJ6: 0 | LK6: 0 | LL6: 0 | LM6: 0 | LN6: 0 | LO6: 0 | LP6: 0 | LQ6: 0 | LR6: 0 | LS6: 0 | LT6: 0 | LU6: 0 | LV6: 0 | LW6: 0 | LX6: 0 | LY6: 0 | LZ6: 0 | MA6: 0 | MB6: 0 | MC6: 0 | MD6: 0 | ME6: 0 | MF6: 0 | MG6: 0 | MH6: 0 | MI6: 0 | MJ6: 0 | MK6: 0 | ML6: 0 | MM6: 0 | MN6: 0 | MO6: 0 | MP6: 0 | MQ6: 0 | MR6: 0 | MS6: 0 | MT6: 0 | MU6: 0 | MV6: 0 | MW6: 0 | MX6: 0 | MY6: 0 | MZ6: 0 | NA6: 0 | NB6: 0 | NC6: 0 | ND6: 0 | NE6: 0 | NF6: 0 | NG6: 0 | NH6: 0 | NI6: 0 | NJ6: 0 | NK6: 0 | NL6: 0 | NM6: 0 | NN6: 0 | NO6: 0 | NP6: 0 | NQ6: 0 | NR6: 0 | NS6: 0 | NT6: 0 | NU6: 0 | NV6: 0 | NW6: 0 | NX6: 0 | NY6: 0 | NZ6: 0 | OA6: 0 | OB6: 0 | OC6: 0 | OD6: 0 | OE6: 0 | OF6: 0 | OG6: 0 | OH6: 0 | OI6: 0 | OJ6: 0 | OK6: 0 | OL6: 33065.012 | OM6: 0 | ON6: 0 | OO6: 1.936932 | OP6: 191.23864 | OQ6: 95812.726
A7: 6 m_c_b | B7: 0 | C7: 0 | D7: 0 | E7: 0 | F7: 0 | G7: 0 | H7: 0 | I7: 0 | J7: 0 | K7: 0 | L7: 0 | M7: 0 | N7: 0 | O7: 0 | P7: 0 | Q7: 0 | R7: 0 | S7: 0 | T7: 0 | U7: 0 | V7: 0 | W7: 0 | X7: 0 | Y7: 0 | Z7: 0 | AA7: 0 | AB7: 0 | AC7: 0 | AD7: 0 | AE7: 0 | AF7: 0 | AG7: 0 | AH7: 0 | AI7: 0 | AJ7: 0 | AK7: 0 | AL7: 0 | AM7: 0 | AN7: 0 | AO7: 0 | AP7: 0 | AQ7: 0 | AR7: 0 | AS7: 0 | AT7: 0 | AU7: 0 | AV7: 0 | AW7: 0 | AX7: 0 | AY7: 0 | AZ7: 0 | BA7: 0 | BB7: 0 | BC7: 0 | BD7: 0 | BE7: 0 | BF7: 0 | BG7: 0 | BH7: 0 | BI7: 0 | BJ7: 0 | BK7: 0 | BL7: 0 | BM7: 0 | BN7: 0 | BO7: 0 | BP7: 0 | BQ7: 0 | BR7: 0 | BS7: 0 | BT7: 0 | BU7: 0 | BV7: 0 | BW7: 0 | BX7: 0 | BY7: 0 | BZ7: 0 | CA7: 0 | CB7: 0 | CC7: 0 | CD7: 0 | CE7: 0 | CF7: 0 | CG7: 0 | CH7: 0 | CI7: 0 | CJ7: 0 | CK7: 0 | CL7: 0 | CM7: 0 | CN7: 0 | CO7: 0 | CP7: 0 | CQ7: 0 | CR7: 0 | CS7: 0 | CT7: 0 | CU7: 0 | CV7: 0 | CW7: 0 | CX7: 0 | CY7: 0 | CZ7: 0 | DA7: 0 | DB7: 0 | DC7: 0 | DD7: 0 | DE7: 0 | DF7: 0 | DG7: 0 | DH7: 0 | DI7: 0 | DJ7: 0 | DK7: 0 | DL7: 0 | DM7: 0 | DN7: 0 | DO7: 0 | DP7: 0 | DQ7: 0 | DR7: 0 | DS7: 0 | DT7: 0 | DU7: 0 | DV7: 0 | DW7: 0 | DX7: 0 | DY7: 0 | DZ7: 0 | EA7: 0 | EB7: 0 | EC7: 0 | ED7: 0 | EE7: 0 | EF7: 0 | EG7: 0 | EH7: 0 | EI7: 0 | EJ7: 0 | EK7: 0 | EL7: 0 | EM7: 0 | EN7: 0 | EO7: 0 | EP7: 0 | EQ7: 0 | ER7: 0 | ES7: 0 | ET7: 0 | EU7: 0 | EV7: 0 | EW7: 0 | EX7: 0.118564 | EY7: 4.368094 | EZ7: 6.880886 | FA7: 2.884654 | FB7: 18.923938 | FC7: 5.781647 | FD7: 1.014396 | FE7: 39.37092 | FF7: 0.561027 | FG7: 0.865145 | FH7: 0.231772 | FI7: 4.193597 | FJ7: 0.067874 | FK7: 0.36169 | FL7: 0.009563 | FM7: 0.008051 | FN7: 0.027766 | FO7: 0.067574 | FP7: 2.381217 | FQ7: 2.2972 | FR7: 4.41745 | FS7: 14.251794 | FT7: 5.005916 | FU7: 505.08858 | FV7: 36.359637 | FW7: 6.728018 | FX7: 1.391978 | FY7: 0.136986 | FZ7: 0.110781 | GA7: 0.128419 | GB7: 0.18423 | GC7: 0.020244 | GD7: 0.338372 | GE7: 34.205965 | GF7: 0.094954 | GG7: 0.010185 | GH7: 0.000289 | GI7: 0.122896 | GJ7: 0.019338 | GK7: 0.0077 | GL7: 0.004333 | GM7: 0.008437 | GN7: 0.000847 | GO7: 0.00731 | GP7: 0.328095 | GQ7: 0.145048 | GR7: 0.014405 | GS7: 0.054233 | GT7: 0.000289 | GU7: 0.003491 | GV7: 0.002386 | GW7: 0.000243 | GX7: 0.004601 | GY7: 0.001841 | GZ7: 0.00041 | HA7: 0.004092 | HB7: 0.001464 | HC7: 0.007994 | HD7: 0.617015 | HE7: 0.275392 | HF7: 51.643932 | HG7: 19.166635 | HH7: 0.11945 | HI7: 0.032593 | HJ7: 0.002629 | HK7: 0.280962 | HL7: 0.088385 | HM7: 0.016366 | HN7: 0.008207 | HO7: 0.04394 | HP7: 7.460426 | HQ7: 1.609512 | HR7: 2.170023 | HS7: 1.426468 | HT7: 2.602192 | HU7: 0.026313 | HV7: 0 | HW7: 0 | HX7: 0 | HY7: 0 | HZ7: 0 | IA7: 0 | IB7: 0 | IC7: 0 | ID7: 0 | IE7: 0 | IF7: 0 | IG7: 0 | IH7: 0 | II7: 0 | IJ7: 0 | IK7: 0 | IL7: 0 | IM7: 0 | IN7: 0 | IO7: 0 | IP7: 0 | IQ7: 0 | IR7: 0 | IS7: 0 | IT7: 0 | IU7: 0 | IV7: 0 | IW7: 0 | IX7: 0 | IY7: 0 | IZ7: 0 | JA7: 0 | JB7: 0 | JC7: 0 | JD7: 0 | JE7: 0 | JF7: 0 | JG7: 0 | JH7: 0 | JI7: 0 | JJ7: 0 | JK7: 0 | JL7: 0 | JM7: 0 | JN7: 0 | JO7: 0 | JP7: 0 | JQ7: 0 | JR7: 0 | JS7: 0 | JT7: 0 | JU7: 0 | JV7: 0 | JW7: 0 | JX7: 0 | JY7: 0 | JZ7: 0 | KA7: 0 | KB7: 0 | KC7: 0 | KD7: 0 | KE7: 0 | KF7: 0 | KG7: 0 | KH7: 0 | KI7: 0 | KJ7: 0 | KK7: 0 | KL7: 0 | KM7: 0 | KN7: 0 | KO7: 0 | KP7: 0 | KQ7: 0 | KR7: 0 | KS7: 0 | KT7: 0 | KU7: 0 | KV7: 0 | KW7: 0 | KX7: 0 | KY7: 0 | KZ7: 0 | LA7: 0 | LB7: 0 | LC7: 0 | LD7: 0 | LE7: 0 | LF7: 0 | LG7: 0 | LH7: 0 | LI7: 0 | LJ7: 0 | LK7: 0 | LL7: 0 | LM7: 0 | LN7: 0 | LO7: 0 | LP7: 0 | LQ7: 0 | LR7: 0 | LS7: 0 | LT7: 0 | LU7: 0 | LV7: 0 | LW7: 0 | LX7: 0 | LY7: 0 | LZ7: 0 | MA7: 0 | MB7: 0 | MC7: 0 | MD7: 0 | ME7: 0 | MF7: 0 | MG7: 0 | MH7: 0 | MI7: 0 | MJ7: 0 | MK7: 0 | ML7: 0 | MM7: 0 | MN7: 0 | MO7: 0 | MP7: 0 | MQ7: 0 | MR7: 0 | MS7: 0 | MT7: 0 | MU7: 0 | MV7: 0 | MW7: 0 | MX7: 0 | MY7: 0 | MZ7: 0 | NA7: 0 | NB7: 0 | NC7: 0 | ND7: 0 | NE7: 0 | NF7: 0 | NG7: 0 | NH7: 0 | NI7: 0 | NJ7: 0 | NK7: 0 | NL7: 0 | NM7: 0 | NN7: 0 | NO7: 0 | NP7: 0 | NQ7: 0 | NR7: 0 | NS7: 0 | NT7: 0 | NU7: 0 | NV7: 0 | NW7: 0 | NX7: 0 | NY7: 0 | NZ7: 0 | OA7: 0 | OB7: 0 | OC7: 0 | OD7: 0 | OE7: 0 | OF7: 0 | OG7: 0 | OH7: 0 | OI7: 0 | OJ7: 0 | OK7: 0 | OL7: 16.184165 | OM7: 0 | ON7: 0 | OO7: 0.773927 | OP7: 7.23184 | OQ7: 811.40921
A8: 7 m_pfb | B8: 0 | C8: 0 | D8: 0 | E8: 0 | F8: 0 | G8: 0 | H8: 0 | I8: 0 | J8: 0 | K8: 0 | L8: 0 | M8: 0 | N8: 0 | O8: 0 | P8: 0 | Q8: 0 | R8: 0 | S8: 0 | T8: 0 | U8: 0 | V8: 0 | W8: 0 | X8: 0 | Y8: 0 | Z8: 0 | AA8: 0 | AB8: 0 | AC8: 0 | AD8: 0 | AE8: 0 | AF8: 0 | AG8: 0 | AH8: 0 | AI8: 0 | AJ8: 0 | AK8: 0 | AL8: 0 | AM8: 0 | AN8: 0 | AO8: 0 | AP8: 0 | AQ8: 0 | AR8: 0 | AS8: 0 | AT8: 0 | AU8: 0 | AV8: 0 | AW8: 0 | AX8: 0 | AY8: 0 | AZ8: 0 | BA8: 0 | BB8: 0 | BC8: 0 | BD8: 0 | BE8: 0 | BF8: 0 | BG8: 0 | BH8: 0 | BI8: 0 | BJ8: 0 | BK8: 0 | BL8: 0 | BM8: 0 | BN8: 0 | BO8: 0 | BP8: 0 | BQ8: 0 | BR8: 0 | BS8: 0 | BT8: 0 | BU8: 0 | BV8: 0 | BW8: 0 | BX8: 0 | BY8: 0 | BZ8: 0 | CA8: 0 | CB8: 0 | CC8: 0 | CD8: 0 | CE8: 0 | CF8: 0 | CG8: 0 | CH8: 0 | CI8: 0 | CJ8: 0 | CK8: 0 | CL8: 0 | CM8: 0 | CN8: 0 | CO8: 0 | CP8: 0 | CQ8: 0 | CR8: 0 | CS8: 0 | CT8: 0 | CU8: 0 | CV8: 0 | CW8: 0 | CX8: 0 | CY8: 0 | CZ8: 0 | DA8: 0 | DB8: 0 | DC8: 0 | DD8: 0 | DE8: 0 | DF8: 0 | DG8: 0 | DH8: 0 | DI8: 0 | DJ8: 0 | DK8: 0 | DL8: 0 | DM8: 0 | DN8: 0 | DO8: 0 | DP8: 0 | DQ8: 0 | DR8: 0 | DS8: 0 | DT8: 0 | DU8: 0 | DV8: 0 | DW8: 0 | DX8: 0 | DY8: 0 | DZ8: 0 | EA8: 0 | EB8: 0 | EC8: 0 | ED8: 0 | EE8: 0 | EF8: 0 | EG8: 0 | EH8: 0 | EI8: 0 | EJ8: 0 | EK8: 0 | EL8: 0 | EM8: 0 | EN8: 0 | EO8: 0 | EP8: 0 | EQ8: 0 | ER8: 0 | ES8: 0 | ET8: 0 | EU8: 0 | EV8: 0 | EW8: 0 | EX8: 41.668524 | EY8: 25.350273 | EZ8: 41.456883 | FA8: 44.429567 | FB8: 34.678793 | FC8: 6.179858 | FD8: 433.26033 | FE8: 18.198296 | FF8: 68.940355 | FG8: 148.7209 | FH8: 32.202209 | FI8: 21.861097 | FJ8: 5.364689 | FK8: 21.153643 | FL8: 0.040706 | FM8: 0.086895 | FN8: 0.634152 | FO8: 0.506432 | FP8: 84.805756 | FQ8: 78.779424 | FR8: 728.59294 | FS8: 282.35195 | FT8: 486.78223 | FU8: 71.935448 | FV8: 2114.9903 | FW8: 364.75606 | FX8: 7376.8851 | FY8: 969.2586 | FZ8: 51.188621 | GA8: 60.050911 | GB8: 58.522251 | GC8: 2.287716 | GD8: 82.547087 | GE8: 135.28545 | GF8: 31.615935 | GG8: 2.483774 | GH8: 0.118322 | GI8: 0.782408 | GJ8: 0.815716 | GK8: 9.862855 | GL8: 0.231456 | GM8: 1.011511 | GN8: 0.33441 | GO8: 0.115971 | GP8: 36.377795 | GQ8: 1.044352 | GR8: 0.087291 | GS8: 0.25295 | GT8: 0.018457 | GU8: 0.015029 | GV8: 0.398115 | GW8: 0.002993 | GX8: 0.035515 | GY8: 0.024574 | GZ8: 0.016893 | HA8: 0.034263 | HB8: 0.013852 | HC8: 0.260222 | HD8: 7.988883 | HE8: 39.39703 | HF8: 102.63003 | HG8: 78.340998 | HH8: 4.277426 | HI8: 0.769206 | HJ8: 0.86297 | HK8: 80.116248 | HL8: 5.885594 | HM8: 0.354449 | HN8: 0.287908 | HO8: 0.969761 | HP8: 112.02483 | HQ8: 13.410138 | HR8: 31.726522 | HS8: 28.395513 | HT8: 45.374655 | HU8: 7.337288 | HV8: 0 | HW8: 0 | HX8: 0 | HY8: 0 | HZ8: 0 | IA8: 0 | IB8: 0 | IC8: 0 | ID8: 0 | IE8: 0 | IF8: 0 | IG8: 0 | IH8: 0 | II8: 0 | IJ8: 0 | IK8: 0 | IL8: 0 | IM8: 0 | IN8: 0 | IO8: 0 | IP8: 0 | IQ8: 0 | IR8: 0 | IS8: 0 | IT8: 0 | IU8: 0 | IV8: 0 | IW8: 0 | IX8: 0 | IY8: 0 | IZ8: 0 | JA8: 0 | JB8: 0 | JC8: 0 | JD8: 0 | JE8: 0 | JF8: 0 | JG8: 0 | JH8: 0 | JI8: 0 | JJ8: 0 | JK8: 0 | JL8: 0 | JM8: 0 | JN8: 0 | JO8: 0 | JP8: 0 | JQ8: 0 | JR8: 0 | JS8: 0 | JT8: 0 | JU8: 0 | JV8: 0 | JW8: 0 | JX8: 0 | JY8: 0 | JZ8: 0 | KA8: 0 | KB8: 0 | KC8: 0 | KD8: 0 | KE8: 0 | KF8: 0 | KG8: 0 | KH8: 0 | KI8: 0 | KJ8: 0 | KK8: 0 | KL8: 0 | KM8: 0 | KN8: 0 | KO8: 0 | KP8: 0 | KQ8: 0 | KR8: 0 | KS8: 0 | KT8: 0 | KU8: 0 | KV8: 0 | KW8: 0 | KX8: 0 | KY8: 0 | KZ8: 0 | LA8: 0 | LB8: 0 | LC8: 0 | LD8: 0 | LE8: 0 | LF8: 0 | LG8: 0 | LH8: 0 | LI8: 0 | LJ8: 0 | LK8: 0 | LL8: 0 | LM8: 0 | LN8: 0 | LO8: 0 | LP8: 0 | LQ8: 0 | LR8: 0 | LS8: 0 | LT8: 0 | LU8: 0 | LV8: 0 | LW8: 0 | LX8: 0 | LY8: 0 | LZ8: 0 | MA8: 0 | MB8: 0 | MC8: 0 | MD8: 0 | ME8: 0 | MF8: 0 | MG8: 0 | MH8: 0 | MI8: 0 | MJ8: 0 | MK8: 0 | ML8: 0 | MM8: 0 | MN8: 0 | MO8: 0 | MP8: 0 | MQ8: 0 | MR8: 0 | MS8: 0 | MT8: 0 | MU8: 0 | MV8: 0 | MW8: 0 | MX8: 0 | MY8: 0 | MZ8: 0 | NA8: 0 | NB8: 0 | NC8: 0 | ND8: 0 | NE8: 0 | NF8: 0 | NG8: 0 | NH8: 0 | NI8: 0 | NJ8: 0 | NK8: 0 | NL8: 0 | NM8: 0 | NN8: 0 | NO8: 0 | NP8: 0 | NQ8: 0 | NR8: 0 | NS8: 0 | NT8: 0 | NU8: 0 | NV8: 0 | NW8: 0 | NX8: 0 | NY8: 0 | NZ8: 0 | OA8: 0 | OB8: 0 | OC8: 0 | OD8: 0 | OE8: 0 | OF8: 0 | OG8: 0 | OH8: 0 | OI8: 0 | OJ8: 0 | OK8: 0 | OL8: 3896.6892 | OM8: 0 | ON8: 0 | OO8: 19.250937 | OP8: 200.69185 | OQ8: 18656.49
A9: 8 m_ocr | B9: 0 | C9: 0 | D9: 0 | E9: 0 | F9: 0 | G9: 0 | H9: 0 | I9: 0 | J9: 0 | K9: 0 | L9: 0 | M9: 0 | N9: 0 | O9: 0 | P9: 0 | Q9: 0 | R9: 0 | S9: 0 | T9: 0 | U9: 0 | V9: 0 | W9: 0 | X9: 0 | Y9: 0 | Z9: 0 | AA9: 0 | AB9: 0 | AC9: 0 | AD9: 0 | AE9: 0 | AF9: 0 | AG9: 0 | AH9: 0 | AI9: 0 | AJ9: 0 | AK9: 0 | AL9: 0 | AM9: 0 | AN9: 0 | AO9: 0 | AP9: 0 | AQ9: 0 | AR9: 0 | AS9: 0 | AT9: 0 | AU9: 0 | AV9: 0 | AW9: 0 | AX9: 0 | AY9: 0 | AZ9: 0 | BA9: 0 | BB9: 0 | BC9: 0 | BD9: 0 | BE9: 0 | BF9: 0 | BG9: 0 | BH9: 0 | BI9: 0 | BJ9: 0 | BK9: 0 | BL9: 0 | BM9: 0 | BN9: 0 | BO9: 0 | BP9: 0 | BQ9: 0 | BR9: 0 | BS9: 0 | BT9: 0 | BU9: 0 | BV9: 0 | BW9: 0 | BX9: 0 | BY9: 0 | BZ9: 0 | CA9: 0 | CB9: 0 | CC9: 0 | CD9: 0 | CE9: 0 | CF9: 0 | CG9: 0 | CH9: 0 | CI9: 0 | CJ9: 0 | CK9: 0 | CL9: 0 | CM9: 0 | CN9: 0 | CO9: 0 | CP9: 0 | CQ9: 0 | CR9: 0 | CS9: 0 | CT9: 0 | CU9: 0 | CV9: 0 | CW9: 0 | CX9: 0 | CY9: 0 | CZ9: 0 | DA9: 0 | DB9: 0 | DC9: 0 | DD9: 0 | DE9: 0 | DF9: 0 | DG9: 0 | DH9: 0 | DI9: 0 | DJ9: 0 | DK9: 0 | DL9: 0 | DM9: 0 | DN9: 0 | DO9: 0 | DP9: 0 | DQ9: 0 | DR9: 0 | DS9: 0 | DT9: 0 | DU9: 0 | DV9: 0 | DW9: 0 | DX9: 0 | DY9: 0 | DZ9: 0 | EA9: 0 | EB9: 0 | EC9: 0 | ED9: 0 | EE9: 0 | EF9: 0 | EG9: 0 | EH9: 0 | EI9: 0 | EJ9: 0 | EK9: 0 | EL9: 0 | EM9: 0 | EN9: 0 | EO9: 0 | EP9: 0 | EQ9: 0 | ER9: 0 | ES9: 0 | ET9: 0 | EU9: 0 | EV9: 0 | EW9: 0 | EX9: 27.780114 | EY9: 11.483454 | EZ9: 230.01659 | FA9: 499.39289 | FB9: 82.301789 | FC9: 45.228431 | FD9: 8.293381 | FE9: 1036.0088 | FF9: 1023.1904 | FG9: 563.28779 | FH9: 1613.1155 | FI9: 80.007215 | FJ9: 272.2951 | FK9: 10.723707 | FL9: 0.586792 | FM9: 2.349604 | FN9: 1.221215 | FO9: 2.856416 | FP9: 47.117779 | FQ9: 59.027754 | FR9: 447.14382 | FS9: 188.96896 | FT9: 205.9705 | FU9: 182.58815 | FV9: 17192.595 | FW9: 14850.135 | FX9: 688.72275 | FY9: 137.48031 | FZ9: 294.06768 | GA9: 37.428532 | GB9: 73.513659 | GC9: 14.194704 | GD9: 84.040604 | GE9: 314.485 | GF9: 5071.5623 | GG9: 21.402095 | GH9: 2.151652 | GI9: 25.354653 | GJ9: 25.306541 | GK9: 21.507043 | GL9: 15.340356 | GM9: 37.217426 | GN9: 75.196455 | GO9: 18.268252 | GP9: 220.83208 | GQ9: 15.783956 | GR9: 2.232308 | GS9: 4.382407 | GT9: 1.062798 | GU9: 1.781653 | GV9: 0.593904 | GW9: 0.234116 | GX9: 0.964668 | GY9: 0.436971 | GZ9: 0.027329 | HA9: 0.695007 | HB9: 0.470205 | HC9: 13.565549 | HD9: 2.200895 | HE9: 1327.6525 | HF9: 1137.9839 | HG9: 2204.506 | HH9: 137.4387 | HI9: 41.758892 | HJ9: 6.683539 | HK9: 55.041695 | HL9: 72.783956 | HM9: 13.170562 | HN9: 2.935283 | HO9: 45.666299 | HP9: 3043.3642 | HQ9: 560.68352 | HR9: 446.74186 | HS9: 190.64008 | HT9: 380.06424 | HU9: 34.35459 | HV9: 0 | HW9: 0 | HX9: 0 | HY9: 0 | HZ9: 0 | IA9: 0 | IB9: 0 | IC9: 0 | ID9: 0 | IE9: 0 | IF9: 0 | IG9: 0 | IH9: 0 | II9: 0 | IJ9: 0 | IK9: 0 | IL9: 0 | IM9: 0 | IN9: 0 | IO9: 0 | IP9: 0 | IQ9: 0 | IR9: 0 | IS9: 0 | IT9: 0 | IU9: 0 | IV9: 0 | IW9: 0 | IX9: 0 | IY9: 0 | IZ9: 0 | JA9: 0 | JB9: 0 | JC9: 0 | JD9: 0 | JE9: 0 | JF9: 0 | JG9: 0 | JH9: 0 | JI9: 0 | JJ9: 0 | JK9: 0 | JL9: 0 | JM9: 0 | JN9: 0 | JO9: 0 | JP9: 0 | JQ9: 0 | JR9: 0 | JS9: 0 | JT9: 0 | JU9: 0 | JV9: 0 | JW9: 0 | JX9: 0 | JY9: 0 | JZ9: 0 | KA9: 0 | KB9: 0 | KC9: 0 | KD9: 0 | KE9: 0 | KF9: 0 | KG9: 0 | KH9: 0 | KI9: 0 | KJ9: 0 | KK9: 0 | KL9: 0 | KM9: 0 | KN9: 0 | KO9: 0 | KP9: 0 | KQ9: 0 | KR9: 0 | KS9: 0 | KT9: 0 | KU9: 0 | KV9: 0 | KW9: 0 | KX9: 0 | KY9: 0 | KZ9: 0 | LA9: 0 | LB9: 0 | LC9: 0 | LD9: 0 | LE9: 0 | LF9: 0 | LG9: 0 | LH9: 0 | LI9: 0 | LJ9: 0 | LK9: 0 | LL9: 0 | LM9: 0 | LN9: 0 | LO9: 0 | LP9: 0 | LQ9: 0 | LR9: 0 | LS9: 0 | LT9: 0 | LU9: 0 | LV9: 0 | LW9: 0 | LX9: 0 | LY9: 0 | LZ9: 0 | MA9: 0 | MB9: 0 | MC9: 0 | MD9: 0 | ME9: 0 | MF9: 0 | MG9: 0 | MH9: 0 | MI9: 0 | MJ9: 0 | MK9: 0 | ML9: 0 | MM9: 0 | MN9: 0 | MO9: 0 | MP9: 0 | MQ9: 0 | MR9: 0 | MS9: 0 | MT9: 0 | MU9: 0 | MV9: 0 | MW9: 0 | MX9: 0 | MY9: 0 | MZ9: 0 | NA9: 0 | NB9: 0 | NC9: 0 | ND9: 0 | NE9: 0 | NF9: 0 | NG9: 0 | NH9: 0 | NI9: 0 | NJ9: 0 | NK9: 0 | NL9: 0 | NM9: 0 | NN9: 0 | NO9: 0 | NP9: 0 | NQ9: 0 | NR9: 0 | NS9: 0 | NT9: 0 | NU9: 0 | NV9: 0 | NW9: 0 | NX9: 0 | NY9: 0 | NZ9: 0 | OA9: 0 | OB9: 0 | OC9: 0 | OD9: 0 | OE9: 0 | OF9: 0 | OG9: 0 | OH9: 0 | OI9: 0 | OJ9: 0 | OK9: 0 | OL9: 18343.613 | OM9: 0 | ON9: 0 | OO9: 58.279062 | OP9: 620.24811 | OQ9: 74629.799
A10: 9 m_ctl | B10: 0 | C10: 0 | D10: 0 | E10: 0 | F10: 0 | G10: 0 | H10: 0 | I10: 0 | J10: 0 | K10: 0 | L10: 0 | M10: 0 | N10: 0 | O10: 0 | P10: 0 | Q10: 0 | R10: 0 | S10: 0 | T10: 0 | U10: 0 | V10: 0 | W10: 0 | X10: 0 | Y10: 0 | Z10: 0 | AA10: 0 | AB10: 0 | AC10: 0 | AD10: 0 | AE10: 0 | AF10: 0 | AG10: 0 | AH10: 0 | AI10: 0 | AJ10: 0 | AK10: 0 | AL10: 0 | AM10: 0 | AN10: 0 | AO10: 0 | AP10: 0 | AQ10: 0 | AR10: 0 | AS10: 0 | AT10: 0 | AU10: 0 | AV10: 0 | AW10: 0 | AX10: 0 | AY10: 0 | AZ10: 0 | BA10: 0 | BB10: 0 | BC10: 0 | BD10: 0 | BE10: 0 | BF10: 0 | BG10: 0 | BH10: 0 | BI10: 0 | BJ10: 0 | BK10: 0 | BL10: 0 | BM10: 0 | BN10: 0 | BO10: 0 | BP10: 0 | BQ10: 0 | BR10: 0 | BS10: 0 | BT10: 0 | BU10: 0 | BV10: 0 | BW10: 0 | BX10: 0 | BY10: 0 | BZ10: 0 | CA10: 0 | CB10: 0 | CC10: 0 | CD10: 0 | CE10: 0 | CF10: 0 | CG10: 0 | CH10: 0 | CI10: 0 | CJ10: 0 | CK10: 0 | CL10: 0 | CM10: 0 | CN10: 0 | CO10: 0 | CP10: 0 | CQ10: 0 | CR10: 0 | CS10: 0 | CT10: 0 | CU10: 0 | CV10: 0 | CW10: 0 | CX10: 0 | CY10: 0 | CZ10: 0 | DA10: 0 | DB10: 0 | DC10: 0 | DD10: 0 | DE10: 0 | DF10: 0 | DG10: 0 | DH10: 0 | DI10: 0 | DJ10: 0 | DK10: 0 | DL10: 0 | DM10: 0 | DN10: 0 | DO10: 0 | DP10: 0 | DQ10: 0 | DR10: 0 | DS10: 0 | DT10: 0 | DU10: 0 | DV10: 0 | DW10: 0 | DX10: 0 | DY10: 0 | DZ10: 0 | EA10: 0 | EB10: 0 | EC10: 0 | ED10: 0 | EE10: 0 | EF10: 0 | EG10: 0 | EH10: 0 | EI10: 0 | EJ10: 0 | EK10: 0 | EL10: 0 | EM10: 0 | EN10: 0 | EO10: 0 | EP10: 0 | EQ10: 0 | ER10: 0 | ES10: 0 | ET10: 0 | EU10: 0 | EV10: 0 | EW10: 0 | EX10: 5.305811 | EY10: 19.181806 | EZ10: 9.820644 | FA10: 27.553406 | FB10: 14.9488 | FC10: 7.583035 | FD10: 5.79191 | FE10: 9.347047 | FF10: 915.58033 | FG10: 34.66979 | FH10: 88.118403 | FI10: 8.033436 | FJ10: 10.210787 | FK10: 78.580304 | FL10: 0.153014 | FM10: 0.535991 | FN10: 0.247014 | FO10: 0.078422 | FP10: 9156.5374 | FQ10: 1218.4683 | FR10: 45.620615 | FS10: 145.20129 | FT10: 37.5247 | FU10: 13.238515 | FV10: 714.01085 | FW10: 88.107227 | FX10: 228.95672 | FY10: 18.952058 | FZ10: 129.50816 | GA10: 4.318884 | GB10: 1.530067 | GC10: 0.193265 | GD10: 11.052618 | GE10: 267.57274 | GF10: 0.766236 | GG10: 1.70031 | GH10: 1.065376 | GI10: 2.46541 | GJ10: 2.1731 | GK10: 2.160803 | GL10: 1.447258 | GM10: 2.335737 | GN10: 0.928338 | GO10: 5.814717 | GP10: 22.234469 | GQ10: 4.595519 | GR10: 0.030789 | GS10: 2.508413 | GT10: 0.025289 | GU10: 0.233761 | GV10: 0.108338 | GW10: 0.089069 | GX10: 0.101283 | GY10: 0.048644 | GZ10: 0.019524 | HA10: 0.244771 | HB10: 0.042572 | HC10: 0.949787 | HD10: 0.340503 | HE10: 9.088898 | HF10: 87.733135 | HG10: 457.78109 | HH10: 10.545521 | HI10: 0.54674 | HJ10: 7.756283 | HK10: 3.137459 | HL10: 4.521617 | HM10: 1.380078 | HN10: 0.29853 | HO10: 1.153143 | HP10: 64.404005 | HQ10: 20.744101 | HR10: 0.546354 | HS10: 3.582408 | HT10: 58.449025 | HU10: 0.955686 | HV10: 0 | HW10: 0 | HX10: 0 | HY10: 0 | HZ10: 0 | IA10: 0 | IB10: 0 | IC10: 0 | ID10: 0 | IE10: 0 | IF10: 0 | IG10: 0 | IH10: 0 | II10: 0 | IJ10: 0 | IK10: 0 | IL10: 0 | IM10: 0 | IN10: 0 | IO10: 0 | IP10: 0 | IQ10: 0 | IR10: 0 | IS10: 0 | IT10: 0 | IU10: 0 | IV10: 0 | IW10: 0 | IX10: 0 | IY10: 0 | IZ10: 0 | JA10: 0 | JB10: 0 | JC10: 0 | JD10: 0 | JE10: 0 | JF10: 0 | JG10: 0 | JH10: 0 | JI10: 0 | JJ10: 0 | JK10: 0 | JL10: 0 | JM10: 0 | JN10: 0 | JO10: 0 | JP10: 0 | JQ10: 0 | JR10: 0 | JS10: 0 | JT10: 0 | JU10: 0 | JV10: 0 | JW10: 0 | JX10: 0 | JY10: 0 | JZ10: 0 | KA10: 0 | KB10: 0 | KC10: 0 | KD10: 0 | KE10: 0 | KF10: 0 | KG10: 0 | KH10: 0 | KI10: 0 | KJ10: 0 | KK10: 0 | KL10: 0 | KM10: 0 | KN10: 0 | KO10: 0 | KP10: 0 | KQ10: 0 | KR10: 0 | KS10: 0 | KT10: 0 | KU10: 0 | KV10: 0 | KW10: 0 | KX10: 0 | KY10: 0 | KZ10: 0 | LA10: 0 | LB10: 0 | LC10: 0 | LD10: 0 | LE10: 0 | LF10: 0 | LG10: 0 | LH10: 0 | LI10: 0 | LJ10: 0 | LK10: 0 | LL10: 0 | LM10: 0 | LN10: 0 | LO10: 0 | LP10: 0 | LQ10: 0 | LR10: 0 | LS10: 0 | LT10: 0 | LU10: 0 | LV10: 0 | LW10: 0 | LX10: 0 | LY10: 0 | LZ10: 0 | MA10: 0 | MB10: 0 | MC10: 0 | MD10: 0 | ME10: 0 | MF10: 0 | MG10: 0 | MH10: 0 | MI10: 0 | MJ10: 0 | MK10: 0 | ML10: 0 | MM10: 0 | MN10: 0 | MO10: 0 | MP10: 0 | MQ10: 0 | MR10: 0 | MS10: 0 | MT10: 0 | MU10: 0 | MV10: 0 | MW10: 0 | MX10: 0 | MY10: 0 | MZ10: 0 | NA10: 0 | NB10: 0 | NC10: 0 | ND10: 0 | NE10: 0 | NF10: 0 | NG10: 0 | NH10: 0 | NI10: 0 | NJ10: 0 | NK10: 0 | NL10: 0 | NM10: 0 | NN10: 0 | NO10: 0 | NP10: 0 | NQ10: 0 | NR10: 0 | NS10: 0 | NT10: 0 | NU10: 0 | NV10: 0 | NW10: 0 | NX10: 0 | NY10: 0 | NZ10: 0 | OA10: 0 | OB10: 0 | OC10: 0 | OD10: 0 | OE10: 0 | OF10: 0 | OG10: 0 | OH10: 0 | OI10: 0 | OJ10: 0 | OK10: 0 | OL10: 2477.3115 | OM10: 0 | ON10: 0 | OO10: 17.857298 | OP10: 1630.029 | OQ10: 18226.785
A11: 10 m_oap | B11: 0 | C11: 0 | D11: 0 | E11: 0 | F11: 0 | G11: 0 | H11: 0 | I11: 0 | J11: 0 | K11: 0 | L11: 0 | M11: 0 | N11: 0 | O11: 0 | P11: 0 | Q11: 0 | R11: 0 | S11: 0 | T11: 0 | U11: 0 | V11: 0 | W11: 0 | X11: 0 | Y11: 0 | Z11: 0 | AA11: 0 | AB11: 0 | AC11: 0 | AD11: 0 | AE11: 0 | AF11: 0 | AG11: 0 | AH11: 0 | AI11: 0 | AJ11: 0 | AK11: 0 | AL11: 0 | AM11: 0 | AN11: 0 | AO11: 0 | AP11: 0 | AQ11: 0 | AR11: 0 | AS11: 0 | AT11: 0 | AU11: 0 | AV11: 0 | AW11: 0 | AX11: 0 | AY11: 0 | AZ11: 0 | BA11: 0 | BB11: 0 | BC11: 0 | BD11: 0 | BE11: 0 | BF11: 0 | BG11: 0 | BH11: 0 | BI11: 0 | BJ11: 0 | BK11: 0 | BL11: 0 | BM11: 0 | BN11: 0 | BO11: 0 | BP11: 0 | BQ11: 0 | BR11: 0 | BS11: 0 | BT11: 0 | BU11: 0 | BV11: 0 | BW11: 0 | BX11: 0 | BY11: 0 | BZ11: 0 | CA11: 0 | CB11: 0 | CC11: 0 | CD11: 0 | CE11: 0 | CF11: 0 | CG11: 0 | CH11: 0 | CI11: 0 | CJ11: 0 | CK11: 0 | CL11: 0 | CM11: 0 | CN11: 0 | CO11: 0 | CP11: 0 | CQ11: 0 | CR11: 0 | CS11: 0 | CT11: 0 | CU11: 0 | CV11: 0 | CW11: 0 | CX11: 0 | CY11: 0 | CZ11: 0 | DA11: 0 | DB11: 0 | DC11: 0 | DD11: 0 | DE11: 0 | DF11: 0 | DG11: 0 | DH11: 0 | DI11: 0 | DJ11: 0 | DK11: 0 | DL11: 0 | DM11: 0 | DN11: 0 | DO11: 0 | DP11: 0 | DQ11: 0 | DR11: 0 | DS11: 0 | DT11: 0 | DU11: 0 | DV11: 0 | DW11: 0 | DX11: 0 | DY11: 0 | DZ11: 0 | EA11: 0 | EB11: 0 | EC11: 0 | ED11: 0 | EE11: 0 | EF11: 0 | EG11: 0 | EH11: 0 | EI11: 0 | EJ11: 0 | EK11: 0 | EL11: 0 | EM11: 0 | EN11: 0 | EO11: 0 | EP11: 0 | EQ11: 0 | ER11: 0 | ES11: 0 | ET11: 0 | EU11: 0 | EV11: 0 | EW11: 0 | EX11: 9.164769 | EY11: 19.905841 | EZ11: 27.443221 | FA11: 31.18406 | FB11: 23.010597 | FC11: 7.241134 | FD11: 3.723716 | FE11: 40.83244 | FF11: 84.60041 | FG11: 894.19037 | FH11: 130.22494 | FI11: 79.849871 | FJ11: 78.424276 | FK11: 37.713352 | FL11: 0.221458 | FM11: 1.483378 | FN11: 0.598416 | FO11: 0.868808 | FP11: 1530.5022 | FQ11: 12385.946 | FR11: 32.006777 | FS11: 368.06847 | FT11: 128.10913 | FU11: 50.640246 | FV11: 3395.012 | FW11: 445.21255 | FX11: 888.53648 | FY11: 109.88736 | FZ11: 752.11041 | GA11: 3.955232 | GB11: 7.201076 | GC11: 1.589008 | GD11: 71.936475 | GE11: 1080.6679 | GF11: 3.509028 | GG11: 4.40427 | GH11: 1.8396 | GI11: 4.005805 | GJ11: 3.452724 | GK11: 3.405755 | GL11: 3.270362 | GM11: 5.924244 | GN11: 4.811976 | GO11: 1.164634 | GP11: 83.319811 | GQ11: 2.453289 | GR11: 0.38919 | GS11: 0.55883 | GT11: 0.065379 | GU11: 0.105611 | GV11: 0.285049 | GW11: 0.112429 | GX11: 0.168035 | GY11: 0.032716 | GZ11: 0.008315 | HA11: 0.108348 | HB11: 0.102915 | HC11: 0.397084 | HD11: 0.580635 | HE11: 26.572781 | HF11: 76.928915 | HG11: 2398.1624 | HH11: 24.387868 | HI11: 6.948887 | HJ11: 3.424712 | HK11: 30.6873 | HL11: 11.250537 | HM11: 3.481103 | HN11: 0.6009 | HO11: 11.090099 | HP11: 476.15425 | HQ11: 92.975071 | HR11: 1.427316 | HS11: 17.892708 | HT11: 240.85559 | HU11: 10.329198 | HV11: 0 | HW11: 0 | HX11: 0 | HY11: 0 | HZ11: 0 | IA11: 0 | IB11: 0 | IC11: 0 | ID11: 0 | IE11: 0 | IF11: 0 | IG11: 0 | IH11: 0 | II11: 0 | IJ11: 0 | IK11: 0 | IL11: 0 | IM11: 0 | IN11: 0 | IO11: 0 | IP11: 0 | IQ11: 0 | IR11: 0 | IS11: 0 | IT11: 0 | IU11: 0 | IV11: 0 | IW11: 0 | IX11: 0 | IY11: 0 | IZ11: 0 | JA11: 0 | JB11: 0 | JC11: 0 | JD11: 0 | JE11: 0 | JF11: 0 | JG11: 0 | JH11: 0 | JI11: 0 | JJ11: 0 | JK11: 0 | JL11: 0 | JM11: 0 | JN11: 0 | JO11: 0 | JP11: 0 | JQ11: 0 | JR11: 0 | JS11: 0 | JT11: 0 | JU11: 0 | JV11: 0 | JW11: 0 | JX11: 0 | JY11: 0 | JZ11: 0 | KA11: 0 | KB11: 0 | KC11: 0 | KD11: 0 | KE11: 0 | KF11: 0 | KG11: 0 | KH11: 0 | KI11: 0 | KJ11: 0 | KK11: 0 | KL11: 0 | KM11: 0 | KN11: 0 | KO11: 0 | KP11: 0 | KQ11: 0 | KR11: 0 | KS11: 0 | KT11: 0 | KU11: 0 | KV11: 0 | KW11: 0 | KX11: 0 | KY11: 0 | KZ11: 0 | LA11: 0 | LB11: 0 | LC11: 0 | LD11: 0 | LE11: 0 | LF11: 0 | LG11: 0 | LH11: 0 | LI11: 0 | LJ11: 0 | LK11: 0 | LL11: 0 | LM11: 0 | LN11: 0 | LO11: 0 | LP11: 0 | LQ11: 0 | LR11: 0 | LS11: 0 | LT11: 0 | LU11: 0 | LV11: 0 | LW11: 0 | LX11: 0 | LY11: 0 | LZ11: 0 | MA11: 0 | MB11: 0 | MC11: 0 | MD11: 0 | ME11: 0 | MF11: 0 | MG11: 0 | MH11: 0 | MI11: 0 | MJ11: 0 | MK11: 0 | ML11: 0 | MM11: 0 | MN11: 0 | MO11: 0 | MP11: 0 | MQ11: 0 | MR11: 0 | MS11: 0 | MT11: 0 | MU11: 0 | MV11: 0 | MW11: 0 | MX11: 0 | MY11: 0 | MZ11: 0 | NA11: 0 | NB11: 0 | NC11: 0 | ND11: 0 | NE11: 0 | NF11: 0 | NG11: 0 | NH11: 0 | NI11: 0 | NJ11: 0 | NK11: 0 | NL11: 0 | NM11: 0 | NN11: 0 | NO11: 0 | NP11: 0 | NQ11: 0 | NR11: 0 | NS11: 0 | NT11: 0 | NU11: 0 | NV11: 0 | NW11: 0 | NX11: 0 | NY11: 0 | NZ11: 0 | OA11: 0 | OB11: 0 | OC11: 0 | OD11: 0 | OE11: 0 | OF11: 0 | OG11: 0 | OH11: 0 | OI11: 0 | OJ11: 0 | OK11: 0 | OL11: 7344.1087 | OM11: 0 | ON11: 0 | OO11: 24.328152 | OP11: 3019.5342 | OQ11: 36667.679
A12: 11 m_rmk | B12: 0 | C12: 0 | D12: 0 | E12: 0 | F12: 0 | G12: 0 | H12: 0 | I12: 0 | J12: 0 | K12: 0 | L12: 0 | M12: 0 | N12: 0 | O12: 0 | P12: 0 | Q12: 0 | R12: 0 | S12: 0 | T12: 0 | U12: 0 | V12: 0 | W12: 0 | X12: 0 | Y12: 0 | Z12: 0 | AA12: 0 | AB12: 0 | AC12: 0 | AD12: 0 | AE12: 0 | AF12: 0 | AG12: 0 | AH12: 0 | AI12: 0 | AJ12: 0 | AK12: 0 | AL12: 0 | AM12: 0 | AN12: 0 | AO12: 0 | AP12: 0 | AQ12: 0 | AR12: 0 | AS12: 0 | AT12: 0 | AU12: 0 | AV12: 0 | AW12: 0 | AX12: 0 | AY12: 0 | AZ12: 0 | BA12: 0 | BB12: 0 | BC12: 0 | BD12: 0 | BE12: 0 | BF12: 0 | BG12: 0 | BH12: 0 | BI12: 0 | BJ12: 0 | BK12: 0 | BL12: 0 | BM12: 0 | BN12: 0 | BO12: 0 | BP12: 0 | BQ12: 0 | BR12: 0 | BS12: 0 | BT12: 0 | BU12: 0 | BV12: 0 | BW12: 0 | BX12: 0 | BY12: 0 | BZ12: 0 | CA12: 0 | CB12: 0 | CC12: 0 | CD12: 0 | CE12: 0 | CF12: 0 | CG12: 0 | CH12: 0 | CI12: 0 | CJ12: 0 | CK12: 0 | CL12: 0 | CM12: 0 | CN12: 0 | CO12: 0 | CP12: 0 | CQ12: 0 | CR12: 0 | CS12: 0 | CT12: 0 | CU12: 0 | CV12: 0 | CW12: 0 | CX12: 0 | CY12: 0 | CZ12: 0 | DA12: 0 | DB12: 0 | DC12: 0 | DD12: 0 | DE12: 0 | DF12: 0 | DG12: 0 | DH12: 0 | DI12: 0 | DJ12: 0 | DK12: 0 | DL12: 0 | DM12: 0 | DN12: 0 | DO12: 0 | DP12: 0 | DQ12: 0 | DR12: 0 | DS12: 0 | DT12: 0 | DU12: 0 | DV12: 0 | DW12: 0 | DX12: 0 | DY12: 0 | DZ12: 0 | EA12: 0 | EB12: 0 | EC12: 0 | ED12: 0 | EE12: 0 | EF12: 0 | EG12: 0 | EH12: 0 | EI12: 0 | EJ12: 0 | EK12: 0 | EL12: 0 | EM12: 0 | EN12: 0 | EO12: 0 | EP12: 0 | EQ12: 0 | ER12: 0 | ES12: 0 | ET12: 0 | EU12: 0 | EV12: 0 | EW12: 0 | EX12: 1.346643 | EY12: 1.370889 | EZ12: 1.338919 | FA12: 1.325981 | FB12: 0.12212 | FC12: 0.184321 | FD12: 0.334318 | FE12: 24.826667 | FF12: 0.711973 | FG12: 2.267811 | FH12: 62.692242 | FI12: 0.386273 | FJ12: 0.394293 | FK12: 0.490501 | FL12: 0.003913 | FM12: 0.140926 | FN12: 0.076238 | FO12: 0.02201 | FP12: 5.162592 | FQ12: 87.389467 | FR12: 0.406832 | FS12: 88.543027 | FT12: 1.460223 | FU12: 0.723498 | FV12: 9.023116 | FW12: 4.912517 | FX12: 0.714386 | FY12: 0.184453 | FZ12: 6.579673 | GA12: 0.024146 | GB12: 0.088001 | GC12: 0.012616 | GD12: 0.251269 | GE12: 0.065738 | GF12: 0.107833 | GG12: 0.013038 | GH12: 0.002288 | GI12: 0.014298 | GJ12: 0.014318 | GK12: 0.006391 | GL12: 0.003121 | GM12: 0.007116 | GN12: 0.003293 | GO12: 0.087495 | GP12: 0.130933 | GQ12: 0.034224 | GR12: 0.004126 | GS12: 0.002256 | GT12: 0.000149 | GU12: 0.001503 | GV12: 0.022065 | GW12: 0.000547 | GX12: 0.001439 | GY12: 0.000846 | GZ12: 0.000777 | HA12: 0.000792 | HB12: 8.8e-05 | HC12: 0.000528 | HD12: 0.015955 | HE12: 0.823182 | HF12: 15.581726 | HG12: 7.924828 | HH12: 0.18117 | HI12: 0.526161 | HJ12: 0.004874 | HK12: 0.03857 | HL12: 0.302146 | HM12: 0.037297 | HN12: 0.015836 | HO12: 0.189067 | HP12: 0.387781 | HQ12: 0.332785 | HR12: 2.048949 | HS12: 0.009676 | HT12: 0.018715 | HU12: 0.136153 | HV12: 0 | HW12: 0 | HX12: 0 | HY12: 0 | HZ12: 0 | IA12: 0 | IB12: 0 | IC12: 0 | ID12: 0 | IE12: 0 | IF12: 0 | IG12: 0 | IH12: 0 | II12: 0 | IJ12: 0 | IK12: 0 | IL12: 0 | IM12: 0 | IN12: 0 | IO12: 0 | IP12: 0 | IQ12: 0 | IR12: 0 | IS12: 0 | IT12: 0 | IU12: 0 | IV12: 0 | IW12: 0 | IX12: 0 | IY12: 0 | IZ12: 0 | JA12: 0 | JB12: 0 | JC12: 0 | JD12: 0 | JE12: 0 | JF12: 0 | JG12: 0 | JH12: 0 | JI12: 0 | JJ12: 0 | JK12: 0 | JL12: 0 | JM12: 0 | JN12: 0 | JO12: 0 | JP12: 0 | JQ12: 0 | JR12: 0 | JS12: 0 | JT12: 0 | JU12: 0 | JV12: 0 | JW12: 0 | JX12: 0 | JY12: 0 | JZ12: 0 | KA12: 0 | KB12: 0 | KC12: 0 | KD12: 0 | KE12: 0 | KF12: 0 | KG12: 0 | KH12: 0 | KI12: 0 | KJ12: 0 | KK12: 0 | KL12: 0 | KM12: 0 | KN12: 0 | KO12: 0 | KP12: 0 | KQ12: 0 | KR12: 0 | KS12: 0 | KT12: 0 | KU12: 0 | KV12: 0 | KW12: 0 | KX12: 0 | KY12: 0 | KZ12: 0 | LA12: 0 | LB12: 0 | LC12: 0 | LD12: 0 | LE12: 0 | LF12: 0 | LG12: 0 | LH12: 0 | LI12: 0 | LJ12: 0 | LK12: 0 | LL12: 0 | LM12: 0 | LN12: 0 | LO12: 0 | LP12: 0 | LQ12: 0 | LR12: 0 | LS12: 0 | LT12: 0 | LU12: 0 | LV12: 0 | LW12: 0 | LX12: 0 | LY12: 0 | LZ12: 0 | MA12: 0 | MB12: 0 | MC12: 0 | MD12: 0 | ME12: 0 | MF12: 0 | MG12: 0 | MH12: 0 | MI12: 0 | MJ12: 0 | MK12: 0 | ML12: 0 | MM12: 0 | MN12: 0 | MO12: 0 | MP12: 0 | MQ12: 0 | MR12: 0 | MS12: 0 | MT12: 0 | MU12: 0 | MV12: 0 | MW12: 0 | MX12: 0 | MY12: 0 | MZ12: 0 | NA12: 0 | NB12: 0 | NC12: 0 | ND12: 0 | NE12: 0 | NF12: 0 | NG12: 0 | NH12: 0 | NI12: 0 | NJ12: 0 | NK12: 0 | NL12: 0 | NM12: 0 | NN12: 0 | NO12: 0 | NP12: 0 | NQ12: 0 | NR12: 0 | NS12: 0 | NT12: 0 | NU12: 0 | NV12: 0 | NW12: 0 | NX12: 0 | NY12: 0 | NZ12: 0 | OA12: 0 | OB12: 0 | OC12: 0 | OD12: 0 | OE12: 0 | OF12: 0 | OG12: 0 | OH12: 0 | OI12: 0 | OJ12: 0 | OK12: 0 | OL12: 36.82824 | OM12: 0 | ON12: 0 | OO12: 0.054455 | OP12: 6.110886 | OQ12: 375.60551
A13: 12 m_wol | B13: 0 | C13: 0 | D13: 0 | E13: 0 | F13: 0 | G13: 0 | H13: 0 | I13: 0 | J13: 0 | K13: 0 | L13: 0 | M13: 0 | N13: 0 | O13: 0 | P13: 0 | Q13: 0 | R13: 0 | S13: 0 | T13: 0 | U13: 0 | V13: 0 | W13: 0 | X13: 0 | Y13: 0 | Z13: 0 | AA13: 0 | AB13: 0 | AC13: 0 | AD13: 0 | AE13: 0 | AF13: 0 | AG13: 0 | AH13: 0 | AI13: 0 | AJ13: 0 | AK13: 0 | AL13: 0 | AM13: 0 | AN13: 0 | AO13: 0 | AP13: 0 | AQ13: 0 | AR13: 0 | AS13: 0 | AT13: 0 | AU13: 0 | AV13: 0 | AW13: 0 | AX13: 0 | AY13: 0 | AZ13: 0 | BA13: 0 | BB13: 0 | BC13: 0 | BD13: 0 | BE13: 0 | BF13: 0 | BG13: 0 | BH13: 0 | BI13: 0 | BJ13: 0 | BK13: 0 | BL13: 0 | BM13: 0 | BN13: 0 | BO13: 0 | BP13: 0 | BQ13: 0 | BR13: 0 | BS13: 0 | BT13: 0 | BU13: 0 | BV13: 0 | BW13: 0 | BX13: 0 | BY13: 0 | BZ13: 0 | CA13: 0 | CB13: 0 | CC13: 0 | CD13: 0 | CE13: 0 | CF13: 0 | CG13: 0 | CH13: 0 | CI13: 0 | CJ13: 0 | CK13: 0 | CL13: 0 | CM13: 0 | CN13: 0 | CO13: 0 | CP13: 0 | CQ13: 0 | CR13: 0 | CS13: 0 | CT13: 0 | CU13: 0 | CV13: 0 | CW13: 0 | CX13: 0 | CY13: 0 | CZ13: 0 | DA13: 0 | DB13: 0 | DC13: 0 | DD13: 0 | DE13: 0 | DF13: 0 | DG13: 0 | DH13: 0 | DI13: 0 | DJ13: 0 | DK13: 0 | DL13: 0 | DM13: 0 | DN13: 0 | DO13: 0 | DP13: 0 | DQ13: 0 | DR13: 0 | DS13: 0 | DT13: 0 | DU13: 0 | DV13: 0 | DW13: 0 | DX13: 0 | DY13: 0 | DZ13: 0 | EA13: 0 | EB13: 0 | EC13: 0 | ED13: 0 | EE13: 0 | EF13: 0 | EG13: 0 | EH13: 0 | EI13: 0 | EJ13: 0 | EK13: 0 | EL13: 0 | EM13: 0 | EN13: 0 | EO13: 0 | EP13: 0 | EQ13: 0 | ER13: 0 | ES13: 0 | ET13: 0 | EU13: 0 | EV13: 0 | EW13: 0 | EX13: 12.345002 | EY13: 17.20645 | EZ13: 190.1405 | FA13: 17.461375 | FB13: 107.81962 | FC13: 15.292455 | FD13: 19.855138 | FE13: 325.8604 | FF13: 39.825367 | FG13: 226.59285 | FH13: 88.279094 | FI13: 362.34656 | FJ13: 6.093003 | FK13: 5.542 | FL13: 0.059428 | FM13: 0.331927 | FN13: 1.158353 | FO13: 0.283025 | FP13: 110.29091 | FQ13: 515.02232 | FR13: 31.956227 | FS13: 224.099 | FT13: 118.5849 | FU13: 30.800879 | FV13: 1112.7083 | FW13: 31.004221 | FX13: 3259.7593 | FY13: 135.56409 | FZ13: 512.63565 | GA13: 5.792961 | GB13: 0.803446 | GC13: 1.935708 | GD13: 72.202301 | GE13: 1308.3581 | GF13: 12.523111 | GG13: 1.653999 | GH13: 0.889735 | GI13: 1.072412 | GJ13: 0.77044 | GK13: 1.377125 | GL13: 1.037794 | GM13: 2.257672 | GN13: 1.146302 | GO13: 0.343335 | GP13: 49.608006 | GQ13: 0.45374 | GR13: 0.023283 | GS13: 0.08847 | GT13: 0.045788 | GU13: 0.017102 | GV13: 0.193178 | GW13: 0.005137 | GX13: 0.086692 | GY13: 0.0051 | GZ13: 0.007551 | HA13: 0.023327 | HB13: 0.031371 | HC13: 0.473518 | HD13: 0.090475 | HE13: 36.407904 | HF13: 12.475392 | HG13: 566.66882 | HH13: 3.386987 | HI13: 1.504942 | HJ13: 2.069038 | HK13: 1.245311 | HL13: 0.410668 | HM13: 0.65826 | HN13: 0.303499 | HO13: 0.651889 | HP13: 62.451324 | HQ13: 4.69835 | HR13: 1.384209 | HS13: 250.62261 | HT13: 63.231709 | HU13: 83.498926 | HV13: 0 | HW13: 0 | HX13: 0 | HY13: 0 | HZ13: 0 | IA13: 0 | IB13: 0 | IC13: 0 | ID13: 0 | IE13: 0 | IF13: 0 | IG13: 0 | IH13: 0 | II13: 0 | IJ13: 0 | IK13: 0 | IL13: 0 | IM13: 0 | IN13: 0 | IO13: 0 | IP13: 0 | IQ13: 0 | IR13: 0 | IS13: 0 | IT13: 0 | IU13: 0 | IV13: 0 | IW13: 0 | IX13: 0 | IY13: 0 | IZ13: 0 | JA13: 0 | JB13: 0 | JC13: 0 | JD13: 0 | JE13: 0 | JF13: 0 | JG13: 0 | JH13: 0 | JI13: 0 | JJ13: 0 | JK13: 0 | JL13: 0 | JM13: 0 | JN13: 0 | JO13: 0 | JP13: 0 | JQ13: 0 | JR13: 0 | JS13: 0 | JT13: 0 | JU13: 0 | JV13: 0 | JW13: 0 | JX13: 0 | JY13: 0 | JZ13: 0 | KA13: 0 | KB13: 0 | KC13: 0 | KD13: 0 | KE13: 0 | KF13: 0 | KG13: 0 | KH13: 0 | KI13: 0 | KJ13: 0 | KK13: 0 | KL13: 0 | KM13: 0 | KN13: 0 | KO13: 0 | KP13: 0 | KQ13: 0 | KR13: 0 | KS13: 0 | KT13: 0 | KU13: 0 | KV13: 0 | KW13: 0 | KX13: 0 | KY13: 0 | KZ13: 0 | LA13: 0 | LB13: 0 | LC13: 0 | LD13: 0 | LE13: 0 | LF13: 0 | LG13: 0 | LH13: 0 | LI13: 0 | LJ13: 0 | LK13: 0 | LL13: 0 | LM13: 0 | LN13: 0 | LO13: 0 | LP13: 0 | LQ13: 0 | LR13: 0 | LS13: 0 | LT13: 0 | LU13: 0 | LV13: 0 | LW13: 0 | LX13: 0 | LY13: 0 | LZ13: 0 | MA13: 0 | MB13: 0 | MC13: 0 | MD13: 0 | ME13: 0 | MF13: 0 | MG13: 0 | MH13: 0 | MI13: 0 | MJ13: 0 | MK13: 0 | ML13: 0 | MM13: 0 | MN13: 0 | MO13: 0 | MP13: 0 | MQ13: 0 | MR13: 0 | MS13: 0 | MT13: 0 | MU13: 0 | MV13: 0 | MW13: 0 | MX13: 0 | MY13: 0 | MZ13: 0 | NA13: 0 | NB13: 0 | NC13: 0 | ND13: 0 | NE13: 0 | NF13: 0 | NG13: 0 | NH13: 0 | NI13: 0 | NJ13: 0 | NK13: 0 | NL13: 0 | NM13: 0 | NN13: 0 | NO13: 0 | NP13: 0 | NQ13: 0 | NR13: 0 | NS13: 0 | NT13: 0 | NU13: 0 | NV13: 0 | NW13: 0 | NX13: 0 | NY13: 0 | NZ13: 0 | OA13: 0 | OB13: 0 | OC13: 0 | OD13: 0 | OE13: 0 | OF13: 0 | OG13: 0 | OH13: 0 | OI13: 0 | OJ13: 0 | OK13: 0 | OL13: 2245.3373 | OM13: 0 | ON13: 0 | OO13: 10.329127 | OP13: 761.11784 | OQ13: 13090.69
... A407: Total | B407: 1322.2471 | C407: 58343.858 | D407: 59380.548 | E407: 174574.18 | F407: 95812.718 | G407: 811.40912 | H407: 18656.49 | I407: 74629.801 | J407: 18226.784 | K407: 36667.675 | L407: 375.60548 | M407: 13090.691 | N407: 25558.781 | O407: 31939.082 | P407: 168899.91 | Q407: 1403941.2 | R407: 392755.18 | S407: 344402.5 | T407: 68470.08 | U407: 99192.089 | V407: 146060.49 | W407: 97294.052 | X407: 30285.509 | Y407: 41608.214 | Z407: 468697.83 | AA407: 161321.43 | AB407: 339096.22 | AC407: 519268.16 | AD407: 251151.44 | AE407: 134875.46 | AF407: 296208.1 | AG407: 851112.65 | AH407: 1428979.4 | AI407: 535532.2 | AJ407: 494152.23 | AK407: 213804.27 | AL407: 527173.6 | AM407: 772075.36 | AN407: 409937.77 | AO407: 2247381.3 | AP407: 885594.13 | AQ407: 1364025.1 | AR407: 1525120.7 | AS407: 523074.64 | AT407: 598983.45 | AU407: 17571.56 | AV407: 8214.2346 | AW407: 8688.8511 | AX407: 3881.6154 | AY407: 2201.8185 | AZ407: 8490.5644 | BA407: 705.35267 | BB407: 2918.3983 | BC407: 2994.0063 | BD407: 956.40693 | BE407: 2627.5026 | BF407: 1012.521 | BG407: 26687.591 | BH407: 7386.8485 | BI407: 122845.64 | BJ407: 360513.61 | BK407: 110587.83 | BL407: 352275.28 | BM407: 128130.06 | BN407: 286424.39 | BO407: 100228.12 | BP407: 267528.11 | BQ407: 309270.24 | BR407: 167684.8 | BS407: 53361.832 | BT407: 968071.68 | BU407: 210596.89 | BV407: 46132.669 | BW407: 140188.23 | BX407: 83492.982 | BY407: 0.000141 | BZ407: 310969.59 | CA407: 209306.53 | CB407: 336884.65 | CC407: 778652.11 | CD407: 287864.04 | CE407: 89704.246 | CF407: 92180.539 | CG407: 277531.87 | CH407: 383237.56 | CI407: 664384.21 | CJ407: 351425.02 | CK407: 55824.663 | CL407: 347555.13 | CM407: 391857.51 | CN407: 537336.29 | CO407: 2510403 | CP407: 650436.98 | CQ407: 1090637.2 | CR407: 708586.36 | CS407: 614973.31 | CT407: 520345.44 | CU407: 796750.49 | CV407: 457897.64 | CW407: 218945.96 | CX407: 2927459.2 | CY407: 1284631.2 | CZ407: 1623483 | DA407: 1102050.2 | DB407: 547094.72 | DC407: 1008981.7 | DD407: 1792322 | DE407: 4008372.2 | DF407: 4392348.8 | DG407: 1215293.5 | DH407: 2088770.2 | DI407: 1962775.7 | DJ407: 3134710.3 | DK407: 2049573.3 | DL407: 2634538 | DM407: 4485285.5 | DN407: 2241035.2 | DO407: 4068417.5 | DP407: 4109284.8 | DQ407: 1294943.7 | DR407: 1816769.1 | DS407: 729048.09 | DT407: 189842.8 | DU407: 730815.93 | DV407: 372976.78 | DW407: 81899.678 | DX407: 191224.74 | DY407: 62680.123 | DZ407: 66002.212 | EA407: 167409.46 | EB407: 56944.485 | EC407: 223539.9 | ED407: 30019.725 | EE407: 289044.75 | EF407: 1372261.6 | EG407: 12020239 | EH407: 11916073 | EI407: 4132491.4 | EJ407: 4620703.5 | EK407: 852469.73 | EL407: 1054302.6 | EM407: 1377661.6 | EN407: 5704406.8 | EO407: 4982922.6 | EP407: 1857298.5 | EQ407: 3428986.3 | ER407: 9741676.7 | ES407: 4076009.7 | ET407: 5889182.7 | EU407: 4369658.4 | EV407: 7356604.7 | EW407: 5341005 | EX407: 310969.6 | EY407: 209306.53 | EZ407: 336884.66 | FA407: 778657.09 | FB407: 286180.33 | FC407: 89701.563 | FD407: 92180.536 | FE407: 277531.87 | FF407: 383237.62 | FG407: 664384.23 | FH407: 351422.82 | FI407: 55789.037 | FJ407: 347335.95 | FK407: 391827.67 | FL407: 536734.16 | FM407: 2457615.4 | FN407: 587572.51 | FO407: 1087480.7 | FP407: 708586.34 | FQ407: 614975.1 | FR407: 520345.48 | FS407: 796859.94 | FT407: 457897.67 | FU407: 219272.92 | FV407: 2927535 | FW407: 1284631.2 | FX407: 1620535.4 | FY407: 1098454.6 | FZ407: 544783.23 | GA407: 1006602.1 | GB407: 1790144.8 | GC407: 3974368.7 | GD407: 4384197.9 | GE407: 1213416 | GF407: 2085210.3 | GG407: 1959936.6 | GH407: 3130025.9 | GI407: 2043767.6 | GJ407: 2630926.5 | GK407: 4470510.8 | GL407: 2234945.5 | GM407: 4059027.5 | GN407: 4103213.5 | GO407: 1295524.9 | GP407: 1811840 | GQ407: 729048.08 | GR407: 189842.81 | GS407: 730815.91 | GT407: 372976.81 | GU407: 81899.677 | GV407: 191224.74 | GW407: 62680.122 | GX407: 66002.214 | GY407: 167409.46 | GZ407: 56944.484 | HA407: 223539.9 | HB407: 30019.724 | HC407: 289044.74 | HD407: 1372261.6 | HE407: 12020239 | HF407: 11916073 | HG407: 4132491.4 | HH407: 4620703.5 | HI407: 852469.71 | HJ407: 1054302.5 | HK407: 1377661.6 | HL407: 5704406.7 | HM407: 4982922.4 | HN407: 1857298.5 | HO407: 3428986.2 | HP407: 9741676.7 | HQ407: 4076009.7 | HR407: 5889182.8 | HS407: 4369658.5 | HT407: 7356604.8 | HU407: 5341005 | HV407: 657001.31 | HW407: 15577614 | HX407: 15614601 | HY407: 30194318 | HZ407: 1052145.6 | IA407: 442127.4 | IB407: 239482.62 | IC407: 12.534127 | ID407: 981.89041 | IE407: 1496.0632 | IF407: 7314.4113 | IG407: 15698.865 | IH407: 5.064123 | II407: 746.06338 | IJ407: 2398.8781 | IK407: 252.31633 | IL407: 1508.2175 | IM407: 4.884514 | IN407: 705.29619 | IO407: 1765.3331 | IP407: 1715.579 | IQ407: 5883.8384 | IR407: 552.22634 | IS407: 27159.56 | IT407: 21840.396 | IU407: 5017.445 | IV407: 9834.5643 | IW407: 6441.8539 | IX407: 7116.1981 | IY407: 528.13124 | IZ407: 2289.7322 | JA407: 34508.19 | JB407: 82802.227 | JC407: 25427.942 | JD407: 96397.894 | JE407: 37187.149 | JF407: 6013.3676 | JG407: 11482.835 | JH407: 218310.09 | JI407: 70746.111 | JJ407: 50139.272 | JK407: 23351.935 | JL407: 9741.5388 | JM407: 10744.815 | JN407: 17794.975 | JO407: 15733.363 | JP407: 132119.94 | JQ407: 40566.171 | JR407: 64524.83 | JS407: 128452.05 | JT407: 27830.3 | JU407: 46968.625 | JV407: 3725.6544 | JW407: 2111.7846 | JX407: 1532.8331 | JY407: 600.20595 | JZ407: 467.70797 | KA407: 1461.8658 | KB407: 137.86759 | KC407: 836.31942 | KD407: 480.06372 | KE407: 207.06712 | KF407: 478.74534 | KG407: 227.86082 | KH407: 4829.8005 | KI407: 242.42102 | KJ407: 5311.4551 | KK407: 1012.1767 | KL407: 5594.5273 | KM407: 7991.545 | KN407: 2160.1144 | KO407: 10423.56 | KP407: 1212.7508 | KQ407: 9031.2666 | KR407: 2659.8164 | KS407: 8059.1666 | KT407: 2319.2559 | KU407: 26712.653 | KV407: 6699.2724 | KW407: 563.95893 | KX407: 2482.0413 | KY407: 2484.2171 | KZ407: 2e-06 | LA407: -4369.4398 | LB407: -2607.7536 | LC407: -1668.3804 | LD407: 3763.78 | LE407: 823.94985 | LF407: -1631.618 | LG407: -1021.9527 | LH407: -4417.0566 | LI407: 86.180839 | LJ407: 2528.6901 | LK407: 2764.866 | LL407: 308.62007 | LM407: 2729.3537 | LN407: 4079.3056 | LO407: 20816.767 | LP407: 310.95719 | LQ407: 34024.377 | LR407: 35914.723 | LS407: 42258.584 | LT407: 27611.115 | LU407: 15685.73 | LV407: 41042.231 | LW407: 4299.9699 | LX407: 8774.0348 | LY407: 101385.34 | LZ407: 396607.96 | MA407: 43956.699 | MB407: 41577.196 | MC407: 18507.089 | MD407: 30128.426 | ME407: 40804.833 | MF407: 789531.74 | MG407: 90663.089 | MH407: 38169.318 | MI407: 44589.982 | MJ407: 75599.247 | MK407: 50743.604 | ML407: 31055.889 | MM407: 58030.278 | MN407: 71450.9 | MO407: 39215.385 | MP407: 97450.755 | MQ407: 124239.54 | MR407: 21852.778 | MS407: 70972.796 | MT407: 79550.14 | MU407: 22447.46 | MV407: 43022.994 | MW407: 31775.829 | MX407: 12132.901 | MY407: 28519.136 | MZ407: 3506.4956 | NA407: 15785.918 | NB407: 10122.061 | NC407: 3218.0665 | ND407: 18100.848 | NE407: 6397.6926 | NF407: 12256.982 | NG407: 20006.638 | NH407: 406594.02 | NI407: 432803.15 | NJ407: 104490.73 | NK407: -4493.6513 | NL407: 537.32026 | NM407: 24289.91 | NN407: 191.66443 | NO407: 188378.28 | NP407: 66718.475 | NQ407: 76770.801 | NR407: 159066.91 | NS407: 256690.99 | NT407: 170551.28 | NU407: 3535.2221 | NV407: 36791.466 | NW407: 15062.147 | NX407: 79514.47 | NY407: -59068.437 | NZ407: 2651890.3 | OA407: 3376727.3 | OB407: 722896.3 | OC407: 24126.887 | OD407: 170293.73 | OE407: 365882.89 | OF407: 84082.957 | OG407: 170293.73 | OH407: 365882.89 | OI407: 84082.957 | OJ407: 20689148 | OK407: 67970677 | OL407: 45525064 | OM407: 1515111.1 | ON407: 7201769.3 | OO407: 13252910 | OP407: 19448145 | OQ407: 5.8658087e+08
